Workbook

Sheet 0. Assumptions
B1: GHANA GOLD BOARD (GOLDBOD)
B2: TRACEABILITY & ASSURANCE SYSTEM (TAS)
B3: PROJECT BUDGET — KEY ASSUMPTIONS
B4: REF: GR/GGB/TS/NCT/042/2026 | April 2026
B6: CORE FINANCIAL ASSUMPTIONS | F6: BUDGET ALLOCATION BY CATEGORY
B7: Assumption | C7: Value | D7: Notes | F7: Category | G7: Weight % | H7: Allocated USD
B8: Estimated Budget (USD) | C8: 11355000 | D8: ★ Change this to update the budget across all sheets | F8: 1. Personnel & HR Costs | G8: 0.28697572 | H8: =G8*$C$8 -> 3258609.3
B9: USD → GHS Exchange Rate | C9: 13 | D9: ★ Change this — GHS amounts recalculate automatically | F9: 2. Software Development | G9: 0.17483444 | H9: =G9*$C$8 -> 1985245
B10: Budget Date | C10: April 2026 | D10: Date of budget preparation | F10: 3. Blockchain Infrastructure | G10: 0.072406181 | H10: =G10*$C$8 -> 822172.19
B11: Contract Duration | C11: 18 Months | D11: 6 Mths Implementation + 12 Mths Stabilisation | F11: 4. Cloud & Hosting (18 months) | G11: 0.047682119 | H11: =G11*$C$8 -> 541430.46
B12: Procurement Method | C12: QCBS | D12: Quality & Cost Based Selection | F12: 5. Software Licenses & Tools | G12: 0.027373068 | H12: =G12*$C$8 -> 310821.19
B13: Primary Currency | C13: USD | D13: GHS equivalent calculated from rate above | F13: 6. Hardware & Field Equipment | G13: 0.06004415 | H13: =G13*$C$8 -> 681801.32
B14: Contingency Rate | C14: 10% | D14: Applied per category; PMO approval to release | F14: 7. Systems Integration (6 agencies) | G14: 0.056512141 | H14: =G14*$C$8 -> 641695.36
B15: FX Variance Buffer | C15: ±5% | D15: Built into contingency for exchange rate movements | F15: 8. Testing & Quality Assurance | G15: 0.025607064 | H15: =G15*$C$8 -> 290768.21
B16: Project Start Date | C16: May 2026 | D16: Indicative — subject to contract signing | F16: 9. Training & Capacity Building | G16: 0.037086093 | H16: =G16*$C$8 -> 421112.58
F17: 10. Compliance & Legal | G17: 0.01589404 | H17: =G17*$C$8 -> 180476.82
B18: GENERAL PROJECT ASSUMPTIONS | F18: 11. Project Management & PMO | G18: 0.033554084 | H18: =G18*$C$8 -> 381006.62
B19: 1. All costs are in USD unless stated otherwise. GHS equivalent rates are indicative only. | F19: 12. Pilot Programme | G19: 0.015452539 | H19: =G19*$C$8 -> 175463.58
B20: 2. Exchange rate locked at contract signing. FX fluctuations covered by 5% contingency buffer. | F20: 13. National Deployment | G20: 0.021192053 | H20: =G20*$C$8 -> 240635.76
B21: 3. Personnel rates are blended for onshore/offshore delivery mix. | F21: 14. Stabilisation & Support (12 mths) | G21: 0.066225166 | H21: =G21*$C$8 -> 751986.75
B22: 4. Software licence costs assume 18-month project duration with annual renewal option. | F22: 15. Documentation & Deliverables | G22: 0.008388521 | H22: =G22*$C$8 -> 95251.656
B23: 5. Hardware procurement subject to GoldBod import duty and procurement regulations. | F23: 16. Contingency (10%) | G23: 0.050772627 | H23: =G23*$C$8 -> 576523.18
B24: 6. Contingency (10%) requires written PMO approval for release; unspent amounts returned to GoldBod. | F24: TOTAL | G24: =SUM(G8:G23) -> 1 | H24: =SUM(H8:H23) -> 11355000
B25: 7. All milestones subject to formal sign-off before subsequent tranche is released.
B26: 8. Training costs assume train-the-trainer model for national rollout efficiency.
B29: Colour Legend: Blue text = User input | Black text = Formula | Yellow background = Key assumption to review | Green text = Cross-sheet link

Sheet Budget-Summary
B2: GHANA GOLD BOARD (GOLDBOD)
B3: TRACEABILITY & ASSURANCE SYSTEM (TAS)
B4: PROJECT BUDGET SUMMARY
B5: REF: GR/GGB/TS/NCT/042/2026 | April 2026
B7: Estimated Budget: | C7: ='0. Assumptions'!C8 -> 11355000 | E7: Exchange Rate: | F7: ='0. Assumptions'!C9 -> 13 | G7: GHS/USD
B9: # | C9: Cost Category | D9: Description | E9: USD Amount | F9: GHS Equivalent | G9: % of Total
B10: 1 | C10: ='0. Assumptions'!F8 -> 1. Personnel & HR Costs | D10: Core team: developers, architects, QA, PMs, compliance officers, support staff. Includes statutory oncosts (SSNIT, Tier 2, medical). | E10: ='0. Assumptions'!H8 -> 3258609.3 | F10: =E10*'0. Assumptions'!$C$9 -> 42361921 | G10: =E10/'0. Assumptions'!$C$8 -> 0.28697572
B11: 2 | C11: ='0. Assumptions'!F9 -> 2. Software Development | D11: Full-stack blockchain platform: smart contracts, APIs, mobile apps, web dashboards, admin portal. | E11: ='0. Assumptions'!H9 -> 1985245 | F11: =E11*'0. Assumptions'!$C$9 -> 25808185 | G11: =E11/'0. Assumptions'!$C$8 -> 0.17483444
B12: 3 | C12: ='0. Assumptions'!F10 -> 3. Blockchain Infrastructure | D12: Hyperledger Fabric nodes, consensus infrastructure, HSMs, certificate authority setup. | E12: ='0. Assumptions'!H10 -> 822172.19 | F12: =E12*'0. Assumptions'!$C$9 -> 10688238 | G12: =E12/'0. Assumptions'!$C$8 -> 0.072406181
B13: 4 | C13: ='0. Assumptions'!F11 -> 4. Cloud & Hosting (18 months) | D13: AWS/Azure hosting, CDN, DR environment, monitoring & backup services for 18 months. | E13: ='0. Assumptions'!H11 -> 541430.46 | F13: =E13*'0. Assumptions'!$C$9 -> 7038596 | G13: =E13/'0. Assumptions'!$C$8 -> 0.047682119
B14: 5 | C14: ='0. Assumptions'!F12 -> 5. Software Licenses & Tools | D14: Development tools, CI/CD pipelines, security scanners, design & collaboration platforms. | E14: ='0. Assumptions'!H12 -> 310821.19 | F14: =E14*'0. Assumptions'!$C$9 -> 4040675.5 | G14: =E14/'0. Assumptions'!$C$8 -> 0.027373068
B15: 6 | C15: ='0. Assumptions'!F13 -> 6. Hardware & Field Equipment | D15: Tablets, GPS devices, digital scales, biometric scanners, ruggedised field kits for regional offices. | E15: ='0. Assumptions'!H13 -> 681801.32 | F15: =E15*'0. Assumptions'!$C$9 -> 8863417.2 | G15: =E15/'0. Assumptions'!$C$8 -> 0.06004415
B16: 7 | C16: ='0. Assumptions'!F14 -> 7. Systems Integration (6 agencies) | D16: API integration with 6 government agencies: GRA, PMMC, Minerals Commission, NIA, FIC, Bank of Ghana. | E16: ='0. Assumptions'!H14 -> 641695.36 | F16: =E16*'0. Assumptions'!$C$9 -> 8342039.7 | G16: =E16/'0. Assumptions'!$C$8 -> 0.056512141
B17: 8 | C17: ='0. Assumptions'!F15 -> 8. Testing & Quality Assurance | D17: Functional, regression, load, security (penetration) testing and UAT coordination. | E17: ='0. Assumptions'!H15 -> 290768.21 | F17: =E17*'0. Assumptions'!$C$9 -> 3779986.8 | G17: =E17/'0. Assumptions'!$C$8 -> 0.025607064
B18: 9 | C18: ='0. Assumptions'!F16 -> 9. Training & Capacity Building | D18: Train-the-trainer programme, e-learning platform, regional workshops, user manuals & change management. | E18: ='0. Assumptions'!H16 -> 421112.58 | F18: =E18*'0. Assumptions'!$C$9 -> 5474463.6 | G18: =E18/'0. Assumptions'!$C$8 -> 0.037086093
B19: 10 | C19: ='0. Assumptions'!F17 -> 10. Compliance & Legal | D19: Data protection (Act 843), AML/CFT compliance, legal advisory, regulatory submissions. | E19: ='0. Assumptions'!H17 -> 180476.82 | F19: =E19*'0. Assumptions'!$C$9 -> 2346198.7 | G19: =E19/'0. Assumptions'!$C$8 -> 0.01589404
B20: 11 | C20: ='0. Assumptions'!F18 -> 11. Project Management & PMO | D20: PMO office, project & financial management, governance, reporting, steering committee support. | E20: ='0. Assumptions'!H18 -> 381006.62 | F20: =E20*'0. Assumptions'!$C$9 -> 4953086.1 | G20: =E20/'0. Assumptions'!$C$8 -> 0.033554084
B21: 12 | C21: ='0. Assumptions'!F19 -> 12. Pilot Programme | D21: Pilot deployment in 2 selected regions with controlled rollout and feedback loop. | E21: ='0. Assumptions'!H19 -> 175463.58 | F21: =E21*'0. Assumptions'!$C$9 -> 2281026.5 | G21: =E21/'0. Assumptions'!$C$8 -> 0.015452539
... B25: 16 | C25: ='0. Assumptions'!F23 -> 16. Contingency (10%) | D25: 10% contingency on direct costs. Released only with written PMO approval. Unspent funds returned. | E25: ='0. Assumptions'!H23 -> 576523.18 | F25: =E25*'0. Assumptions'!$C$9 -> 7494801.3 | G25: =E25/'0. Assumptions'!$C$8 -> 0.050772627
C26: TOTAL PROJECT BUDGET | E26: =SUM(E10:E25) -> 11355000 | F26: =SUM(F10:F25) -> 147615000 | G26: =SUM(G10:G25) -> 1
B28: Notes:
B29: 1. All amounts in USD. GHS equivalents are indicative at the exchange rate shown above.
B30: 2. Budget allocations are proportional — changing the Estimated Budget automatically recalculates all line items.
B31: 3. Contingency (10%) requires written PMO approval for release. Unspent amounts returned to GoldBod.
B32: 4. Exchange rate locked at contract signing. ±5% FX variance buffer built into contingency.
B33: 5. Contract duration: 18 months (6 months implementation + 12 months stabilisation & support).
B35: Prepared: April 2026 | Procurement Method: QCBS (Quality & Cost Based Selection)

Sheet Cover
A1: GHANA GOLD BOARD (GOLDBOD) TRACEABILITY & ASSURANCE SYSTEM (TAS) PROJECT BUDGET — REF: GR/GGB/TS/NCT/042/2026
B5: Contract Duration: | C5: 18 Months (6 Mths Implementation + 12 Mths Stabilisation)
B6: Procurement Method: | C6: Quality & Cost Based Selection (QCBS)
B7: Currency (Primary): | C7: ="USD (with GHS equivalent at "&TEXT('0. Assumptions'!C9,"0.00")&" USD/GHS)" -> USD (with GHS equivalent at 13.00 USD/GHS)
B8: Exchange Rate: | C8: ="1 USD = "&TEXT('0. Assumptions'!C9,"0.00")&" GHS (Indicative – April 2026)" -> 1 USD = 13.00 GHS (Indicative – April 2026)
B9: Budget Date: | C9: April 2026
B10: Regulatory Framework: | C10: Public Procurement Act, 2003 (Act 663 as amended)
A12: EXECUTIVE BUDGET SUMMARY
B13: Cost Category | C13: USD Amount | D13: GHS Amount | E13: % of Total
B14: 1. Personnel & HR Costs | C14: ='0. Assumptions'!H8 -> 3258609.3 | D14: =C14*'0. Assumptions'!$C$9 -> 42361921 | E14: =C14/C30 -> 0.28697572
B15: 2. Software Development | C15: ='0. Assumptions'!H9 -> 1985245 | D15: =C15*'0. Assumptions'!$C$9 -> 25808185 | E15: =C15/C30 -> 0.17483444
B16: 3. Blockchain Infrastructure | C16: ='0. Assumptions'!H10 -> 822172.19 | D16: =C16*'0. Assumptions'!$C$9 -> 10688238 | E16: =C16/C30 -> 0.072406181
B17: 4. Cloud & Hosting (18 months) | C17: ='0. Assumptions'!H11 -> 541430.46 | D17: =C17*'0. Assumptions'!$C$9 -> 7038596 | E17: =C17/C30 -> 0.047682119
B18: 5. Software Licenses & Tools | C18: ='0. Assumptions'!H12 -> 310821.19 | D18: =C18*'0. Assumptions'!$C$9 -> 4040675.5 | E18: =C18/C30 -> 0.027373068
B19: 6. Hardware & Field Equipment | C19: ='0. Assumptions'!H13 -> 681801.32 | D19: =C19*'0. Assumptions'!$C$9 -> 8863417.2 | E19: =C19/C30 -> 0.06004415
B20: 7. Systems Integration (6 agencies) | C20: ='0. Assumptions'!H14 -> 641695.36 | D20: =C20*'0. Assumptions'!$C$9 -> 8342039.7 | E20: =C20/C30 -> 0.056512141
B21: 8. Testing & Quality Assurance | C21: ='0. Assumptions'!H15 -> 290768.21 | D21: =C21*'0. Assumptions'!$C$9 -> 3779986.8 | E21: =C21/C30 -> 0.025607064
B22: 9. Training & Capacity Building | C22: ='0. Assumptions'!H16 -> 421112.58 | D22: =C22*'0. Assumptions'!$C$9 -> 5474463.6 | E22: =C22/C30 -> 0.037086093
B23: 10. Compliance & Legal | C23: ='0. Assumptions'!H17 -> 180476.82 | D23: =C23*'0. Assumptions'!$C$9 -> 2346198.7 | E23: =C23/C30 -> 0.01589404
B24: 11. Project Management & PMO | C24: ='0. Assumptions'!H18 -> 381006.62 | D24: =C24*'0. Assumptions'!$C$9 -> 4953086.1 | E24: =C24/C30 -> 0.033554084
B25: 12. Pilot Programme | C25: ='0. Assumptions'!H19 -> 175463.58 | D25: =C25*'0. Assumptions'!$C$9 -> 2281026.5 | E25: =C25/C30 -> 0.015452539
B26: 13. National Deployment | C26: ='0. Assumptions'!H20 -> 240635.76 | D26: =C26*'0. Assumptions'!$C$9 -> 3128264.9 | E26: =C26/C30 -> 0.021192053
B27: 14. Stabilisation & Support (12 mths) | C27: ='0. Assumptions'!H21 -> 751986.75 | D27: =C27*'0. Assumptions'!$C$9 -> 9775827.8 | E27: =C27/C30 -> 0.066225166
B28: 15. Documentation & Deliverables | C28: ='0. Assumptions'!H22 -> 95251.656 | D28: =C28*'0. Assumptions'!$C$9 -> 1238271.5 | E28: =C28/C30 -> 0.008388521
B29: 16. Contingency (10%) | C29: ='0. Assumptions'!H23 -> 576523.18 | D29: =C29*'0. Assumptions'!$C$9 -> 7494801.3 | E29: =C29/C30 -> 0.050772627
B30: TOTAL PROJECT BUDGET | C30: =SUM(C14:C29) -> 11355000 | D30: =SUM(D14:D29) -> 147615000 | E30: 100.0%

Sheet 1. Personnel Costs
A1: SECTION 1 — PERSONNEL & HR COSTS
B3: Role / Position | C3: Monthly Rate (USD) | D3: # Staff | E3: Months | F3: Total USD | G3: Total GHS
A4: A. TECHNICAL DEVELOPMENT TEAM (Implementation Phase)
B5: Blockchain Architect / Lead Developer | C5: 12000 | D5: 1 | E5: 8 | F5: =C5*D5*E5 -> 96000 | G5: =F5*'0. Assumptions'!$C$9 -> 1248000
B6: Senior Backend Developer (Blockchain) | C6: 9000 | D6: 2 | E6: 6 | F6: =C6*D6*E6 -> 108000 | G6: =F6*'0. Assumptions'!$C$9 -> 1404000
B7: Senior Backend Developer (API/Core) | C7: 8500 | D7: 2 | E7: 6 | F7: =C7*D7*E7 -> 102000 | G7: =F7*'0. Assumptions'!$C$9 -> 1326000
B8: Frontend Developer (Web Portal) | C8: 7000 | D8: 2 | E8: 6 | F8: =C8*D8*E8 -> 84000 | G8: =F8*'0. Assumptions'!$C$9 -> 1092000
B9: Mobile App Developer (Android/iOS) | C9: 7500 | D9: 2 | E9: 6 | F9: =C9*D9*E9 -> 90000 | G9: =F9*'0. Assumptions'!$C$9 -> 1170000
B10: Smart Contract Developer | C10: 9500 | D10: 1 | E10: 5 | F10: =C10*D10*E10 -> 47500 | G10: =F10*'0. Assumptions'!$C$9 -> 617500
B11: DevOps / Cloud Engineer | C11: 8000 | D11: 2 | E11: 7 | F11: =C11*D11*E11 -> 112000 | G11: =F11*'0. Assumptions'!$C$9 -> 1456000
B12: Database Administrator | C12: 7000 | D12: 1 | E12: 6 | F12: =C12*D12*E12 -> 42000 | G12: =F12*'0. Assumptions'!$C$9 -> 546000
B13: Cybersecurity / Security Engineer | C13: 8500 | D13: 1 | E13: 6 | F13: =C13*D13*E13 -> 51000 | G13: =F13*'0. Assumptions'!$C$9 -> 663000
B14: Sub-Total: A. TECHNICAL DEVELOPMENT TEAM (Implementation Phase) | F14: =SUM(F5:F13) -> 732500 | G14: =F14*'0. Assumptions'!$C$9 -> 9522500
A15: B. QA & TESTING TEAM
B16: QA Lead / Test Manager | C16: 7500 | D16: 1 | E16: 5 | F16: =C16*D16*E16 -> 37500 | G16: =F16*'0. Assumptions'!$C$9 -> 487500
B17: QA Engineer / Functional Tester | C17: 5500 | D17: 3 | E17: 5 | F17: =C17*D17*E17 -> 82500 | G17: =F17*'0. Assumptions'!$C$9 -> 1072500
B18: Test Automation Engineer | C18: 6500 | D18: 1 | E18: 4 | F18: =C18*D18*E18 -> 26000 | G18: =F18*'0. Assumptions'!$C$9 -> 338000
B19: Penetration Tester / Security Auditor | C19: 8000 | D19: 1 | E19: 2 | F19: =C19*D19*E19 -> 16000 | G19: =F19*'0. Assumptions'!$C$9 -> 208000
B20: Sub-Total: B. QA & TESTING TEAM | F20: =SUM(F16:F19) -> 162000 | G20: =F20*'0. Assumptions'!$C$9 -> 2106000
A21: C. UI/UX & BUSINESS ANALYSIS
B22: Lead UI/UX Designer | C22: 7000 | D22: 1 | E22: 5 | F22: =C22*D22*E22 -> 35000 | G22: =F22*'0. Assumptions'!$C$9 -> 455000
B23: Junior UI/UX Designer | C23: 4500 | D23: 1 | E23: 4 | F23: =C23*D23*E23 -> 18000 | G23: =F23*'0. Assumptions'!$C$9 -> 234000
B24: Business Analyst (Gold Supply Chain) | C24: 7000 | D24: 2 | E24: 6 | F24: =C24*D24*E24 -> 84000 | G24: =F24*'0. Assumptions'!$C$9 -> 1092000
B25: Requirements Engineer | C25: 6000 | D25: 1 | E25: 4 | F25: =C25*D25*E25 -> 24000 | G25: =F25*'0. Assumptions'!$C$9 -> 312000
B26: Domain Expert – AML/CFT Compliance | C26: 9000 | D26: 1 | E26: 4 | F26: =C26*D26*E26 -> 36000 | G26: =F26*'0. Assumptions'!$C$9 -> 468000
B27: Sub-Total: C. UI/UX & BUSINESS ANALYSIS | F27: =SUM(F22:F26) -> 197000 | G27: =F27*'0. Assumptions'!$C$9 -> 2561000
A28: D. INTEGRATION & DATA SPECIALISTS
B29: Integration Architect | C29: 9000 | D29: 1 | E29: 5 | F29: =C29*D29*E29 -> 45000 | G29: =F29*'0. Assumptions'!$C$9 -> 585000
B30: API Developer / Integration Engineer | C30: 7000 | D30: 2 | E30: 5 | F30: =C30*D30*E30 -> 70000 | G30: =F30*'0. Assumptions'!$C$9 -> 910000
B31: Data Engineer | C31: 7000 | D31: 1 | E31: 6 | F31: =C31*D31*E31 -> 42000 | G31: =F31*'0. Assumptions'!$C$9 -> 546000
B32: Data Scientist / Analytics Specialist | C32: 7500 | D32: 1 | E32: 4 | F32: =C32*D32*E32 -> 30000 | G32: =F32*'0. Assumptions'!$C$9 -> 390000
B33: Sub-Total: D. INTEGRATION & DATA SPECIALISTS | F33: =SUM(F29:F32) -> 187000 | G33: =F33*'0. Assumptions'!$C$9 -> 2431000
A34: E. TRAINING & CHANGE MANAGEMENT
B35: Training Programme Manager | C35: 6500 | D35: 1 | E35: 6 | F35: =C35*D35*E35 -> 39000 | G35: =F35*'0. Assumptions'!$C$9 -> 507000
B36: Field Training Specialist (Regional) | C36: 4500 | D36: 4 | E36: 4 | F36: =C36*D36*E36 -> 72000 | G36: =F36*'0. Assumptions'!$C$9 -> 936000
B37: Change Management Consultant | C37: 8000 | D37: 1 | E37: 4 | F37: =C37*D37*E37 -> 32000 | G37: =F37*'0. Assumptions'!$C$9 -> 416000
B38: Technical Writer / Documentation Spec. | C38: 5000 | D38: 1 | E38: 6 | F38: =C38*D38*E38 -> 30000 | G38: =F38*'0. Assumptions'!$C$9 -> 390000
B39: E-Learning / LMS Developer | C39: 5500 | D39: 1 | E39: 3 | F39: =C39*D39*E39 -> 16500 | G39: =F39*'0. Assumptions'!$C$9 -> 214500
B40: Sub-Total: E. TRAINING & CHANGE MANAGEMENT | F40: =SUM(F35:F39) -> 189500 | G40: =F40*'0. Assumptions'!$C$9 -> 2463500
A41: F. PROJECT MANAGEMENT
B42: Project Manager | C42: 10000 | D42: 1 | E42: 18 | F42: =C42*D42*E42 -> 180000 | G42: =F42*'0. Assumptions'!$C$9 -> 2340000
B43: Deputy Project Manager | C43: 7500 | D43: 1 | E43: 18 | F43: =C43*D43*E43 -> 135000 | G43: =F43*'0. Assumptions'!$C$9 -> 1755000
B44: Project Coordinator | C44: 5000 | D44: 1 | E44: 18 | F44: =C44*D44*E44 -> 90000 | G44: =F44*'0. Assumptions'!$C$9 -> 1170000
B45: Project Administrator | C45: 3500 | D45: 1 | E45: 18 | F45: =C45*D45*E45 -> 63000 | G45: =F45*'0. Assumptions'!$C$9 -> 819000
B46: Financial Manager / Controller | C46: 6500 | D46: 1 | E46: 18 | F46: =C46*D46*E46 -> 117000 | G46: =F46*'0. Assumptions'!$C$9 -> 1521000
B47: Sub-Total: F. PROJECT MANAGEMENT | F47: =SUM(F42:F46) -> 585000 | G47: =F47*'0. Assumptions'!$C$9 -> 7605000
A48: G. COMPLIANCE & LEGAL
B49: Compliance Officer – Data Protection (Act 843) | C49: 7000 | D49: 1 | E49: 12 | F49: =C49*D49*E49 -> 84000 | G49: =F49*'0. Assumptions'!$C$9 -> 1092000
B50: AML/CFT Compliance Specialist | C50: 8000 | D50: 1 | E50: 8 | F50: =C50*D50*E50 -> 64000 | G50: =F50*'0. Assumptions'!$C$9 -> 832000
B51: Legal Advisor (Contract / IP / Regulatory) | C51: 8500 | D51: 1 | E51: 6 | F51: =C51*D51*E51 -> 51000 | G51: =F51*'0. Assumptions'!$C$9 -> 663000
B52: Sub-Total: G. COMPLIANCE & LEGAL | F52: =SUM(F49:F51) -> 199000 | G52: =F52*'0. Assumptions'!$C$9 -> 2587000
A53: H. STABILISATION & SUPPORT TEAM (Months 7–18)
B54: Technical Support Engineer (L2/L3) | C54: 6000 | D54: 3 | E54: 12 | F54: =C54*D54*E54 -> 216000 | G54: =F54*'0. Assumptions'!$C$9 -> 2808000
B55: System Administrator | C55: 5500 | D55: 2 | E55: 12 | F55: =C55*D55*E55 -> 132000 | G55: =F55*'0. Assumptions'!$C$9 -> 1716000
B56: Help Desk / L1 Support Agent | C56: 3000 | D56: 4 | E56: 12 | F56: =C56*D56*E56 -> 144000 | G56: =F56*'0. Assumptions'!$C$9 -> 1872000
B57: Blockchain Node Operator | C57: 6000 | D57: 1 | E57: 12 | F57: =C57*D57*E57 -> 72000 | G57: =F57*'0. Assumptions'!$C$9 -> 936000
B58: Sub-Total: H. STABILISATION & SUPPORT TEAM (Months 7–18) | F58: =SUM(F54:F57) -> 564000 | G58: =F58*'0. Assumptions'!$C$9 -> 7332000
A59: I. GHANA EMPLOYMENT ONCOSTS (Statutory)
B60: SSNIT – Employer Contribution (13% of basic salary) | F60: 245000 | G60: =F60*'0. Assumptions'!$C$9 -> 3185000
B61: Tier 2 Pension Contribution (5% of basic salary) | F61: 94000 | G61: =F61*'0. Assumptions'!$C$9 -> 1222000
B62: Staff Medical Insurance Allowance (est. $200/person/month, ~50 staff) | F62: 108000 | G62: =F62*'0. Assumptions'!$C$9 -> 1404000
B63: Professional Indemnity & Project Insurance | F63: 65000 | G63: =F63*'0. Assumptions'!$C$9 -> 845000
B64: Staff Welfare & Team Activities | F64: 28000 | G64: =F64*'0. Assumptions'!$C$9 -> 364000
B65: TOTAL PERSONNEL & HR COSTS | F65: =F14+F20+F27+F33+F40+F47+F52+F58+SUM(F60:F64) -> 3356000 | G65: =F65*'0. Assumptions'!$C$9 -> 43628000
B67: ="NOTE: Blue text = hardcoded inputs (rates, headcount, duration). Black text = formulas. Green text = GHS conversions at 1 USD = "&TEXT('0. Assumptions'!C9,"0.00")&" GHS (indicative)." -> NOTE: Blue text = hardcoded inputs (rates, headcount, duration). Black text = formulas. Green text = GHS conversions at 1 USD = 13.00 GHS (indicative).

Sheet 2. Software Development
A1: SECTION 2 — SOFTWARE DEVELOPMENT & PROJECT IMPLEMENTATION
B3: Development Activity / Deliverable | C3: Estimated Cost (USD) | D3: Estimated Cost (GHS)
A4: PHASE 1: DESIGN & REQUIREMENTS (Months 1–2)
B5: System Architecture Design & Technical Blueprint | C5: 85000 | D5: =C5*'0. Assumptions'!$C$9 -> 1105000
B6: Blockchain Network Architecture Specification | C6: 55000 | D6: =C6*'0. Assumptions'!$C$9 -> 715000
B7: UX Research & Wireframing (all user roles) | C7: 45000 | D7: =C7*'0. Assumptions'!$C$9 -> 585000
B8: Stakeholder Workshops & Requirements Workshops (3 rounds) | C8: 30000 | D8: =C8*'0. Assumptions'!$C$9 -> 390000
B9: Data Model & Database Schema Design | C9: 25000 | D9: =C9*'0. Assumptions'!$C$9 -> 325000
B10: Security Architecture & Threat Modelling | C10: 35000 | D10: =C10*'0. Assumptions'!$C$9 -> 455000
B11: Integration Architecture & API Design (6 agencies) | C11: 40000 | D11: =C11*'0. Assumptions'!$C$9 -> 520000
B12: Sub-Total: PHASE 1: DESIGN & REQUIREMENTS (Months 1–2) | C12: =SUM(C5:C11) -> 315000 | D12: =C12*'0. Assumptions'!$C$9 -> 4095000
A13: PHASE 2: CORE PLATFORM DEVELOPMENT (Months 2–4)
B14: Blockchain Network Setup – Hyperledger Fabric (permissioned) | C14: 120000 | D14: =C14*'0. Assumptions'!$C$9 -> 1560000
B15: Smart Contract Development & Auditing | C15: 95000 | D15: =C15*'0. Assumptions'!$C$9 -> 1235000
B16: Core Backend API Development (Node.js / Python) | C16: 150000 | D16: =C16*'0. Assumptions'!$C$9 -> 1950000
B17: Supply Chain Transaction Module | C17: 80000 | D17: =C17*'0. Assumptions'!$C$9 -> 1040000
B18: KYC/AML Module (identity & compliance) | C18: 70000 | D18: =C18*'0. Assumptions'!$C$9 -> 910000
B19: Assay & Weight Recording Module | C19: 55000 | D19: =C19*'0. Assumptions'!$C$9 -> 715000
B20: Chain-of-Custody / Provenance Ledger Module | C20: 85000 | D20: =C20*'0. Assumptions'!$C$9 -> 1105000
B21: Admin Dashboard & Analytics Portal (Web) | C21: 75000 | D21: =C21*'0. Assumptions'!$C$9 -> 975000
B22: Reporting & BI Module (OECD/LBMA/FIC reports) | C22: 60000 | D22: =C22*'0. Assumptions'!$C$9 -> 780000
B23: Notification Engine (SMS, email, push) | C23: 30000 | D23: =C23*'0. Assumptions'!$C$9 -> 390000
B24: Document Management & IPFS Off-chain Storage | C24: 40000 | D24: =C24*'0. Assumptions'!$C$9 -> 520000
B25: Role-Based Access Control & Permissioning Engine | C25: 35000 | D25: =C25*'0. Assumptions'!$C$9 -> 455000
B26: Sub-Total: PHASE 2: CORE PLATFORM DEVELOPMENT (Months 2–4) | C26: =SUM(C14:C25) -> 895000 | D26: =C26*'0. Assumptions'!$C$9 -> 11635000
A27: PHASE 3: MOBILE APPLICATION DEVELOPMENT
B28: Android Mobile App – Field Officers & Miners | C28: 80000 | D28: =C28*'0. Assumptions'!$C$9 -> 1040000
B29: iOS Mobile App – Field Officers | C29: 65000 | D29: =C29*'0. Assumptions'!$C$9 -> 845000
B30: Offline Mode & Data Sync Engine | C30: 45000 | D30: =C30*'0. Assumptions'!$C$9 -> 585000
B31: QR/NFC/RFID Scanner Integration | C31: 25000 | D31: =C31*'0. Assumptions'!$C$9 -> 325000
B32: GPS & Geolocation Integration | C32: 20000 | D32: =C32*'0. Assumptions'!$C$9 -> 260000
B33: Digital Signature / e-Certificate Module | C33: 30000 | D33: =C33*'0. Assumptions'!$C$9 -> 390000
B34: Photo Capture & Evidence Upload Module | C34: 20000 | D34: =C34*'0. Assumptions'!$C$9 -> 260000
B35: Sub-Total: PHASE 3: MOBILE APPLICATION DEVELOPMENT | C35: =SUM(C28:C34) -> 285000 | D35: =C35*'0. Assumptions'!$C$9 -> 3705000
A36: PHASE 4: DEVOPS, CI/CD & INFRASTRUCTURE-AS-CODE
B37: CI/CD Pipeline Setup (GitHub Actions / Jenkins) | C37: 25000 | D37: =C37*'0. Assumptions'!$C$9 -> 325000
B38: Docker / Kubernetes Container Orchestration | C38: 35000 | D38: =C38*'0. Assumptions'!$C$9 -> 455000
B39: Infrastructure-as-Code (Terraform / Ansible) | C39: 20000 | D39: =C39*'0. Assumptions'!$C$9 -> 260000
B40: Environment Setup: Dev / Staging / UAT / Production | C40: 30000 | D40: =C40*'0. Assumptions'!$C$9 -> 390000
B41: Automated Deployment & Rollback Procedures | C41: 15000 | D41: =C41*'0. Assumptions'!$C$9 -> 195000
B42: Performance Monitoring & Alerting Setup | C42: 18000 | D42: =C42*'0. Assumptions'!$C$9 -> 234000
B43: Sub-Total: PHASE 4: DEVOPS, CI/CD & INFRASTRUCTURE-AS-CODE | C43: =SUM(C37:C42) -> 143000 | D43: =C43*'0. Assumptions'!$C$9 -> 1859000
A44: PHASE 5: PILOT DEVELOPMENT (Months 5–6)
B45: Pilot Configuration for 2–3 Mine Sites | C45: 40000 | D45: =C45*'0. Assumptions'!$C$9 -> 520000
B46: Pilot-Specific Customisation & Field Adaptation | C46: 25000 | D46: =C46*'0. Assumptions'!$C$9 -> 325000
B47: Iterative Bug Fixes & Field Feedback Integration | C47: 30000 | D47: =C47*'0. Assumptions'!$C$9 -> 390000
B48: Load & Stress Testing for Pilot Volume | C48: 18000 | D48: =C48*'0. Assumptions'!$C$9 -> 234000
B49: Sub-Total: PHASE 5: PILOT DEVELOPMENT (Months 5–6) | C49: =SUM(C45:C48) -> 113000 | D49: =C49*'0. Assumptions'!$C$9 -> 1469000
A50: PHASE 6: NATIONAL DEPLOYMENT & GO-LIVE
B51: National Rollout Configuration & Data Migration | C51: 45000 | D51: =C51*'0. Assumptions'!$C$9 -> 585000
B52: Go-Live Support (War Room, 24/7 for 2 weeks) | C52: 22000 | D52: =C52*'0. Assumptions'!$C$9 -> 286000
B53: Post Go-Live Hotfix Sprint (first 4 weeks) | C53: 25000 | D53: =C53*'0. Assumptions'!$C$9 -> 325000
B54: Sub-Total: PHASE 6: NATIONAL DEPLOYMENT & GO-LIVE | C54: =SUM(C51:C53) -> 92000 | D54: =C54*'0. Assumptions'!$C$9 -> 1196000
A55: ONGOING DEVELOPMENT – STABILISATION (Months 7–18)
B56: Quarterly Feature Enhancements (4 sprints × 3 months) | C56: 80000 | D56: =C56*'0. Assumptions'!$C$9 -> 1040000
B57: Bug Fix & Patch Management | C57: 40000 | D57: =C57*'0. Assumptions'!$C$9 -> 520000
B58: Performance Tuning & Optimisation | C58: 25000 | D58: =C58*'0. Assumptions'!$C$9 -> 325000
B59: Regulatory & Compliance Updates | C59: 20000 | D59: =C59*'0. Assumptions'!$C$9 -> 260000
B60: API Version Upgrades (agency systems) | C60: 15000 | D60: =C60*'0. Assumptions'!$C$9 -> 195000
B61: Sub-Total: ONGOING DEVELOPMENT – STABILISATION (Months 7–18) | C61: =SUM(C56:C60) -> 180000 | D61: =C61*'0. Assumptions'!$C$9 -> 2340000
B62: TOTAL SOFTWARE DEVELOPMENT | C62: =C12+C26+C35+C43+C49+C54+C61 -> 2023000 | D62: =C62*'0. Assumptions'!$C$9 -> 26299000

Sheet 3. Infrastructure & Licenses
A1: SECTION 3 — BLOCKCHAIN INFRASTRUCTURE, CLOUD & SOFTWARE LICENSES
B3: Item | C3: Unit Cost (USD) | D3: Qty / Months | E3: Total USD | F3: Total GHS
A4: BLOCKCHAIN INFRASTRUCTURE
B5: Hyperledger Fabric Platform Support & SLA | C5: 15000 | D5: 18 | E5: =C5*D5 -> 270000 | F5: =E5*'0. Assumptions'!$C$9 -> 3510000
B6: Blockchain Node Hosting (6 validator nodes × cloud) | C6: 1800 | D6: 18 | E6: =C6*D6 -> 32400 | F6: =E6*'0. Assumptions'!$C$9 -> 421200
B7: Hardware Security Modules (HSM) – cloud-based KMS | C7: 4000 | D7: 18 | E7: =C7*D7 -> 72000 | F7: =E7*'0. Assumptions'!$C$9 -> 936000
B8: Blockchain Explorer & Monitoring Tool | C8: 1200 | D8: 18 | E8: =C8*D8 -> 21600 | F8: =E8*'0. Assumptions'!$C$9 -> 280800
B9: Smart Contract Audit (external firm) | C9: 25000 | D9: 1 | E9: =C9*D9 -> 25000 | F9: =E9*'0. Assumptions'!$C$9 -> 325000
B10: Certificate Authority Setup & Annual Maintenance | C10: 8000 | D10: 1 | E10: =C10*D10 -> 8000 | F10: =E10*'0. Assumptions'!$C$9 -> 104000
B11: IPFS / Off-Chain Distributed Storage | C11: 1000 | D11: 18 | E11: =C11*D11 -> 18000 | F11: =E11*'0. Assumptions'!$C$9 -> 234000
B12: Blockchain Disaster Recovery Node | C12: 1500 | D12: 18 | E12: =C12*D12 -> 27000 | F12: =E12*'0. Assumptions'!$C$9 -> 351000
B13: Sub-Total: BLOCKCHAIN INFRASTRUCTURE | E13: =SUM(E5:E12) -> 474000 | F13: =E13*'0. Assumptions'!$C$9 -> 6162000
A14: CLOUD & HOSTING INFRASTRUCTURE (18 months)
B15: Compute – Application Servers (prod + staging + dev) | C15: 3500 | D15: 18 | E15: =C15*D15 -> 63000 | F15: =E15*'0. Assumptions'!$C$9 -> 819000
B16: Database Servers (managed PostgreSQL + Redis) | C16: 1800 | D16: 18 | E16: =C16*D16 -> 32400 | F16: =E16*'0. Assumptions'!$C$9 -> 421200
B17: Object Storage (S3 equivalent – docs, images, logs) | C17: 600 | D17: 18 | E17: =C17*D17 -> 10800 | F17: =E17*'0. Assumptions'!$C$9 -> 140400
B18: CDN – Content Delivery Network (Ghana region) | C18: 400 | D18: 18 | E18: =C18*D18 -> 7200 | F18: =E18*'0. Assumptions'!$C$9 -> 93600
B19: Load Balancer & Auto-Scaling | C19: 350 | D19: 18 | E19: =C19*D19 -> 6300 | F19: =E19*'0. Assumptions'!$C$9 -> 81900
B20: VPN & Networking / Egress Costs | C20: 500 | D20: 18 | E20: =C20*D20 -> 9000 | F20: =E20*'0. Assumptions'!$C$9 -> 117000
B21: Web Application Firewall (WAF) + DDoS Protection | C21: 800 | D21: 18 | E21: =C21*D21 -> 14400 | F21: =E21*'0. Assumptions'!$C$9 -> 187200
B22: SSL Certificates & PKI | C22: 200 | D22: 18 | E22: =C22*D22 -> 3600 | F22: =E22*'0. Assumptions'!$C$9 -> 46800
B23: SIEM / Security Monitoring (cloud) | C23: 900 | D23: 18 | E23: =C23*D23 -> 16200 | F23: =E23*'0. Assumptions'!$C$9 -> 210600
B24: Backup & Disaster Recovery (cross-region replication) | C24: 1200 | D24: 18 | E24: =C24*D24 -> 21600 | F24: =E24*'0. Assumptions'!$C$9 -> 280800
B25: Data Residency / Local DC Co-location (Act 843) | C25: 2500 | D25: 18 | E25: =C25*D25 -> 45000 | F25: =E25*'0. Assumptions'!$C$9 -> 585000
B26: Sub-Total: CLOUD & HOSTING INFRASTRUCTURE (18 months) | E26: =SUM(E15:E25) -> 229500 | F26: =E26*'0. Assumptions'!$C$9 -> 2983500
A27: SOFTWARE LICENSES & DEVELOPMENT TOOLS
B28: GitHub Enterprise (version control & CI/CD) | C28: 3000 | D28: 1 | E28: =C28*D28 -> 3000 | F28: =E28*'0. Assumptions'!$C$9 -> 39000
B29: Jira + Confluence (project management & docs) | C29: 2500 | D29: 1 | E29: =C29*D29 -> 2500 | F29: =E29*'0. Assumptions'!$C$9 -> 32500
B30: Figma Organisation (UI/UX design) | C30: 1200 | D30: 1 | E30: =C30*D30 -> 1200 | F30: =E30*'0. Assumptions'!$C$9 -> 15600
B31: SonarQube (code quality) | C31: 1500 | D31: 1 | E31: =C31*D31 -> 1500 | F31: =E31*'0. Assumptions'!$C$9 -> 19500
B32: Postman Enterprise (API testing) | C32: 1000 | D32: 1 | E32: =C32*D32 -> 1000 | F32: =E32*'0. Assumptions'!$C$9 -> 13000
B33: Datadog APM (application monitoring) | C33: 4800 | D33: 1 | E33: =C33*D33 -> 4800 | F33: =E33*'0. Assumptions'!$C$9 -> 62400
B34: PagerDuty (incident management) | C34: 1200 | D34: 1 | E34: =C34*D34 -> 1200 | F34: =E34*'0. Assumptions'!$C$9 -> 15600
B35: Power BI Premium (analytics & dashboards) | C35: 4200 | D35: 1 | E35: =C35*D35 -> 4200 | F35: =E35*'0. Assumptions'!$C$9 -> 54600
B36: LoadRunner / JMeter Pro (performance testing) | C36: 2500 | D36: 1 | E36: =C36*D36 -> 2500 | F36: =E36*'0. Assumptions'!$C$9 -> 32500
B37: Burp Suite Pro (security testing) | C37: 1500 | D37: 1 | E37: =C37*D37 -> 1500 | F37: =E37*'0. Assumptions'!$C$9 -> 19500
B38: Microsoft 365 (team productivity – 30 users) | C38: 5400 | D38: 1 | E38: =C38*D38 -> 5400 | F38: =E38*'0. Assumptions'!$C$9 -> 70200
B39: Sub-Total: SOFTWARE LICENSES & DEVELOPMENT TOOLS | E39: =SUM(E28:E38) -> 28800 | F39: =E39*'0. Assumptions'!$C$9 -> 374400
A40: THIRD-PARTY API & COMPLIANCE SERVICES (18 months)
B41: Ghana Card / NIA Identity Verification API | C41: 1500 | D41: 18 | E41: =C41*D41 -> 27000 | F41: =E41*'0. Assumptions'!$C$9 -> 351000
B42: AML/CFT Sanctions Screening (Refinitiv/LexisNexis) | C42: 2000 | D42: 18 | E42: =C42*D42 -> 36000 | F42: =E42*'0. Assumptions'!$C$9 -> 468000
B43: PEP & Adverse Media Screening Service | C43: 1200 | D43: 18 | E43: =C43*D43 -> 21600 | F43: =E43*'0. Assumptions'!$C$9 -> 280800
B44: SMS Gateway – Bulk SMS (MTN/Vodafone Ghana) | C44: 800 | D44: 18 | E44: =C44*D44 -> 14400 | F44: =E44*'0. Assumptions'!$C$9 -> 187200
B45: Google Maps / Geolocation API | C45: 500 | D45: 18 | E45: =C45*D45 -> 9000 | F45: =E45*'0. Assumptions'!$C$9 -> 117000
B46: Email Delivery Service (SendGrid / AWS SES) | C46: 200 | D46: 18 | E46: =C46*D46 -> 3600 | F46: =E46*'0. Assumptions'!$C$9 -> 46800
B47: DocuSign / Digital Signature Service | C47: 600 | D47: 18 | E47: =C47*D47 -> 10800 | F47: =E47*'0. Assumptions'!$C$9 -> 140400
B48: Source Code Escrow Agreement | C48: 3000 | D48: 1 | E48: =C48*D48 -> 3000 | F48: =E48*'0. Assumptions'!$C$9 -> 39000
B49: Sub-Total: THIRD-PARTY API & COMPLIANCE SERVICES (18 months) | E49: =SUM(E41:E48) -> 125400 | F49: =E49*'0. Assumptions'!$C$9 -> 1630200
B50: TOTAL INFRASTRUCTURE & LICENSES | E50: =E13+E26+E39+E49 -> 857700 | F50: =E50*'0. Assumptions'!$C$9 -> 11150100

Sheet 4. Hardware & Other Costs
A1: SECTION 4 — HARDWARE, TRAINING, INTEGRATION, COMPLIANCE & PROJECT MANAGEMENT
B3: Item / Activity | C3: Unit Cost (USD) | D3: Quantity | E3: Total USD | F3: Total GHS
A4: HARDWARE & FIELD EQUIPMENT
B5: Rugged Android Smartphones for Field Officers | C5: 350 | D5: 120 | E5: =C5*D5 -> 42000 | F5: =E5*'0. Assumptions'!$C$9 -> 546000
B6: Protective Cases & Screen Protectors | C6: 30 | D6: 120 | E6: =C6*D6 -> 3600 | F6: =E6*'0. Assumptions'!$C$9 -> 46800
B7: QR Code / NFC Scanners (handheld) | C7: 280 | D7: 80 | E7: =C7*D7 -> 22400 | F7: =E7*'0. Assumptions'!$C$9 -> 291200
B8: Barcode Label Printer (for serialised tags) | C8: 450 | D8: 20 | E8: =C8*D8 -> 9000 | F8: =E8*'0. Assumptions'!$C$9 -> 117000
B9: Label Printing Supplies (rolls, ink – 18 months) | C9: 600 | D9: 1 | E9: =C9*D9 -> 600 | F9: =E9*'0. Assumptions'!$C$9 -> 7800
B10: Digital Scales with Data Capture (assay sites) | C10: 1200 | D10: 30 | E10: =C10*D10 -> 36000 | F10: =E10*'0. Assumptions'!$C$9 -> 468000
B11: Field GPS Handheld Units (remote areas) | C11: 200 | D11: 30 | E11: =C11*D11 -> 6000 | F11: =E11*'0. Assumptions'!$C$9 -> 78000
B12: Mobile Hotspot / MiFi Devices (LTE) | C12: 150 | D12: 50 | E12: =C12*D12 -> 7500 | F12: =E12*'0. Assumptions'!$C$9 -> 97500
B13: Solar Chargers & Power Banks (off-grid) | C13: 80 | D13: 80 | E13: =C13*D13 -> 6400 | F13: =E13*'0. Assumptions'!$C$9 -> 83200
B14: Laptop Computers (project team) | C14: 1200 | D14: 25 | E14: =C14*D14 -> 30000 | F14: =E14*'0. Assumptions'!$C$9 -> 390000
B15: Desktop Workstations (GoldBod offices) | C15: 1000 | D15: 20 | E15: =C15*D15 -> 20000 | F15: =E15*'0. Assumptions'!$C$9 -> 260000
B16: Network Switches & WiFi Access Points | C16: 350 | D16: 15 | E16: =C16*D16 -> 5250 | F16: =E16*'0. Assumptions'!$C$9 -> 68250
... B20: Equipment Insurance (18 months, all hardware) | C20: 8000 | D20: 1 | E20: =C20*D20 -> 8000 | F20: =E20*'0. Assumptions'!$C$9 -> 104000
B21: Sub-Total: HARDWARE & FIELD EQUIPMENT | E21: =SUM(E5:E20) -> 218750 | F21: =E21*'0. Assumptions'!$C$9 -> 2843750
A22: SYSTEMS INTEGRATION — 6 GOVERNMENT AGENCIES
B23: Minerals Commission – Licensing & Cadastre API | C23: 45000 | D23: 1 | E23: =C23*D23 -> 45000 | F23: =E23*'0. Assumptions'!$C$9 -> 585000
B24: Ghana Revenue Authority (GRA) – Customs Export API | C24: 40000 | D24: 1 | E24: =C24*D24 -> 40000 | F24: =E24*'0. Assumptions'!$C$9 -> 520000
B25: Bank of Ghana – Payment & FX Reporting API | C25: 45000 | D25: 1 | E25: =C25*D25 -> 45000 | F25: =E25*'0. Assumptions'!$C$9 -> 585000
B26: Financial Intelligence Centre (FIC) – STR/SAR Filing | C26: 38000 | D26: 1 | E26: =C26*D26 -> 38000 | F26: =E26*'0. Assumptions'!$C$9 -> 494000
B27: Environmental Protection Authority (EPA) | C27: 32000 | D27: 1 | E27: =C27*D27 -> 32000 | F27: =E27*'0. Assumptions'!$C$9 -> 416000
B28: Water Resources Commission (WRC) | C28: 28000 | D28: 1 | E28: =C28*D28 -> 28000 | F28: =E28*'0. Assumptions'!$C$9 -> 364000
B29: Integration Testing & End-to-End Validation | C29: 35000 | D29: 1 | E29: =C29*D29 -> 35000 | F29: =E29*'0. Assumptions'!$C$9 -> 455000
B30: API Gateway Setup & Developer Portal | C30: 20000 | D30: 1 | E30: =C30*D30 -> 20000 | F30: =E30*'0. Assumptions'!$C$9 -> 260000
B31: Ongoing Integration Maintenance (12 months) | C31: 25000 | D31: 1 | E31: =C31*D31 -> 25000 | F31: =E31*'0. Assumptions'!$C$9 -> 325000
B32: Sub-Total: SYSTEMS INTEGRATION — 6 GOVERNMENT AGENCIES | E32: =SUM(E23:E31) -> 308000 | F32: =E32*'0. Assumptions'!$C$9 -> 4004000
A33: TRAINING & CAPACITY BUILDING
B34: Training Needs Assessment & Curriculum Development | C34: 15000 | D34: 1 | E34: =C34*D34 -> 15000 | F34: =E34*'0. Assumptions'!$C$9 -> 195000
B35: LMS Setup & E-Learning Module Production | C35: 22000 | D35: 1 | E35: =C35*D35 -> 22000 | F35: =E35*'0. Assumptions'!$C$9 -> 286000
B36: User Manuals, Video Guides & Visual Aids | C36: 12000 | D36: 1 | E36: =C36*D36 -> 12000 | F36: =E36*'0. Assumptions'!$C$9 -> 156000
B37: GoldBod IT Staff – Blockchain & System Admin Training | C37: 8000 | D37: 1 | E37: =C37*D37 -> 8000 | F37: =E37*'0. Assumptions'!$C$9 -> 104000
B38: Field Officer Training (10 regions × 2 batches) | C38: 4500 | D38: 20 | E38: =C38*D38 -> 90000 | F38: =E38*'0. Assumptions'!$C$9 -> 1170000
B39: Tier 1/2 Buyer & Kitchen Operator Training | C39: 3000 | D39: 30 | E39: =C39*D39 -> 90000 | F39: =E39*'0. Assumptions'!$C$9 -> 1170000
B40: Aggregator & Transporter Training | C40: 2500 | D40: 20 | E40: =C40*D40 -> 50000 | F40: =E40*'0. Assumptions'!$C$9 -> 650000
B41: Miner / Small-Scale ASM Sensitisation Workshops | C41: 1800 | D41: 40 | E41: =C41*D41 -> 72000 | F41: =E41*'0. Assumptions'!$C$9 -> 936000
B42: Train-the-Trainer Programme | C42: 10000 | D42: 1 | E42: =C42*D42 -> 10000 | F42: =E42*'0. Assumptions'!$C$9 -> 130000
B43: Training Venue, Catering & Logistics (regional) | C43: 1200 | D43: 20 | E43: =C43*D43 -> 24000 | F43: =E43*'0. Assumptions'!$C$9 -> 312000
B44: Refresher Training – Stabilisation Phase | C44: 25000 | D44: 1 | E44: =C44*D44 -> 25000 | F44: =E44*'0. Assumptions'!$C$9 -> 325000
B45: Change Management Programme | C45: 18000 | D45: 1 | E45: =C45*D45 -> 18000 | F45: =E45*'0. Assumptions'!$C$9 -> 234000
B46: Sub-Total: TRAINING & CAPACITY BUILDING | E46: =SUM(E34:E45) -> 436000 | F46: =E46*'0. Assumptions'!$C$9 -> 5668000
A47: TESTING & QUALITY ASSURANCE
B48: Test Environment Hosting (UAT + staging – 6 months) | C48: 5000 | D48: 6 | E48: =C48*D48 -> 30000 | F48: =E48*'0. Assumptions'!$C$9 -> 390000
B49: Automated Testing Framework Setup | C49: 18000 | D49: 1 | E49: =C49*D49 -> 18000 | F49: =E49*'0. Assumptions'!$C$9 -> 234000
B50: Performance / Load Testing (JMeter) | C50: 12000 | D50: 1 | E50: =C50*D50 -> 12000 | F50: =E50*'0. Assumptions'!$C$9 -> 156000
B51: External Security Audit & Penetration Testing | C51: 35000 | D51: 1 | E51: =C51*D51 -> 35000 | F51: =E51*'0. Assumptions'!$C$9 -> 455000
B52: Blockchain Security Audit (specialist firm) | C52: 25000 | D52: 1 | E52: =C52*D52 -> 25000 | F52: =E52*'0. Assumptions'!$C$9 -> 325000
B53: LBMA / OECD Compliance Assessment | C53: 20000 | D53: 1 | E53: =C53*D53 -> 20000 | F53: =E53*'0. Assumptions'!$C$9 -> 260000
B54: ISO 27001 Gap Analysis & Preparation | C54: 18000 | D54: 1 | E54: =C54*D54 -> 18000 | F54: =E54*'0. Assumptions'!$C$9 -> 234000
B55: UAT Facilitation (multi-site, all stakeholders) | C55: 15000 | D55: 1 | E55: =C55*D55 -> 15000 | F55: =E55*'0. Assumptions'!$C$9 -> 195000
B56: Usability / Field Testing (remote sites) | C56: 8000 | D56: 1 | E56: =C56*D56 -> 8000 | F56: =E56*'0. Assumptions'!$C$9 -> 104000
B57: Test Defect Tracking Tool License (1 year) | C57: 2000 | D57: 1 | E57: =C57*D57 -> 2000 | F57: =E57*'0. Assumptions'!$C$9 -> 26000
B58: Sub-Total: TESTING & QUALITY ASSURANCE | E58: =SUM(E48:E57) -> 183000 | F58: =E58*'0. Assumptions'!$C$9 -> 2379000
A59: COMPLIANCE, LEGAL & REGULATORY
B60: Data Protection Impact Assessment (DPIA – Act 843) | C60: 12000 | D60: 1 | E60: =C60*D60 -> 12000 | F60: =E60*'0. Assumptions'!$C$9 -> 156000
B61: Privacy Policy & Data Processing Agreements (legal) | C61: 8000 | D61: 1 | E61: =C61*D61 -> 8000 | F61: =E61*'0. Assumptions'!$C$9 -> 104000
B62: AML/CFT Policy Framework & Legal Review | C62: 10000 | D62: 1 | E62: =C62*D62 -> 10000 | F62: =E62*'0. Assumptions'!$C$9 -> 130000
B63: FATF / OECD Compliance Framework Documentation | C63: 12000 | D63: 1 | E63: =C63*D63 -> 12000 | F63: =E63*'0. Assumptions'!$C$9 -> 156000
B64: IP Assignment & Open-Source Licence Review | C64: 6000 | D64: 1 | E64: =C64*D64 -> 6000 | F64: =E64*'0. Assumptions'!$C$9 -> 78000
B65: SOC 2 Type II Audit Preparation | C65: 20000 | D65: 1 | E65: =C65*D65 -> 20000 | F65: =E65*'0. Assumptions'!$C$9 -> 260000
B66: Professional Indemnity Insurance (18 months) | C66: 18000 | D66: 1 | E66: =C66*D66 -> 18000 | F66: =E66*'0. Assumptions'!$C$9 -> 234000
B67: Cyber Liability Insurance (18 months) | C67: 12000 | D67: 1 | E67: =C67*D67 -> 12000 | F67: =E67*'0. Assumptions'!$C$9 -> 156000
B68: Legal Advisor – Contract Review & Disputes | C68: 15000 | D68: 1 | E68: =C68*D68 -> 15000 | F68: =E68*'0. Assumptions'!$C$9 -> 195000
B69: PPA Registration, Tax Clearance & Filings | C69: 5000 | D69: 1 | E69: =C69*D69 -> 5000 | F69: =E69*'0. Assumptions'!$C$9 -> 65000
B70: Withholding Tax Provision (est. on foreign services) | C70: 20000 | D70: 1 | E70: =C70*D70 -> 20000 | F70: =E70*'0. Assumptions'!$C$9 -> 260000
B71: VAT on Applicable Local Costs (15%) | C71: 15000 | D71: 1 | E71: =C71*D71 -> 15000 | F71: =E71*'0. Assumptions'!$C$9 -> 195000
B72: Sub-Total: COMPLIANCE, LEGAL & REGULATORY | E72: =SUM(E60:E71) -> 153000 | F72: =E72*'0. Assumptions'!$C$9 -> 1989000
A73: PROJECT MANAGEMENT & GOVERNANCE (PMO)
B74: PMO Setup & Project Management Software | C74: 8000 | D74: 1 | E74: =C74*D74 -> 8000 | F74: =E74*'0. Assumptions'!$C$9 -> 104000
B75: Monthly Steering Committee Meetings (18 months) | C75: 1200 | D75: 18 | E75: =C75*D75 -> 21600 | F75: =E75*'0. Assumptions'!$C$9 -> 280800
B76: Project Launch Event & National Go-Live Ceremony | C76: 20000 | D76: 1 | E76: =C76*D76 -> 20000 | F76: =E76*'0. Assumptions'!$C$9 -> 260000
B77: International Airfare (expert missions, 4 visits) | C77: 5000 | D77: 4 | E77: =C77*D77 -> 20000 | F77: =E77*'0. Assumptions'!$C$9 -> 260000
B78: Accommodation & Per Diem (international experts) | C78: 3500 | D78: 4 | E78: =C78*D78 -> 14000 | F78: =E78*'0. Assumptions'!$C$9 -> 182000
B79: Domestic Travel – Regional Site Visits (18 months) | C79: 12000 | D79: 1 | E79: =C79*D79 -> 12000 | F79: =E79*'0. Assumptions'!$C$9 -> 156000
B80: Equipment Transportation & Logistics | C80: 8000 | D80: 1 | E80: =C80*D80 -> 8000 | F80: =E80*'0. Assumptions'!$C$9 -> 104000
B81: Office Rental & Running Costs (PMO office, 18 mths) | C81: 2500 | D81: 18 | E81: =C81*D81 -> 45000 | F81: =E81*'0. Assumptions'!$C$9 -> 585000
B82: Communication & Utilities (18 months) | C82: 1000 | D82: 18 | E82: =C82*D82 -> 18000 | F82: =E82*'0. Assumptions'!$C$9 -> 234000
B83: Monthly Progress Reports & Deliverable Production | C83: 1500 | D83: 18 | E83: =C83*D83 -> 27000 | F83: =E83*'0. Assumptions'!$C$9 -> 351000
B84: Public Relations & Media Engagement | C84: 10000 | D84: 1 | E84: =C84*D84 -> 10000 | F84: =E84*'0. Assumptions'!$C$9 -> 130000
B85: Sub-Total: PROJECT MANAGEMENT & GOVERNANCE (PMO) | E85: =SUM(E74:E84) -> 203600 | F85: =E85*'0. Assumptions'!$C$9 -> 2646800
A86: PILOT PROGRAMME (Months 5–6)
B87: Pilot Site Setup & Configuration (3 sites) | C87: 20000 | D87: 3 | E87: =C87*D87 -> 60000 | F87: =E87*'0. Assumptions'!$C$9 -> 780000
B88: Pilot Equipment Deployment & Installation | C88: 10000 | D88: 1 | E88: =C88*D88 -> 10000 | F88: =E88*'0. Assumptions'!$C$9 -> 130000
B89: Pilot Monitoring, Evaluation & Reporting | C89: 12000 | D89: 1 | E89: =C89*D89 -> 12000 | F89: =E89*'0. Assumptions'!$C$9 -> 156000
B90: Pilot Training & On-Site Support | C90: 8000 | D90: 1 | E90: =C90*D90 -> 8000 | F90: =E90*'0. Assumptions'!$C$9 -> 104000
B91: Pilot Iteration & System Refinement | C91: 18000 | D91: 1 | E91: =C91*D91 -> 18000 | F91: =E91*'0. Assumptions'!$C$9 -> 234000
B92: Pilot Closure Report & Go/No-Go Assessment | C92: 5000 | D92: 1 | E92: =C92*D92 -> 5000 | F92: =E92*'0. Assumptions'!$C$9 -> 65000
B93: Sub-Total: PILOT PROGRAMME (Months 5–6) | E93: =SUM(E87:E92) -> 113000 | F93: =E93*'0. Assumptions'!$C$9 -> 1469000
A94: NATIONAL DEPLOYMENT (Month 6)
B95: National Infrastructure Rollout – 10 Regions | C95: 35000 | D95: 1 | E95: =C95*D95 -> 35000 | F95: =E95*'0. Assumptions'!$C$9 -> 455000
B96: Regional Equipment Delivery & Installation | C96: 20000 | D96: 1 | E96: =C96*D96 -> 20000 | F96: =E96*'0. Assumptions'!$C$9 -> 260000
B97: Go-Live 24/7 War Room Support (2 weeks) | C97: 15000 | D97: 1 | E97: =C97*D97 -> 15000 | F97: =E97*'0. Assumptions'!$C$9 -> 195000
B98: Communications Campaign & Awareness | C98: 12000 | D98: 1 | E98: =C98*D98 -> 12000 | F98: =E98*'0. Assumptions'!$C$9 -> 156000
B99: National Deployment Documentation | C99: 5000 | D99: 1 | E99: =C99*D99 -> 5000 | F99: =E99*'0. Assumptions'!$C$9 -> 65000
B100: Sub-Total: NATIONAL DEPLOYMENT (Month 6) | E100: =SUM(E95:E99) -> 87000 | F100: =E100*'0. Assumptions'!$C$9 -> 1131000
A101: DOCUMENTATION & KNOWLEDGE TRANSFER DELIVERABLES
B102: System Architecture & Technical Documentation | C102: 10000 | D102: 1 | E102: =C102*D102 -> 10000 | F102: =E102*'0. Assumptions'!$C$9 -> 130000
B103: User Manuals (all roles, multi-language) | C103: 8000 | D103: 1 | E103: =C103*D103 -> 8000 | F103: =E103*'0. Assumptions'!$C$9 -> 104000
B104: Administrator & IT Operations Manual | C104: 6000 | D104: 1 | E104: =C104*D104 -> 6000 | F104: =E104*'0. Assumptions'!$C$9 -> 78000
...

Sheet 5. Payment Milestones
A1: PAYMENT MILESTONE SCHEDULE
B3: Milestone | C3: Description | D3: % of Total | E3: Amount (USD) | F3: Amount (GHS) | G3: Expected Date
B4: M0 | C4: Contract Signing Advance | D4: 0.15 | E4: =D4*'0. Assumptions'!$C$8 -> 1703250 | F4: =E4*'0. Assumptions'!$C$9 -> 22142250 | G4: Week 0
B5: M1 | C5: Phase 1 Completion – Design, Architecture & Requirements | D5: 0.12 | E5: =D5*'0. Assumptions'!$C$8 -> 1362600 | F5: =E5*'0. Assumptions'!$C$9 -> 17713800 | G5: Month 2
B6: M2 | C6: Phase 2 Completion – Core Platform & Blockchain Development | D6: 0.2 | E6: =D6*'0. Assumptions'!$C$8 -> 2271000 | F6: =E6*'0. Assumptions'!$C$9 -> 29523000 | G6: Month 4
B7: M3 | C7: Phase 3 Completion – Integration & Testing | D7: 0.1 | E7: =D7*'0. Assumptions'!$C$8 -> 1135500 | F7: =E7*'0. Assumptions'!$C$9 -> 14761500 | G7: Month 5
B8: M4 | C8: Phase 4 Completion – Pilot Deployment | D8: 0.08 | E8: =D8*'0. Assumptions'!$C$8 -> 908400 | F8: =E8*'0. Assumptions'!$C$9 -> 11809200 | G8: Month 6
B9: M5 | C9: Phase 5 – National Go-Live | D9: 0.15 | E9: =D9*'0. Assumptions'!$C$8 -> 1703250 | F9: =E9*'0. Assumptions'!$C$9 -> 22142250 | G9: Month 6
B10: M6a | C10: Stabilisation – Quarter 1 (Monthly 2% × 3) | D10: 0.06 | E10: =D10*'0. Assumptions'!$C$8 -> 681300 | F10: =E10*'0. Assumptions'!$C$9 -> 8856900 | G10: Months 7–9
B11: M6b | C11: Stabilisation – Quarter 2 (Monthly 2% × 3) | D11: 0.06 | E11: =D11*'0. Assumptions'!$C$8 -> 681300 | F11: =E11*'0. Assumptions'!$C$9 -> 8856900 | G11: Months 10–12
B12: M6c | C12: Stabilisation – Quarter 3 (Monthly 1% × 3) | D12: 0.03 | E12: =D12*'0. Assumptions'!$C$8 -> 340650 | F12: =E12*'0. Assumptions'!$C$9 -> 4428450 | G12: Months 13–15
B13: M7 | C13: Final Handover & Knowledge Transfer | D13: 0.03 | E13: =D13*'0. Assumptions'!$C$8 -> 340650 | F13: =E13*'0. Assumptions'!$C$9 -> 4428450 | G13: Month 18
B14: RET | C14: Performance Retention (released post-warranty) | D14: 0.02 | E14: =D14*'0. Assumptions'!$C$8 -> 227100 | F14: =E14*'0. Assumptions'!$C$9 -> 2952300 | G14: Month 24
B15: TOTAL CONTRACT VALUE | D15: =SUM(D4:D14) -> 1 | E15: ='0. Assumptions'!$C$8 -> 11355000 | F15: =E15*'0. Assumptions'!$C$9 -> 147615000

Sheet 6. Financial Risk Register
A1: FINANCIAL RISK REGISTER
A3: Risk ID | B3: Risk Description | C3: Probability | D3: Impact | E3: Cost Impact | F3: Mitigation Strategy
A4: FR-01 | B4: Currency exchange rate fluctuation (GHS depreciation) | C4: Medium | D4: High | E4: ±5–10% on GHS costs | F4: Build 5% FX buffer; USD-denominated contracts
A5: FR-02 | B5: Scope creep & change requests | C5: High | D5: High | E5: +10–20% on dev costs | F5: Strict change control; change request pricing schedule
A6: FR-03 | B6: Delayed payments from GoldBod/GoG | C6: Medium | D6: Medium | E6: Cash flow impact | F6: Milestone-based invoicing; advance payment
A7: FR-04 | B7: Integration complexity underestimated | C7: High | D7: High | E7: +15–25% on integration | F7: Detailed API assessment; dedicated integration PM
A8: FR-05 | B8: Blockchain implementation complexity | C8: Medium | D8: High | E8: +10–20% on blockchain | F8: Expert consultation; PoC before full build
A9: FR-06 | B9: Training requirements underestimated | C9: Medium | D9: Medium | E9: +10–15% on training | F9: Phased training; early needs assessment
A10: FR-07 | B10: Equipment procurement delays (import) | C10: Medium | D10: Medium | E10: Schedule impact | F10: Early ordering; identify local alternatives
A11: FR-08 | B11: Import duty / tax increases | C11: Low | D11: Medium | E11: +3–5% on hardware | F11: Forward purchasing; monitor tax policy
A12: FR-09 | B12: Technology cost inflation (cloud/SaaS) | C12: Medium | D12: Medium | E12: +5% on cloud costs | F12: Reserved instances; multi-year licensing
A13: FR-10 | B13: Third-party API unavailability (Ghana Card, GRA) | C13: Medium | D13: High | E13: Timeline impact | F13: Early engagement; mock APIs for dev/test
A14: FR-11 | B14: Security breach during stabilisation | C14: Low | D14: Very High | E14: Unbudgeted incident response | F14: Cyber insurance; SIEM; penetration testing
A15: FR-12 | B15: Key personnel attrition (blockchain talent) | C15: Medium | D15: High | E15: +5–10% on recruitment | F15: Competitive rates; retention bonuses

Sheet 7. Assumptions
A1: KEY ASSUMPTIONS & CONSTRAINTS
B3: Assumption Category | C3: Detail
B4: Exchange Rate | C4: ="1 USD = "&TEXT('0. Assumptions'!C9,"0.00")&" GHS (indicative, April 2026). Rates locked at contract signing." -> 1 USD = 13.00 GHS (indicative, April 2026). Rates locked at contract signing.
B5: Exchange Rate Variance | C5: ±5% buffer built into contingency for FX movements.
B6: Ghana Inflation | C6: ~20% p.a. local inflation assumed; escalation clause to be negotiated for GHS costs beyond Month 6.
B7: Cloud Cost Inflation | C7: ±5% year-on-year; reserved instance pricing to be secured at contract start.
B8: Contract Start | C8: Contract signature assumed Q2 2026; Phase 1 begins within 1 week of signing.
B9: Project Duration | C9: 18 months – 6 months implementation + 12 months stabilisation & support.
B10: Tax – VAT | C10: 15% VAT applies on all locally procured goods and services. Included in local cost estimates.
B11: Tax – WHT | C11: Withholding tax on foreign service payments per Ghana Revenue Authority rates. Provision included.
B12: Tax – PAYE | C12: Employer PAYE obligations for all Ghanaian staff. Managed via payroll.
B13: SSNIT | C13: 13% employer SSNIT contribution on basic salary of all Ghanaian employees.
B14: Tier 2 Pension | C14: 5% employer Tier 2 contribution on basic salary.
B15: Scope | C15: No material scope changes assumed. Change requests priced separately per agreed schedule.
B16: Agency Integration | C16: GoldBod will facilitate introductions and access to all 6 government agencies within Month 1.
... B27: Post-Handover Warranty | C27: 12-month post-handover warranty commences at end of stabilisation phase (Month 18).

Sheet 8. Deployment Costs
A1: SECTION 8 — DEPLOYMENT COSTS (Pilot & National Rollout)
A2: Deployment Activity / Item | B2: Estimated Cost (USD) | C2: Estimated Cost (GHS)
A3: PILOT DEPLOYMENT — 3 MINE SITES (Months 5–6)
A4: Pilot site survey & readiness assessment (3 sites) | B4: 15000 | C4: =B4*'0. Assumptions'!$C$9 -> 195000
A5: Site-specific hardware installation & configuration | B5: 18000 | C5: =B5*'0. Assumptions'!$C$9 -> 234000
A6: Blockchain node deployment at pilot sites | B6: 8000 | C6: =B6*'0. Assumptions'!$C$9 -> 104000
A7: Network & connectivity setup at pilot sites | B7: 12000 | C7: =B7*'0. Assumptions'!$C$9 -> 156000
A8: Pilot data migration & historical records import | B8: 10000 | C8: =B8*'0. Assumptions'!$C$9 -> 130000
A9: Pilot user onboarding & account provisioning | B9: 6000 | C9: =B9*'0. Assumptions'!$C$9 -> 78000
A10: On-site pilot training & orientation (3 sites × 3 days) | B10: 12000 | C10: =B10*'0. Assumptions'!$C$9 -> 156000
A11: Pilot monitoring, war room & daily standups | B11: 9000 | C11: =B11*'0. Assumptions'!$C$9 -> 117000
A12: Field feedback sessions & UX iteration | B12: 7000 | C12: =B12*'0. Assumptions'!$C$9 -> 91000
A13: Pilot performance report & go/no-go assessment | B13: 5000 | C13: =B13*'0. Assumptions'!$C$9 -> 65000
A14: Pilot closeout & lessons-learned documentation | B14: 4000 | C14: =B14*'0. Assumptions'!$C$9 -> 52000
A15: Sub-Total | B15: =SUM(B4:B14) -> 106000 | C15: =B15*'0. Assumptions'!$C$9 -> 1378000
A16: PRE-NATIONAL DEPLOYMENT PREPARATION
A17: National deployment planning & runbook development | B17: 8000 | C17: =B17*'0. Assumptions'!$C$9 -> 104000
A18: Infrastructure pre-provisioning (all 10 regions) | B18: 22000 | C18: =B18*'0. Assumptions'!$C$9 -> 286000
A19: Bulk hardware staging, testing & labelling | B19: 9000 | C19: =B19*'0. Assumptions'!$C$9 -> 117000
A20: National data migration & master data setup | B20: 18000 | C20: =B20*'0. Assumptions'!$C$9 -> 234000
A21: User account bulk provisioning (all actors) | B21: 10000 | C21: =B21*'0. Assumptions'!$C$9 -> 130000
A22: Stakeholder pre-briefing (10 regional offices) | B22: 12000 | C22: =B22*'0. Assumptions'!$C$9 -> 156000
A23: Pre-deployment penetration test & sign-off | B23: 15000 | C23: =B23*'0. Assumptions'!$C$9 -> 195000
A24: Sub-Total | B24: =SUM(B17:B23) -> 94000 | C24: =B24*'0. Assumptions'!$C$9 -> 1222000
A25: NATIONAL GO-LIVE — 10 REGIONS (Month 6)
A26: Regional equipment delivery & logistics (10 regions) | B26: 28000 | C26: =B26*'0. Assumptions'!$C$9 -> 364000
A27: On-site installation teams (10 teams × 3 technicians, 3 days) | B27: 30000 | C27: =B27*'0. Assumptions'!$C$9 -> 390000
A28: Network/connectivity activation across all sites | B28: 15000 | C28: =B28*'0. Assumptions'!$C$9 -> 195000
A29: Go-live war room (24/7 support — 2 weeks) | B29: 22000 | C29: =B29*'0. Assumptions'!$C$9 -> 286000
A30: National launch event & press conference | B30: 15000 | C30: =B30*'0. Assumptions'!$C$9 -> 195000
A31: Public awareness campaign (radio, TV, billboards) | B31: 20000 | C31: =B31*'0. Assumptions'!$C$9 -> 260000
A32: SMS broadcast to all registered miners/buyers | B32: 3000 | C32: =B32*'0. Assumptions'!$C$9 -> 39000
A33: Post go-live hotfix sprints (first 4 weeks) | B33: 18000 | C33: =B33*'0. Assumptions'!$C$9 -> 234000
A34: Regional helpdesk activation & staffing | B34: 14000 | C34: =B34*'0. Assumptions'!$C$9 -> 182000
A35: Go-live documentation & sign-off pack | B35: 5000 | C35: =B35*'0. Assumptions'!$C$9 -> 65000
A36: Sub-Total | B36: =SUM(B26:B35) -> 170000 | C36: =B36*'0. Assumptions'!$C$9 -> 2210000
A37: CLOUD & INFRASTRUCTURE SCALE-UP AT GO-LIVE
A38: Auto-scaling configuration & load testing at national volume | B38: 8000 | C38: =B38*'0. Assumptions'!$C$9 -> 104000
A39: CDN & caching optimisation for Ghana latency | B39: 5000 | C39: =B39*'0. Assumptions'!$C$9 -> 65000
A40: Disaster recovery drill at go-live scale | B40: 6000 | C40: =B40*'0. Assumptions'!$C$9 -> 78000
A41: Blockchain node replication & geo-distribution | B41: 7000 | C41: =B41*'0. Assumptions'!$C$9 -> 91000
A42: Monitoring dashboards configuration (real-time) | B42: 4000 | C42: =B42*'0. Assumptions'!$C$9 -> 52000
A43: Sub-Total | B43: =SUM(B38:B42) -> 30000 | C43: =B43*'0. Assumptions'!$C$9 -> 390000
A44: TOTAL DEPLOYMENT COSTS | B44: =B15+B24+B36+B43 -> 400000 | C44: =B44*'0. Assumptions'!$C$9 -> 5200000

Sheet 9. Training & Capacity
A1: SECTION 9 — TRAINING & CAPACITY BUILDING COSTS
A2: Training Activity | B2: Unit Cost (USD) | C2: Qty | D2: Total USD | E2: Total GHS
A3: TRAINING PROGRAMME DESIGN & MATERIALS
A4: Training Needs Assessment & Skills Gap Analysis | B4: 12000 | C4: 1 | D4: =B4*C4 -> 12000 | E4: =D4*'0. Assumptions'!$C$9 -> 156000
A5: Curriculum Design (all 8 user roles) | B5: 18000 | C5: 1 | D5: =B5*C5 -> 18000 | E5: =D5*'0. Assumptions'!$C$9 -> 234000
A6: User Manuals & Quick Reference Guides (all roles) | B6: 10000 | C6: 1 | D6: =B6*C6 -> 10000 | E6: =D6*'0. Assumptions'!$C$9 -> 130000
A7: Video Tutorial Production (16 modules) | B7: 2500 | C7: 16 | D7: =B7*C7 -> 40000 | E7: =D7*'0. Assumptions'!$C$9 -> 520000
A8: Interactive E-Learning Modules (LMS) | B8: 3000 | C8: 8 | D8: =B8*C8 -> 24000 | E8: =D8*'0. Assumptions'!$C$9 -> 312000
A9: Poster & Visual Aid Design (local languages) | B9: 5000 | C9: 1 | D9: =B9*C9 -> 5000 | E9: =D9*'0. Assumptions'!$C$9 -> 65000
A10: LMS Platform Setup & Content Upload | B10: 8000 | C10: 1 | D10: =B10*C10 -> 8000 | E10: =D10*'0. Assumptions'!$C$9 -> 104000
A11: Training Material Translation (Twi, Hausa, Dagbani) | B11: 6000 | C11: 1 | D11: =B11*C11 -> 6000 | E11: =D11*'0. Assumptions'!$C$9 -> 78000
A12: Sub-Total | D12: =SUM(D4:D11) -> 123000 | E12: =D12*'0. Assumptions'!$C$9 -> 1599000
A13: GOLDBOD TECHNICAL STAFF TRAINING
A14: Blockchain Technology & Node Management (5-day) | B14: 8000 | C14: 1 | D14: =B14*C14 -> 8000 | E14: =D14*'0. Assumptions'!$C$9 -> 104000
A15: System Administration & DevOps (3-day) | B15: 5000 | C15: 1 | D15: =B15*C15 -> 5000 | E15: =D15*'0. Assumptions'!$C$9 -> 65000
A16: Database Administration & Backup (2-day) | B16: 3500 | C16: 1 | D16: =B16*C16 -> 3500 | E16: =D16*'0. Assumptions'!$C$9 -> 45500
A17: Security & Incident Response Training (2-day) | B17: 4000 | C17: 1 | D17: =B17*C17 -> 4000 | E17: =D17*'0. Assumptions'!$C$9 -> 52000
A18: Analytics & BI Dashboard Training (2-day) | B18: 3000 | C18: 1 | D18: =B18*C18 -> 3000 | E18: =D18*'0. Assumptions'!$C$9 -> 39000
A19: API Integration & Developer Training (3-day) | B19: 4500 | C19: 1 | D19: =B19*C19 -> 4500 | E19: =D19*'0. Assumptions'!$C$9 -> 58500
A20: Sub-Total | D20: =SUM(D14:D19) -> 28000 | E20: =D20*'0. Assumptions'!$C$9 -> 364000
A21: FIELD OFFICER TRAINING (10 REGIONS)
A22: Train-the-Trainer Programme (20 regional trainers) | B22: 8000 | C22: 1 | D22: =B22*C22 -> 8000 | E22: =D22*'0. Assumptions'!$C$9 -> 104000
A23: Field Officer Training — Region 1 (Greater Accra) | B23: 3500 | C23: 2 | D23: =B23*C23 -> 7000 | E23: =D23*'0. Assumptions'!$C$9 -> 91000
A24: Field Officer Training — Region 2 (Ashanti) | B24: 3500 | C24: 2 | D24: =B24*C24 -> 7000 | E24: =D24*'0. Assumptions'!$C$9 -> 91000
A25: Field Officer Training — Region 3 (Western) | B25: 3500 | C25: 2 | D25: =B25*C25 -> 7000 | E25: =D25*'0. Assumptions'!$C$9 -> 91000
A26: Field Officer Training — Region 4 (Eastern) | B26: 3500 | C26: 2 | D26: =B26*C26 -> 7000 | E26: =D26*'0. Assumptions'!$C$9 -> 91000
A27: Field Officer Training — Region 5 (Brong-Ahafo) | B27: 3500 | C27: 2 | D27: =B27*C27 -> 7000 | E27: =D27*'0. Assumptions'!$C$9 -> 91000
A28: Field Officer Training — Regions 6–10 (Northern zones) | B28: 4500 | C28: 2 | D28: =B28*C28 -> 9000 | E28: =D28*'0. Assumptions'!$C$9 -> 117000
A29: Field Training Logistics (venue, transport, per diem/region) | B29: 1200 | C29: 10 | D29: =B29*C29 -> 12000 | E29: =D29*'0. Assumptions'!$C$9 -> 156000
A30: Sub-Total | D30: =SUM(D22:D29) -> 64000 | E30: =D30*'0. Assumptions'!$C$9 -> 832000
A31: INDUSTRY ACTOR TRAINING
A32: Tier 1 & 2 Licensed Buyer Training (30 sessions) | B32: 2500 | C32: 30 | D32: =B32*C32 -> 75000 | E32: =D32*'0. Assumptions'!$C$9 -> 975000
A33: Kitchen / Aggregator Operator Training (20 sessions) | B33: 2000 | C33: 20 | D33: =B33*C33 -> 40000 | E33: =D33*'0. Assumptions'!$C$9 -> 520000
A34: Transporter & Logistics Operator Training (15 sessions) | B34: 1800 | C34: 15 | D34: =B34*C34 -> 27000 | E34: =D34*'0. Assumptions'!$C$9 -> 351000
A35: ASM / Small-Scale Miner Sensitisation (40 community sessions) | B35: 1500 | C35: 40 | D35: =B35*C35 -> 60000 | E35: =D35*'0. Assumptions'!$C$9 -> 780000
A36: Large-Scale Mine Corporate User Training (10 companies) | B36: 3000 | C36: 10 | D36: =B36*C36 -> 30000 | E36: =D36*'0. Assumptions'!$C$9 -> 390000
A37: Export / Trading Company Training (15 sessions) | B37: 2500 | C37: 15 | D37: =B37*C37 -> 37500 | E37: =D37*'0. Assumptions'!$C$9 -> 487500
A38: Sub-Total | D38: =SUM(D32:D37) -> 269500 | E38: =D38*'0. Assumptions'!$C$9 -> 3503500
A39: REFRESHER & STABILISATION TRAINING (Months 7–18)
A40: Quarterly refresher workshops (all roles, 4 cycles) | B40: 12000 | C40: 1 | D40: =B40*C40 -> 12000 | E40: =D40*'0. Assumptions'!$C$9 -> 156000
A41: On-demand coaching & remote support sessions | B41: 8000 | C41: 1 | D41: =B41*C41 -> 8000 | E41: =D41*'0. Assumptions'!$C$9 -> 104000
A42: New feature release training (per quarterly release) | B42: 4000 | C42: 4 | D42: =B42*C42 -> 16000 | E42: =D42*'0. Assumptions'!$C$9 -> 208000
A43: Helpdesk script & FAQ update training | B43: 3000 | C43: 1 | D43: =B43*C43 -> 3000 | E43: =D43*'0. Assumptions'!$C$9 -> 39000
A44: Sub-Total | D44: =SUM(D40:D43) -> 39000 | E44: =D44*'0. Assumptions'!$C$9 -> 507000
A45: CHANGE MANAGEMENT PROGRAMME
A46: Stakeholder communication strategy & materials | B46: 8000 | C46: 1 | D46: =B46*C46 -> 8000 | E46: =D46*'0. Assumptions'!$C$9 -> 104000
A47: Change champion identification & coaching | B47: 6000 | C47: 1 | D47: =B47*C47 -> 6000 | E47: =D47*'0. Assumptions'!$C$9 -> 78000
A48: Resistance management & user adoption workshops | B48: 5000 | C48: 1 | D48: =B48*C48 -> 5000 | E48: =D48*'0. Assumptions'!$C$9 -> 65000
A49: Adoption monitoring & reporting (18 months) | B49: 6000 | C49: 1 | D49: =B49*C49 -> 6000 | E49: =D49*'0. Assumptions'!$C$9 -> 78000
A50: Sub-Total | D50: =SUM(D46:D49) -> 25000 | E50: =D50*'0. Assumptions'!$C$9 -> 325000
A51: TOTAL TRAINING & CAPACITY BUILDING | D51: =D12+D20+D30+D38+D44+D50 -> 548500 | E51: =D51*'0. Assumptions'!$C$9 -> 7130500

Sheet 10. Integration Costs
A1: SECTION 10 — INTEGRATION & INTEROPERABILITY COSTS
A2: Integration / API Activity | B2: Unit Cost (USD) | C2: Qty | D2: Total USD | E2: Total GHS
A3: GOVERNMENT AGENCY INTEGRATIONS
A4: Minerals Commission — Licensing & Cadastre API (dev+test) | B4: 45000 | C4: 1 | D4: =B4*C4 -> 45000 | E4: =D4*'0. Assumptions'!$C$9 -> 585000
A5: Ghana Revenue Authority — Customs Export Verification API | B5: 40000 | C5: 1 | D5: =B5*C5 -> 40000 | E5: =D5*'0. Assumptions'!$C$9 -> 520000
A6: Bank of Ghana — Payment & FX Reporting API | B6: 45000 | C6: 1 | D6: =B6*C6 -> 45000 | E6: =D6*'0. Assumptions'!$C$9 -> 585000
A7: Financial Intelligence Centre — STR/SAR e-Filing | B7: 38000 | C7: 1 | D7: =B7*C7 -> 38000 | E7: =D7*'0. Assumptions'!$C$9 -> 494000
A8: Environmental Protection Authority — Permit API | B8: 32000 | C8: 1 | D8: =B8*C8 -> 32000 | E8: =D8*'0. Assumptions'!$C$9 -> 416000
A9: Water Resources Commission — Compliance API | B9: 28000 | C9: 1 | D9: =B9*C9 -> 28000 | E9: =D9*'0. Assumptions'!$C$9 -> 364000
A10: Ghana Card / NIA — Identity Verification API | B10: 20000 | C10: 1 | D10: =B10*C10 -> 20000 | E10: =D10*'0. Assumptions'!$C$9 -> 260000
A11: Government Agency Integration Testing & Validation | B11: 25000 | C11: 1 | D11: =B11*C11 -> 25000 | E11: =D11*'0. Assumptions'!$C$9 -> 325000
A12: Ongoing Integration Maintenance (12 months) | B12: 18000 | C12: 1 | D12: =B12*C12 -> 18000 | E12: =D12*'0. Assumptions'!$C$9 -> 234000
A13: Sub-Total | D13: =SUM(D4:D12) -> 291000 | E13: =D13*'0. Assumptions'!$C$9 -> 3783000
A14: PAYMENT & FINANCIAL INTEGRATIONS
A15: MTN Mobile Money API Integration & Certification | B15: 12000 | C15: 1 | D15: =B15*C15 -> 12000 | E15: =D15*'0. Assumptions'!$C$9 -> 156000
A16: Vodafone Cash API Integration | B16: 10000 | C16: 1 | D16: =B16*C16 -> 10000 | E16: =D16*'0. Assumptions'!$C$9 -> 130000
A17: AirtelTigo Money API Integration | B17: 8000 | C17: 1 | D17: =B17*C17 -> 8000 | E17: =D17*'0. Assumptions'!$C$9 -> 104000
A18: Bank Payment Gateway Integration (GhIPSS) | B18: 15000 | C18: 1 | D18: =B18*C18 -> 15000 | E18: =D18*'0. Assumptions'!$C$9 -> 195000
A19: Transaction Fee Provision (est. avg 0.5% — 18 months) | B19: 18000 | C19: 1 | D19: =B19*C19 -> 18000 | E19: =D19*'0. Assumptions'!$C$9 -> 234000
A20: Sub-Total | D20: =SUM(D15:D19) -> 63000 | E20: =D20*'0. Assumptions'!$C$9 -> 819000
A21: COMPLIANCE & SCREENING INTEGRATIONS
A22: AML/CFT Sanctions Screening API (OFAC/EU/UN lists) | B22: 24000 | C22: 1 | D22: =B22*C22 -> 24000 | E22: =D22*'0. Assumptions'!$C$9 -> 312000
A23: PEP & Adverse Media Screening Service | B23: 18000 | C23: 1 | D23: =B23*C23 -> 18000 | E23: =D23*'0. Assumptions'!$C$9 -> 234000
A24: Beneficial Ownership Verification Service | B24: 12000 | C24: 1 | D24: =B24*C24 -> 12000 | E24: =D24*'0. Assumptions'!$C$9 -> 156000
A25: Annual API subscription renewal (stabilisation phase) | B25: 15000 | C25: 1 | D25: =B25*C25 -> 15000 | E25: =D25*'0. Assumptions'!$C$9 -> 195000
A26: Sub-Total | D26: =SUM(D22:D25) -> 69000 | E26: =D26*'0. Assumptions'!$C$9 -> 897000
A27: COMMUNICATION & NOTIFICATION INTEGRATIONS
A28: Bulk SMS Gateway — MTN/Vodafone Ghana (setup + 18 mths) | B28: 9600 | C28: 1 | D28: =B28*C28 -> 9600 | E28: =D28*'0. Assumptions'!$C$9 -> 124800
A29: Email Delivery Service (SendGrid/AWS SES — 18 mths) | B29: 3600 | C29: 1 | D29: =B29*C29 -> 3600 | E29: =D29*'0. Assumptions'!$C$9 -> 46800
A30: WhatsApp Business API (optional notifications) | B30: 6000 | C30: 1 | D30: =B30*C30 -> 6000 | E30: =D30*'0. Assumptions'!$C$9 -> 78000
A31: Push Notification Service (FCM/APNs) | B31: 2400 | C31: 1 | D31: =B31*C31 -> 2400 | E31: =D31*'0. Assumptions'!$C$9 -> 31200
A32: Sub-Total | D32: =SUM(D28:D31) -> 21600 | E32: =D32*'0. Assumptions'!$C$9 -> 280800
A33: GEOLOCATION & MAPPING INTEGRATIONS
A34: Google Maps Platform API (Places, Geocoding, Routes) | B34: 9000 | C34: 1 | D34: =B34*C34 -> 9000 | E34: =D34*'0. Assumptions'!$C$9 -> 117000
A35: GPS Tracker Fleet Management Integration | B35: 5000 | C35: 1 | D35: =B35*C35 -> 5000 | E35: =D35*'0. Assumptions'!$C$9 -> 65000
A36: Geofencing Rules Engine (mining zone boundaries) | B36: 8000 | C36: 1 | D36: =B36*C36 -> 8000 | E36: =D36*'0. Assumptions'!$C$9 -> 104000
A37: Sub-Total | D37: =SUM(D34:D36) -> 22000 | E37: =D37*'0. Assumptions'!$C$9 -> 286000
A38: API MANAGEMENT & DEVELOPER INFRASTRUCTURE
A39: API Gateway Setup & Configuration (Kong/AWS API GW) | B39: 12000 | C39: 1 | D39: =B39*C39 -> 12000 | E39: =D39*'0. Assumptions'!$C$9 -> 156000
A40: API Documentation Portal (Swagger/Redoc) | B40: 5000 | C40: 1 | D40: =B40*C40 -> 5000 | E40: =D40*'0. Assumptions'!$C$9 -> 65000
A41: API Versioning & Lifecycle Management Tools | B41: 4000 | C41: 1 | D41: =B41*C41 -> 4000 | E41: =D41*'0. Assumptions'!$C$9 -> 52000
A42: Developer Sandbox Environment (18 months) | B42: 6000 | C42: 1 | D42: =B42*C42 -> 6000 | E42: =D42*'0. Assumptions'!$C$9 -> 78000
A43: API Security — Rate Limiting, OAuth2, mTLS | B43: 8000 | C43: 1 | D43: =B43*C43 -> 8000 | E43: =D43*'0. Assumptions'!$C$9 -> 104000
A44: Sub-Total | D44: =SUM(D39:D43) -> 35000 | E44: =D44*'0. Assumptions'!$C$9 -> 455000
A45: DATA MIGRATION & LEGACY INTEGRATION
A46: Existing GoldBod Records — ETL Extraction & Cleansing | B46: 18000 | C46: 1 | D46: =B46*C46 -> 18000 | E46: =D46*'0. Assumptions'!$C$9 -> 234000
A47: Historical Transaction Data Migration & Validation | B47: 15000 | C47: 1 | D47: =B47*C47 -> 15000 | E47: =D47*'0. Assumptions'!$C$9 -> 195000
A48: Parallel Run Support (legacy + new system overlap) | B48: 10000 | C48: 1 | D48: =B48*C48 -> 10000 | E48: =D48*'0. Assumptions'!$C$9 -> 130000
A49: Data Quality Assessment & Remediation | B49: 8000 | C49: 1 | D49: =B49*C49 -> 8000 | E49: =D49*'0. Assumptions'!$C$9 -> 104000
A50: Sub-Total | D50: =SUM(D46:D49) -> 51000 | E50: =D50*'0. Assumptions'!$C$9 -> 663000
A51: TOTAL INTEGRATION & INTEROPERABILITY COSTS | D51: =D13+D20+D26+D32+D37+D44+D50 -> 552600 | E51: =D51*'0. Assumptions'!$C$9 -> 7183800

Sheet 11. Testing & QA
A1: SECTION 11 — TESTING & QUALITY ASSURANCE COSTS
A2: Testing Activity | B2: Unit Cost (USD) | C2: Qty | D2: Total USD | E2: Total GHS
A3: TEST INFRASTRUCTURE & ENVIRONMENTS
A4: Test Environment Hosting — UAT + Staging (6 months) | B4: 5000 | C4: 6 | D4: =B4*C4 -> 30000 | E4: =D4*'0. Assumptions'!$C$9 -> 390000
A5: Test Data Generation & Masking Tools | B5: 6000 | C5: 1 | D5: =B5*C5 -> 6000 | E5: =D5*'0. Assumptions'!$C$9 -> 78000
A6: Test Automation Framework Setup (Selenium/Appium/Cypress) | B6: 18000 | C6: 1 | D6: =B6*C6 -> 18000 | E6: =D6*'0. Assumptions'!$C$9 -> 234000
A7: Performance Testing Tool — JMeter/Gatling Setup | B7: 8000 | C7: 1 | D7: =B7*C7 -> 8000 | E7: =D7*'0. Assumptions'!$C$9 -> 104000
A8: Mobile Device Testing Lab (Android/iOS physical devices) | B8: 12000 | C8: 1 | D8: =B8*C8 -> 12000 | E8: =D8*'0. Assumptions'!$C$9 -> 156000
A9: BrowserStack Cloud Testing Subscription (6 months) | B9: 3000 | C9: 6 | D9: =B9*C9 -> 18000 | E9: =D9*'0. Assumptions'!$C$9 -> 234000
A10: Defect Tracking Tool License — Jira (18 months) | B10: 2000 | C10: 1 | D10: =B10*C10 -> 2000 | E10: =D10*'0. Assumptions'!$C$9 -> 26000
A11: Sub-Total | D11: =SUM(D4:D10) -> 94000 | E11: =D11*'0. Assumptions'!$C$9 -> 1222000
A12: FUNCTIONAL TESTING
A13: Unit Testing (developer-led, covered in dev cost) | B13: 0 | C13: 1 | D13: =B13*C13 -> 0 | E13: =D13*'0. Assumptions'!$C$9 -> 0
A14: Integration Testing — all 6 agency APIs | B14: 15000 | C14: 1 | D14: =B14*C14 -> 15000 | E14: =D14*'0. Assumptions'!$C$9 -> 195000
A15: System Testing — end-to-end functional scenarios | B15: 12000 | C15: 1 | D15: =B15*C15 -> 12000 | E15: =D15*'0. Assumptions'!$C$9 -> 156000
A16: Regression Testing (per sprint — 12 sprints) | B16: 2000 | C16: 12 | D16: =B16*C16 -> 24000 | E16: =D16*'0. Assumptions'!$C$9 -> 312000
A17: User Acceptance Testing — GoldBod staff (facilitated) | B17: 15000 | C17: 1 | D17: =B17*C17 -> 15000 | E17: =D17*'0. Assumptions'!$C$9 -> 195000
A18: UAT — Industry actors (buyers, miners, transporters) | B18: 10000 | C18: 1 | D18: =B18*C18 -> 10000 | E18: =D18*'0. Assumptions'!$C$9 -> 130000
A19: Sub-Total | D19: =SUM(D13:D18) -> 76000 | E19: =D19*'0. Assumptions'!$C$9 -> 988000
A20: NON-FUNCTIONAL TESTING
A21: Performance & Load Testing (target: 10,000 concurrent users) | B21: 18000 | C21: 1 | D21: =B21*C21 -> 18000 | E21: =D21*'0. Assumptions'!$C$9 -> 234000
A22: Stress Testing & Capacity Planning | B22: 8000 | C22: 1 | D22: =B22*C22 -> 8000 | E22: =D22*'0. Assumptions'!$C$9 -> 104000
A23: Scalability Testing — national transaction volumes | B23: 6000 | C23: 1 | D23: =B23*C23 -> 6000 | E23: =D23*'0. Assumptions'!$C$9 -> 78000
A24: Offline Mode & Network Resilience Testing | B24: 5000 | C24: 1 | D24: =B24*C24 -> 5000 | E24: =D24*'0. Assumptions'!$C$9 -> 65000
A25: Disaster Recovery Failover Testing | B25: 8000 | C25: 1 | D25: =B25*C25 -> 8000 | E25: =D25*'0. Assumptions'!$C$9 -> 104000
A26: Blockchain Consensus & Fault Tolerance Testing | B26: 12000 | C26: 1 | D26: =B26*C26 -> 12000 | E26: =D26*'0. Assumptions'!$C$9 -> 156000
A27: Sub-Total | D27: =SUM(D21:D26) -> 57000 | E27: =D27*'0. Assumptions'!$C$9 -> 741000
A28: SECURITY TESTING
A29: External Penetration Testing — Web & API (OWASP top 10) | B29: 35000 | C29: 1 | D29: =B29*C29 -> 35000 | E29: =D29*'0. Assumptions'!$C$9 -> 455000
A30: Mobile App Security Testing (Android & iOS) | B30: 15000 | C30: 1 | D30: =B30*C30 -> 15000 | E30: =D30*'0. Assumptions'!$C$9 -> 195000
A31: Blockchain Smart Contract Security Audit | B31: 25000 | C31: 1 | D31: =B31*C31 -> 25000 | E31: =D31*'0. Assumptions'!$C$9 -> 325000
A32: Vulnerability Assessment & Remediation Review | B32: 12000 | C32: 1 | D32: =B32*C32 -> 12000 | E32: =D32*'0. Assumptions'!$C$9 -> 156000
A33: Data Privacy & GDPR/Act 843 Compliance Scan | B33: 8000 | C33: 1 | D33: =B33*C33 -> 8000 | E33: =D33*'0. Assumptions'!$C$9 -> 104000
A34: Source Code Review (external firm) | B34: 18000 | C34: 1 | D34: =B34*C34 -> 18000 | E34: =D34*'0. Assumptions'!$C$9 -> 234000
A35: Sub-Total | D35: =SUM(D29:D34) -> 113000 | E35: =D35*'0. Assumptions'!$C$9 -> 1469000
A36: COMPLIANCE & STANDARDS TESTING
A37: LBMA Responsible Gold Guidance Compliance Assessment | B37: 20000 | C37: 1 | D37: =B37*C37 -> 20000 | E37: =D37*'0. Assumptions'!$C$9 -> 260000
A38: OECD Due Diligence Guidance Alignment Review | B38: 15000 | C38: 1 | D38: =B38*C38 -> 15000 | E38: =D38*'0. Assumptions'!$C$9 -> 195000
A39: ISO 27001 Gap Analysis & Internal Audit | B39: 18000 | C39: 1 | D39: =B39*C39 -> 18000 | E39: =D39*'0. Assumptions'!$C$9 -> 234000
A40: AML/CFT Controls Testing (FATF Recommendations) | B40: 12000 | C40: 1 | D40: =B40*C40 -> 12000 | E40: =D40*'0. Assumptions'!$C$9 -> 156000
A41: Accessibility Testing (WCAG 2.1 — government portal) | B41: 5000 | C41: 1 | D41: =B41*C41 -> 5000 | E41: =D41*'0. Assumptions'!$C$9 -> 65000
A42: Sub-Total | D42: =SUM(D37:D41) -> 70000 | E42: =D42*'0. Assumptions'!$C$9 -> 910000
A43: TEST DOCUMENTATION & REPORTING
A44: Test Strategy & Master Test Plan | B44: 6000 | C44: 1 | D44: =B44*C44 -> 6000 | E44: =D44*'0. Assumptions'!$C$9 -> 78000
A45: Test Cases & Test Scripts (all modules) | B45: 8000 | C45: 1 | D45: =B45*C45 -> 8000 | E45: =D45*'0. Assumptions'!$C$9 -> 104000
A46: Traceability Matrix (requirements ↔ test cases) | B46: 4000 | C46: 1 | D46: =B46*C46 -> 4000 | E46: =D46*'0. Assumptions'!$C$9 -> 52000
A47: Test Completion Reports & Sign-off Packs | B47: 3000 | C47: 1 | D47: =B47*C47 -> 3000 | E47: =D47*'0. Assumptions'!$C$9 -> 39000
A48: Defect Reports & Root Cause Analysis Documentation | B48: 3000 | C48: 1 | D48: =B48*C48 -> 3000 | E48: =D48*'0. Assumptions'!$C$9 -> 39000
A49: Sub-Total | D49: =SUM(D44:D48) -> 24000 | E49: =D49*'0. Assumptions'!$C$9 -> 312000
A50: TOTAL TESTING & QA COSTS | D50: =D11+D19+D27+D35+D42+D49 -> 434000 | E50: =D50*'0. Assumptions'!$C$9 -> 5642000

Sheet 12. PMO & Governance
A1: SECTION 12 — PROJECT MANAGEMENT & GOVERNANCE COSTS
A2: PMO Activity / Item | B2: Unit Cost (USD) | C2: Qty / Mths | D2: Total USD | E2: Total GHS
A3: PMO SETUP & TOOLS
A4: PMO Office Setup & Fit-Out (18 months rental incl.) | B4: 3000 | C4: 18 | D4: =B4*C4 -> 54000 | E4: =D4*'0. Assumptions'!$C$9 -> 702000
A5: Project Management Software (MS Project / Smartsheet) | B5: 2500 | C5: 1 | D5: =B5*C5 -> 2500 | E5: =D5*'0. Assumptions'!$C$9 -> 32500
A6: Document Management System (SharePoint / Confluence) | B6: 2000 | C6: 1 | D6: =B6*C6 -> 2000 | E6: =D6*'0. Assumptions'!$C$9 -> 26000
A7: Time Tracking & Resource Management Tool | B7: 1200 | C7: 1 | D7: =B7*C7 -> 1200 | E7: =D7*'0. Assumptions'!$C$9 -> 15600
A8: Risk Management Tool License | B8: 1500 | C8: 1 | D8: =B8*C8 -> 1500 | E8: =D8*'0. Assumptions'!$C$9 -> 19500
A9: Gantt Scheduling & Baseline Management | B9: 1000 | C9: 1 | D9: =B9*C9 -> 1000 | E9: =D9*'0. Assumptions'!$C$9 -> 13000
A10: Video Conferencing & Collaboration (Zoom/Teams — 18 mths) | B10: 3600 | C10: 1 | D10: =B10*C10 -> 3600 | E10: =D10*'0. Assumptions'!$C$9 -> 46800
A11: Sub-Total | D11: =SUM(D4:D10) -> 65800 | E11: =D11*'0. Assumptions'!$C$9 -> 855400
A12: GOVERNANCE & REPORTING
A13: Monthly Steering Committee Meetings (venue + facilitation) | B13: 1200 | C13: 18 | D13: =B13*C13 -> 21600 | E13: =D13*'0. Assumptions'!$C$9 -> 280800
A14: Technical Review Board Meetings (bi-monthly, 9 meetings) | B14: 800 | C14: 9 | D14: =B14*C14 -> 7200 | E14: =D14*'0. Assumptions'!$C$9 -> 93600
A15: Monthly Progress Reports Preparation | B15: 1500 | C15: 18 | D15: =B15*C15 -> 27000 | E15: =D15*'0. Assumptions'!$C$9 -> 351000
A16: Quarterly Financial Reports | B16: 2000 | C16: 6 | D16: =B16*C16 -> 12000 | E16: =D16*'0. Assumptions'!$C$9 -> 156000
A17: Risk & Issue Log Maintenance | B17: 500 | C17: 18 | D17: =B17*C17 -> 9000 | E17: =D17*'0. Assumptions'!$C$9 -> 117000
A18: Change Request Management & Documentation | B18: 1000 | C18: 18 | D18: =B18*C18 -> 18000 | E18: =D18*'0. Assumptions'!$C$9 -> 234000
A19: Quality Assurance Reviews (monthly) | B19: 1000 | C19: 18 | D19: =B19*C19 -> 18000 | E19: =D19*'0. Assumptions'!$C$9 -> 234000
A20: Compliance Status Reports (bi-monthly) | B20: 800 | C20: 9 | D20: =B20*C20 -> 7200 | E20: =D20*'0. Assumptions'!$C$9 -> 93600
A21: Sub-Total | D21: =SUM(D13:D20) -> 120000 | E21: =D21*'0. Assumptions'!$C$9 -> 1560000
A22: STAKEHOLDER ENGAGEMENT & EVENTS
A23: Project Launch Kickoff Event | B23: 8000 | C23: 1 | D23: =B23*C23 -> 8000 | E23: =D23*'0. Assumptions'!$C$9 -> 104000
A24: National Go-Live Ceremony | B24: 15000 | C24: 1 | D24: =B24*C24 -> 15000 | E24: =D24*'0. Assumptions'!$C$9 -> 195000
A25: Regional Stakeholder Engagement Workshops (10 regions) | B25: 3000 | C25: 10 | D25: =B25*C25 -> 30000 | E25: =D25*'0. Assumptions'!$C$9 -> 390000
A26: Ministerial / Board Briefing Packs (quarterly) | B26: 1500 | C26: 6 | D26: =B26*C26 -> 9000 | E26: =D26*'0. Assumptions'!$C$9 -> 117000
A27: Public Relations & Media Engagement Programme | B27: 10000 | C27: 1 | D27: =B27*C27 -> 10000 | E27: =D27*'0. Assumptions'!$C$9 -> 130000
A28: Communication Materials (brochures, flyers, rollup banners) | B28: 6000 | C28: 1 | D28: =B28*C28 -> 6000 | E28: =D28*'0. Assumptions'!$C$9 -> 78000
A29: Project Close-Out Workshop & Handover Ceremony | B29: 8000 | C29: 1 | D29: =B29*C29 -> 8000 | E29: =D29*'0. Assumptions'!$C$9 -> 104000
A30: Sub-Total | D30: =SUM(D23:D29) -> 86000 | E30: =D30*'0. Assumptions'!$C$9 -> 1118000
A31: TRAVEL & LOGISTICS
A32: International Airfare — Expert Missions to Ghana (4 visits) | B32: 5000 | C32: 4 | D32: =B32*C32 -> 20000 | E32: =D32*'0. Assumptions'!$C$9 -> 260000
A33: Accommodation & Per Diem — International Experts (4 stays) | B33: 3500 | C33: 4 | D33: =B33*C33 -> 14000 | E33: =D33*'0. Assumptions'!$C$9 -> 182000
A34: Domestic Air Travel — Regional Oversight Visits | B34: 1500 | C34: 10 | D34: =B34*C34 -> 15000 | E34: =D34*'0. Assumptions'!$C$9 -> 195000
A35: Ground Transport — Project Team (18 months) | B35: 1000 | C35: 18 | D35: =B35*C35 -> 18000 | E35: =D35*'0. Assumptions'!$C$9 -> 234000
A36: Equipment Transportation & Delivery Logistics | B36: 8000 | C36: 1 | D36: =B36*C36 -> 8000 | E36: =D36*'0. Assumptions'!$C$9 -> 104000
A37: Emergency / Urgent Travel Reserve | B37: 5000 | C37: 1 | D37: =B37*C37 -> 5000 | E37: =D37*'0. Assumptions'!$C$9 -> 65000
A38: Sub-Total | D38: =SUM(D32:D37) -> 80000 | E38: =D38*'0. Assumptions'!$C$9 -> 1040000
A39: ADMINISTRATIVE & OFFICE COSTS
A40: Office Utilities & Internet (18 months) | B40: 1000 | C40: 18 | D40: =B40*C40 -> 18000 | E40: =D40*'0. Assumptions'!$C$9 -> 234000
A41: Printing, Stationery & Office Supplies | B41: 500 | C41: 18 | D41: =B41*C41 -> 9000 | E41: =D41*'0. Assumptions'!$C$9 -> 117000
A42: Courier & Document Delivery | B42: 300 | C42: 18 | D42: =B42*C42 -> 5400 | E42: =D42*'0. Assumptions'!$C$9 -> 70200
A43: Bank Charges & Transfer Fees (18 months) | B43: 400 | C43: 18 | D43: =B43*C43 -> 7200 | E43: =D43*'0. Assumptions'!$C$9 -> 93600
A44: Contingency Admin Reserve | B44: 5000 | C44: 1 | D44: =B44*C44 -> 5000 | E44: =D44*'0. Assumptions'!$C$9 -> 65000
A45: Sub-Total | D45: =SUM(D40:D44) -> 44600 | E45: =D45*'0. Assumptions'!$C$9 -> 579800
A46: TOTAL PMO & GOVERNANCE COSTS | D46: =D11+D21+D30+D38+D45 -> 396400 | E46: =D46*'0. Assumptions'!$C$9 -> 5153200

Sheet 13. Compliance & Regulatory
A1: SECTION 13 — COMPLIANCE & REGULATORY COSTS
A2: Compliance Activity | B2: Estimated Cost (USD) | C2: Estimated Cost (GHS)
A3: GHANA LEGAL & REGULATORY COMPLIANCE
A4: Data Protection Act 843 — DPIA & Privacy Impact Assessment | B4: 12000 | C4: =B4*'0. Assumptions'!$C$9 -> 156000
A5: Privacy Policy & Data Processing Agreements (legal drafting) | B5: 8000 | C5: =B5*'0. Assumptions'!$C$9 -> 104000
A6: Data Protection Commission Registration & Filing | B6: 2000 | C6: =B6*'0. Assumptions'!$C$9 -> 26000
A7: AML Act 1044 — AML/CFT Policy & Controls Framework | B7: 10000 | C7: =B7*'0. Assumptions'!$C$9 -> 130000
A8: Ghana Gold Board Act 1140 — Regulatory Alignment Review | B8: 8000 | C8: =B8*'0. Assumptions'!$C$9 -> 104000
A9: Public Procurement Act Compliance — Documentation & Filings | B9: 5000 | C9: =B9*'0. Assumptions'!$C$9 -> 65000
A10: Withholding Tax Provision on Foreign Service Payments | B10: 20000 | C10: =B10*'0. Assumptions'!$C$9 -> 260000
A11: VAT on Applicable Local Costs (15% provision) | B11: 15000 | C11: =B11*'0. Assumptions'!$C$9 -> 195000
A12: SSNIT, PAYE & Pension Compliance Administration (18 months) | B12: 12000 | C12: =B12*'0. Assumptions'!$C$9 -> 156000
A13: Tax Clearance Certificate & GRA Filings | B13: 3000 | C13: =B13*'0. Assumptions'!$C$9 -> 39000
A14: PPA Supplier Registration & Bidding Documentation | B14: 4000 | C14: =B14*'0. Assumptions'!$C$9 -> 52000
A15: Sub-Total | B15: =SUM(B4:B14) -> 99000 | C15: =B15*'0. Assumptions'!$C$9 -> 1287000
A16: INTERNATIONAL STANDARDS COMPLIANCE
A17: OECD Due Diligence Guidance — Framework Implementation | B17: 15000 | C17: =B17*'0. Assumptions'!$C$9 -> 195000
A18: LBMA Responsible Gold Guidance — Compliance Programme | B18: 18000 | C18: =B18*'0. Assumptions'!$C$9 -> 234000
A19: FATF Recommendations Alignment — Controls Mapping | B19: 10000 | C19: =B19*'0. Assumptions'!$C$9 -> 130000
A20: RMI (Responsible Minerals Initiative) Compliance Assessment | B20: 12000 | C20: =B20*'0. Assumptions'!$C$9 -> 156000
A21: ICGLR Certification Programme Alignment | B21: 8000 | C21: =B21*'0. Assumptions'!$C$9 -> 104000
A22: Sub-Total | B22: =SUM(B17:B21) -> 63000 | C22: =B22*'0. Assumptions'!$C$9 -> 819000
A23: INFORMATION SECURITY & CERTIFICATIONS
A24: ISO 27001 Gap Analysis & Readiness Assessment | B24: 18000 | C24: =B24*'0. Assumptions'!$C$9 -> 234000
A25: ISO 27001 Certification Audit (external certification body) | B25: 25000 | C25: =B25*'0. Assumptions'!$C$9 -> 325000
A26: SOC 2 Type II Readiness & Audit | B26: 30000 | C26: =B26*'0. Assumptions'!$C$9 -> 390000
A27: Blockchain Technology Certification (specialist body) | B27: 8000 | C27: =B27*'0. Assumptions'!$C$9 -> 104000
A28: Annual Security Compliance Review (18 months) | B28: 10000 | C28: =B28*'0. Assumptions'!$C$9 -> 130000
A29: Sub-Total | B29: =SUM(B24:B28) -> 91000 | C29: =B29*'0. Assumptions'!$C$9 -> 1183000
A30: INTELLECTUAL PROPERTY & CONTRACTS
A31: IP Assignment Agreement — Full Source Code & Documentation | B31: 8000 | C31: =B31*'0. Assumptions'!$C$9 -> 104000
A32: Open Source Licence Compliance Review | B32: 4000 | C32: =B32*'0. Assumptions'!$C$9 -> 52000
A33: Third-Party Vendor Contract Review (legal) | B33: 6000 | C33: =B33*'0. Assumptions'!$C$9 -> 78000
A34: Source Code Escrow Agreement Setup & Annual Fee | B34: 5000 | C34: =B34*'0. Assumptions'!$C$9 -> 65000
A35: Patent / Trademark Searches (if applicable) | B35: 3000 | C35: =B35*'0. Assumptions'!$C$9 -> 39000
A36: Sub-Total | B36: =SUM(B31:B35) -> 26000 | C36: =B36*'0. Assumptions'!$C$9 -> 338000
A37: INSURANCE
A38: Professional Indemnity Insurance (18 months) | B38: 18000 | C38: =B38*'0. Assumptions'!$C$9 -> 234000
A39: Cyber Liability Insurance (18 months) | B39: 14000 | C39: =B39*'0. Assumptions'!$C$9 -> 182000
A40: Project Insurance & Contractor All-Risk (18 months) | B40: 10000 | C40: =B40*'0. Assumptions'!$C$9 -> 130000
A41: Hardware & Equipment Insurance (18 months) | B41: 8000 | C41: =B41*'0. Assumptions'!$C$9 -> 104000
A42: Employer's Liability Insurance (Ghana staff, 18 months) | B42: 6000 | C42: =B42*'0. Assumptions'!$C$9 -> 78000
A43: Sub-Total | B43: =SUM(B38:B42) -> 56000 | C43: =B43*'0. Assumptions'!$C$9 -> 728000
A44: AUDIT & EXTERNAL ASSURANCE
A45: Annual Financial Audit (Year 1 project accounts) | B45: 12000 | C45: =B45*'0. Assumptions'!$C$9 -> 156000
A46: External IT Audit — System Controls & Access Review | B46: 10000 | C46: =B46*'0. Assumptions'!$C$9 -> 130000
A47: AML/CFT Controls Effectiveness Review (external firm) | B47: 12000 | C47: =B47*'0. Assumptions'!$C$9 -> 156000
A48: Data Protection Audit (post go-live, Month 9) | B48: 8000 | C48: =B48*'0. Assumptions'!$C$9 -> 104000
A49: Project Close-Out Audit & Asset Verification | B49: 6000 | C49: =B49*'0. Assumptions'!$C$9 -> 78000
A50: Sub-Total | B50: =SUM(B45:B49) -> 48000 | C50: =B50*'0. Assumptions'!$C$9 -> 624000
A51: TOTAL COMPLIANCE & REGULATORY COSTS | B51: =B15+B22+B29+B36+B43+B50 -> 383000 | C51: =B51*'0. Assumptions'!$C$9 -> 4979000

Sheet 14. Documentation
A1: SECTION 14 — DOCUMENTATION & DELIVERABLES COSTS
A2: Document / Deliverable | B2: Estimated Cost (USD) | C2: Estimated Cost (GHS)
A3: TECHNICAL DOCUMENTATION
A4: System Architecture & Design Document (SDD) | B4: 8000 | C4: =B4*'0. Assumptions'!$C$9 -> 104000
A5: Blockchain Network Architecture Specification | B5: 5000 | C5: =B5*'0. Assumptions'!$C$9 -> 65000
A6: API Reference Documentation & Swagger/OpenAPI Specs | B6: 5000 | C6: =B6*'0. Assumptions'!$C$9 -> 65000
A7: Database Schema & Data Dictionary | B7: 4000 | C7: =B7*'0. Assumptions'!$C$9 -> 52000
A8: Security Architecture & Threat Model Document | B8: 5000 | C8: =B8*'0. Assumptions'!$C$9 -> 65000
A9: Infrastructure-as-Code Documentation (Terraform/Ansible) | B9: 3000 | C9: =B9*'0. Assumptions'!$C$9 -> 39000
A10: DevOps & CI/CD Pipeline Documentation | B10: 3000 | C10: =B10*'0. Assumptions'!$C$9 -> 39000
A11: Disaster Recovery & Business Continuity Plan (BCP) | B11: 6000 | C11: =B11*'0. Assumptions'!$C$9 -> 78000
A12: Source Code Repository Documentation & README files | B12: 3000 | C12: =B12*'0. Assumptions'!$C$9 -> 39000
A13: Sub-Total | B13: =SUM(B4:B12) -> 42000 | C13: =B13*'0. Assumptions'!$C$9 -> 546000
A14: USER-FACING DOCUMENTATION
A15: System Administrator Manual | B15: 6000 | C15: =B15*'0. Assumptions'!$C$9 -> 78000
A16: Field Officer User Manual (Android App) | B16: 5000 | C16: =B16*'0. Assumptions'!$C$9 -> 65000
A17: Web Portal User Guide (all roles) | B17: 5000 | C17: =B17*'0. Assumptions'!$C$9 -> 65000
A18: Miner / ASM Simplified Usage Guide (pictorial, local lang.) | B18: 4000 | C18: =B18*'0. Assumptions'!$C$9 -> 52000
A19: Tier 1/2 Buyer User Manual | B19: 4000 | C19: =B19*'0. Assumptions'!$C$9 -> 52000
A20: Aggregator & Transporter User Guide | B20: 3000 | C20: =B20*'0. Assumptions'!$C$9 -> 39000
A21: Help Desk / L1 Support Runbook | B21: 4000 | C21: =B21*'0. Assumptions'!$C$9 -> 52000
A22: FAQ Document & Troubleshooting Guide | B22: 3000 | C22: =B22*'0. Assumptions'!$C$9 -> 39000
A23: Sub-Total | B23: =SUM(B15:B22) -> 34000 | C23: =B23*'0. Assumptions'!$C$9 -> 442000
A24: COMPLIANCE & GOVERNANCE DOCUMENTS
A25: Data Protection & Privacy Policy | B25: 4000 | C25: =B25*'0. Assumptions'!$C$9 -> 52000
A26: AML/CFT Compliance Manual & Procedures | B26: 5000 | C26: =B26*'0. Assumptions'!$C$9 -> 65000
A27: OECD/LBMA Compliance Framework Documentation | B27: 6000 | C27: =B27*'0. Assumptions'!$C$9 -> 78000
A28: Change Management & Escalation Procedures | B28: 3000 | C28: =B28*'0. Assumptions'!$C$9 -> 39000
A29: Incident Response & Security Breach Plan | B29: 4000 | C29: =B29*'0. Assumptions'!$C$9 -> 52000
A30: System Audit Trail & Access Log Specification | B30: 3000 | C30: =B30*'0. Assumptions'!$C$9 -> 39000
A31: SLA Definition & Performance KPI Framework | B31: 4000 | C31: =B31*'0. Assumptions'!$C$9 -> 52000
A32: Sub-Total | B32: =SUM(B25:B31) -> 29000 | C32: =B32*'0. Assumptions'!$C$9 -> 377000
A33: PROJECT MANAGEMENT DOCUMENTS
A34: Project Initiation Document (PID) & Project Charter | B34: 3000 | C34: =B34*'0. Assumptions'!$C$9 -> 39000
A35: Project Schedule (Gantt) & Work Breakdown Structure | B35: 2000 | C35: =B35*'0. Assumptions'!$C$9 -> 26000
A36: 18 Monthly Progress Reports | B36: 1500 | C36: =B36*'0. Assumptions'!$C$9 -> 19500
A37: Risk Register & Issue Log (maintained 18 months) | B37: 2000 | C37: =B37*'0. Assumptions'!$C$9 -> 26000
A38: Change Request Log & Change Management Register | B38: 1500 | C38: =B38*'0. Assumptions'!$C$9 -> 19500
A39: Monthly Financial Reports & Budget Variance Reports | B39: 2000 | C39: =B39*'0. Assumptions'!$C$9 -> 26000
A40: Lessons Learned Register (ongoing) | B40: 1500 | C40: =B40*'0. Assumptions'!$C$9 -> 19500
A41: Project Closure Report | B41: 4000 | C41: =B41*'0. Assumptions'!$C$9 -> 52000
A42: Sub-Total | B42: =SUM(B34:B41) -> 17500 | C42: =B42*'0. Assumptions'!$C$9 -> 227500
A43: HANDOVER & SUSTAINABILITY DOCUMENTS
A44: Knowledge Transfer Plan & Schedule | B44: 4000 | C44: =B44*'0. Assumptions'!$C$9 -> 52000
A45: System Handover Pack (all documentation compiled) | B45: 6000 | C45: =B45*'0. Assumptions'!$C$9 -> 78000
A46: Source Code Handover & Repository Transfer Documentation | B46: 5000 | C46: =B46*'0. Assumptions'!$C$9 -> 65000
A47: Staff Capability Assessment & Training Completion Certificates | B47: 3000 | C47: =B47*'0. Assumptions'!$C$9 -> 39000
A48: Post-Handover Warranty Terms & Support Agreement | B48: 3000 | C48: =B48*'0. Assumptions'!$C$9 -> 39000
A49: Long-Term Sustainability & Operational Plan | B49: 5000 | C49: =B49*'0. Assumptions'!$C$9 -> 65000
A50: Technology Refresh Roadmap (3-year horizon) | B50: 4000 | C50: =B50*'0. Assumptions'!$C$9 -> 52000
A51: Sub-Total | B51: =SUM(B44:B50) -> 30000 | C51: =B51*'0. Assumptions'!$C$9 -> 390000
A52: TRAINING MATERIALS (as deliverables)
A53: LMS with all e-learning modules (handed over to GoldBod) | B53: 8000 | C53: =B53*'0. Assumptions'!$C$9 -> 104000
A54: Printed training materials (1,000 sets — all roles) | B54: 4000 | C54: =B54*'0. Assumptions'!$C$9 -> 52000
A55: Video tutorial library (16 HD videos, hosted) | B55: 5000 | C55: =B55*'0. Assumptions'!$C$9 -> 65000
A56: Assessment & certification exam materials | B56: 2000 | C56: =B56*'0. Assumptions'!$C$9 -> 26000
A57: Sub-Total | B57: =SUM(B53:B56) -> 19000 | C57: =B57*'0. Assumptions'!$C$9 -> 247000
A58: TOTAL DOCUMENTATION & DELIVERABLES COSTS | B58: =B13+B23+B32+B42+B51+B57 -> 171500 | C58: =B58*'0. Assumptions'!$C$9 -> 2229500

Sheet 15. Contingency Budget
A1: SECTION 15 — CONTINGENCY BUDGET
A2: Contingency is provisioned at 10% of direct costs per category. Release requires written PMO approval. Unspent contingency is returned to GoldBod.
B3: Cost Category | C3: Direct Cost (USD) | D3: Contingency Rate | E3: Contingency (USD) | F3: Contingency (GHS)
B4: 1 | C4: Personnel & HR Costs | D4: 3250000 | E4: 0.08 | F4: =D4*E4 -> 260000 | G4: =F4*'0. Assumptions'!$C$9 -> 3380000
B5: 2 | C5: Software Development | D5: 1980000 | E5: 0.12 | F5: =D5*E5 -> 237600 | G5: =F5*'0. Assumptions'!$C$9 -> 3088800
B6: 3 | C6: Blockchain Infrastructure | D6: 820000 | E6: 0.12 | F6: =D6*E6 -> 98400 | G6: =F6*'0. Assumptions'!$C$9 -> 1279200
B7: 4 | C7: Cloud & Hosting (18 months) | D7: 540000 | E7: 0.08 | F7: =D7*E7 -> 43200 | G7: =F7*'0. Assumptions'!$C$9 -> 561600
B8: 5 | C8: Software Licenses & Tools | D8: 310000 | E8: 0.05 | F8: =D8*E8 -> 15500 | G8: =F8*'0. Assumptions'!$C$9 -> 201500
B9: 6 | C9: Hardware & Field Equipment | D9: 680000 | E9: 0.1 | F9: =D9*E9 -> 68000 | G9: =F9*'0. Assumptions'!$C$9 -> 884000
B10: 7 | C10: Deployment Costs | D10: 400000 | E10: 0.1 | F10: =D10*E10 -> 40000 | G10: =F10*'0. Assumptions'!$C$9 -> 520000
B11: 8 | C11: Systems Integration (6 agencies + APIs) | D11: 640000 | E11: 0.15 | F11: =D11*E11 -> 96000 | G11: =F11*'0. Assumptions'!$C$9 -> 1248000
B12: 9 | C12: Testing & Quality Assurance | D12: 290000 | E12: 0.1 | F12: =D12*E12 -> 29000 | G12: =F12*'0. Assumptions'!$C$9 -> 377000
B13: 10 | C13: Training & Capacity Building | D13: 420000 | E13: 0.1 | F13: =D13*E13 -> 42000 | G13: =F13*'0. Assumptions'!$C$9 -> 546000
B14: 11 | C14: Compliance & Regulatory | D14: 180000 | E14: 0.08 | F14: =D14*E14 -> 14400 | G14: =F14*'0. Assumptions'!$C$9 -> 187200
B15: 12 | C15: Project Management & PMO | D15: 380000 | E15: 0.08 | F15: =D15*E15 -> 30400 | G15: =F15*'0. Assumptions'!$C$9 -> 395200
... B17: 14 | C17: Additional Risk Reserve (currency/tax) | D17: 250000 | E17: 1 | F17: =D17*E17 -> 250000 | G17: =F17*'0. Assumptions'!$C$9 -> 3250000
B18: TOTAL CONTINGENCY PROVISION | F18: =SUM(F4:F17) -> 1229250 | G18: =F18*'0. Assumptions'!$C$9 -> 15980250
B20: CONTINGENCY POLICY:
B21: 1. Contingency funds are NOT automatic — each draw requires a formal Contingency Release Request (CRR) approved by GoldBod PMO Director.
B22: 2. Draws ≤ USD 10,000 may be approved by the Project Manager. Draws > USD 10,000 require Steering Committee approval.
B23: 3. Category rates reflect complexity: Integration (15%) and Software Dev (12%) carry higher rates due to scope uncertainty.
B24: 4. Currency/Tax Reserve (Line 14) covers GHS exchange rate movements >5% or unbudgeted tax policy changes.
B25: 5. Any unspent contingency at project close is returned to GoldBod and not retained by the implementing vendor.
B26: 6. A contingency utilisation report is included in each monthly progress report.

Sheet 16. Financial Impact & ROI
A1: GOLDBOD — FINANCIAL IMPACT ANALYSIS: TAS IMPLEMENTATION BUSINESS CASE
A2: This sheet models GoldBod's current baseline revenues, estimated revenue leakage, and the projected financial gains from the TAS. All figures are estimates based on Ghana Gold Board Act 2025, Bank of Ghana data, and regional ASM sector benchmarks.
A4: PART A — GOLDBOD CURRENT FINANCIAL BASELINE (Pre-TAS, Annual Estimates)
B5: Revenue / Income Stream | C5: Annual Volume | D5: Gold Price Basis (USD/oz) | E5: Annual Revenue (USD) | F5: Annual Revenue (GHS)
B6: Gold Purchased from ASM Sector (est. 30 tonnes/yr) | C6: 30 tonnes | D6: 2150 | E6: 2073675000 | F6: =E6*'0. Assumptions'!$C$9 -> 26957775000
B7: Export Levy Revenue (est. 3% on export value) | C7: Levy | D7: 2150 | E7: 62210250 | F7: =E7*'0. Assumptions'!$C$9 -> 808733250
B8: Licensing & Permit Fees (all categories) | C8: Fixed | E8: 8500000 | F8: =E8*'0. Assumptions'!$C$9 -> 110500000
B9: Assay & Certification Fees | C9: Per assay | E9: 2200000 | F9: =E9*'0. Assumptions'!$C$9 -> 28600000
B10: Administrative / Service Fees | C10: Various | E10: 1800000 | F10: =E10*'0. Assumptions'!$C$9 -> 23400000
B11: Fines & Penalties (enforcement actions) | C11: Variable | E11: 900000 | F11: =E11*'0. Assumptions'!$C$9 -> 11700000
B12: ESTIMATED TOTAL ANNUAL BASELINE REVENUE | E12: =SUM(E6:E11) -> 2149285250 | F12: =E12*'0. Assumptions'!$C$9 -> 27940708250
A14: PART B — ESTIMATED ANNUAL REVENUE LEAKAGE (Current, Pre-TAS)
B15: Leakage Category | C15: Mechanism / Description | D15: Leakage Rate | E15: Leakage USD/yr | F15: Leakage GHS/yr
B16: Gold Smuggling & Illicit Export | C16: Unregistered gold bypassing GoldBod, exported via neighbouring countries | D16: 0.25 | E16: 518418750 | F16: =E16*'0. Assumptions'!$C$9 -> 6739443750
B17: Under-Declaration of Weight / Grade | C17: Miners & buyers under-report quantity and purity at assay points | D17: 0.12 | E17: 248841000 | F17: =E17*'0. Assumptions'!$C$9 -> 3234933000
B18: Export Levy Avoidance | C18: Exporters misclassify gold as semi-processed or use false invoices | D18: 0.3 | E18: 18663075 | F18: =E18*'0. Assumptions'!$C$9 -> 242619975
B19: Royalty Under-Payment (ASM sector) | C19: ASM operators under-declare production volumes to GRA | D19: 0.2 | E19: 20736750 | F19: =E19*'0. Assumptions'!$C$9 -> 269577750
B20: Ghost Licensing / Duplicate Registrations | C20: Multiple registrations for same operation; expired licences still trading | D20: 0.05 | E20: 425000 | F20: =E20*'0. Assumptions'!$C$9 -> 5525000
B21: Fictitious KYC / Beneficial Ownership Concealment | C21: Shell companies hide true owners; AML controls bypassed | D21: 0.1 | E21: 900000 | F21: =E21*'0. Assumptions'!$C$9 -> 11700000
B22: Corrupt Assay Certification | C22: Bribed assay staff certify incorrect weights/grades | D22: 0.08 | E22: 165894000 | F22: =E22*'0. Assumptions'!$C$9 -> 2156622000
B23: Untracked Artisanal Mining Sites | C23: ~35% of ASM sites unregistered; zero revenue captured | D23: 0.35 | E23: 21773587 | F23: =E23*'0. Assumptions'!$C$9 -> 283056631
B24: ESTIMATED TOTAL ANNUAL REVENUE LEAKAGE | E24: =SUM(E16:E23) -> 995652162 | F24: =E24*'0. Assumptions'!$C$9 -> 12943478106
A26: PART C — TAS PROJECTED IMPACT: ANNUAL GAINS (Post-Implementation, Yr 2 Onwards)
B27: Benefit / Gain Category | C27: Recovery / Impact Mechanism | D27: Recovery Rate (TAS) | E27: Annual Gain (USD) | F27: Annual Gain (GHS)
B28: Illicit Export Reduction | C28: Blockchain chain-of-custody makes undocumented gold unsaleable internationally | D28: 0.6 | E28: 311051250 | F28: =E28*'0. Assumptions'!$C$9 -> 4043666250
B29: Weight/Grade Under-Declaration Prevention | C29: Digital scales + immutable ledger records eliminate manual tampering | D29: 0.8 | E29: 199072800 | F29: =E29*'0. Assumptions'!$C$9 -> 2587946400
B30: Export Levy Capture Improvement | C30: Automated GRA API cross-matching eliminates false invoices | D30: 0.7 | E30: 13064152 | F30: =E30*'0. Assumptions'!$C$9 -> 169833976
B31: Royalty Revenue Recovery | C31: GPS-tagged production sites + digital weighing closes ASM under-reporting gap | D31: 0.65 | E31: 13478887 | F31: =E31*'0. Assumptions'!$C$9 -> 175225531
B32: New Licences & Registrations (formalisation of unregistered ASM) | C32: TAS incentivises formal registration for market access; 2,000 new licences est. | D32: 1 | E32: 6000000 | F32: =E32*'0. Assumptions'!$C$9 -> 78000000
B33: Assay Fee Revenue Increase (volume uplift from formalisation) | C33: More formal actors → more assay events → more fee income | D33: 1 | E33: 3500000 | F33: =E33*'0. Assumptions'!$C$9 -> 45500000
B34: AML/CFT Fines & Penalty Revenue | C34: FIC integration enables automated STR detection & enforcement actions | D34: 1 | E34: 2200000 | F34: =E34*'0. Assumptions'!$C$9 -> 28600000
B35: Reduced Operational Costs — Manual Processing Elimination | C35: Digital workflows replace paper-based processes; headcount redeployed | D35: 1 | E35: 4800000 | F35: =E35*'0. Assumptions'!$C$9 -> 62400000
B36: Premium Pricing — LBMA/OECD Responsible Sourcing Certificate | C36: TAS-certified Ghanaian gold commands 1-3% price premium on international markets | D36: 1 | E36: 31105125 | F36: =E36*'0. Assumptions'!$C$9 -> 404366625
B37: Ghana Card KYC Cost Savings (replacing manual ID verification) | C37: Automated digital ID reduces compliance officer workload | D37: 1 | E37: 1200000 | F37: =E37*'0. Assumptions'!$C$9 -> 15600000
B38: Reduced Gold Sector Corruption Investigations | C38: Immutable audit trail reduces legal/investigation costs to government | D38: 1 | E38: 2500000 | F38: =E38*'0. Assumptions'!$C$9 -> 32500000
B39: Improved Investor Confidence (FDI premium — long-term benefit est.) | C39: Transparent, certified supply chain attracts responsible mining investment | D39: 1 | E39: 10000000 | F39: =E39*'0. Assumptions'!$C$9 -> 130000000
B40: TOTAL ESTIMATED ANNUAL GAIN (from Year 2) | E40: =SUM(E28:E39) -> 597972214 | F40: =E40*'0. Assumptions'!$C$9 -> 7773638782
A42: PART D — RETURN ON INVESTMENT (ROI) SUMMARY
B43: Total TAS Project Investment (18 months) | C43: USD | E43: ='0. Assumptions'!C8 -> 11355000 | F43: =E43*'0. Assumptions'!$C$9 -> 147615000
B44: Estimated Annual Gain from Year 2 | C44: USD | E44: =E40 -> 597972214
B45: Payback Period | C45: Months | E45: ~14 months post go-live
B46: 5-Year Cumulative Net Gain (Yrs 2–6) | C46: USD | E46: =E40*5-E43 -> 2978506070
B47: 10-Year Cumulative Net Gain (Yrs 2–11) | C47: USD | E47: =E40*10-E43 -> 5968367140
B48: ROI at Year 3 (net gain / investment) | C48: % | E48: =(E40*2-E43)/E43 -> 104.32316
B49: ROI at Year 5 | C49: % | E49: =(E40*4-E43)/E43 -> 209.64631
B50: Benefit-to-Cost Ratio (Year 5) | C50: x | E50: =E40*4/E43 -> 210.64631
A52: DISCLAIMER: All baseline revenue, leakage and gain estimates are derived from public data (Bank of Ghana, Minerals Commission, PMMC reports), IMF Ghana Article IV consultations, and sector benchmarks. Actual outcomes will vary based on compliance rates, gold price movements, and implementation quality. These figures are for decision-support purposes and are conservative estimates.
