Workbook

Sheet README
A1: CATTLE FARM FINANCIAL MODEL - dairy + beef breeding
A2: 10-year model, live formulas. Start on Assumptions.
A4: PURPOSE | B4: Test whether a mixed dairy and beef-breeding farm makes money, and which levers (breeding strategy, herd size, infrastructure cost, milk price, feed) change the answer.
A5: IMPORTANT | B5: All prices, costs and yields are GENERIC PLACEHOLDERS in USD. Replace them with local quotes (milk buyer, cattle market, feed supplier, equipment suppliers, bank) before relying on any result.
A7: COLOUR CODE | B7: Blue text = input | Black = formula | Green = link from another sheet | Yellow fill = biggest value drivers.
A9: SHEETS
A10: Assumptions | B10: Every input in one place, plus the Base / Downside / Upside selector (cell F5).
A11: Capex | B11: About 35 itemised startup lines (animals, sheds, milking, cooling, borehole, fencing, vehicles) with depreciation lives.
A12: Herd | B12: Cows, calves, heifer replacement (2-year lag), culls, litres of milk, and a land carrying-capacity warning.
A13: Revenue | B13: 13 streams: raw milk, processed dairy, bull calves, cross-bred calves, surplus heifers (ordinary + breeding stock), dairy culls, beef weaners, finished steers, beef culls, manure, breeding services, grants.
A14: Opex | B14: Feed, health & breeding, replacement stock, labour, processing, utilities, overheads, land costs, contingency.
A15: Financials | B15: Income statement, enterprise gross margins, loan schedule, tax with loss carry-forward, terminal value, project and equity cash flows, DSCR.
A16: Returns | B16: Investment, IRR, NPV, payback, break-even milk and weaner price, checks and charts.
A17: Breeding_Economics | B17: Per-cow view: what calves add under different breeding strategies, and how many cows are needed to cover fixed costs.
A18: Monthly_Y1 | B18: Year-1 monthly cash flow and a check that the working capital reserve is enough.
A19: Scenarios | B19: STATIC snapshot comparing strategies (mixed vs dairy-only vs beef-only, breeding upgrade, lean capex, bigger herds).
A21: HOW TO USE | B21: 1) Put local prices and costs into blue cells on Assumptions and Capex. 2) Set the scenario selector. 3) Read Returns and Monthly_Y1. 4) Test the breeding levers: cross-bred share, sexed semen share, breeding-stock share.
A23: LIMITS | B23: No VAT, no currency moves, no multi-year drought beyond the Downside case. Tax is a flat rate on profit with loss carry-forward: check local farm tax rules and exemptions. Herd is modelled in annual steps with fractional animals. Livestock is not depreciated; it is valued at market in the terminal value. Finishing margin is booked in the same year (simplification). No sustaining capex is depreciated.

Sheet Assumptions
A1: ASSUMPTIONS - every input in one place
A2: Blue = input you can change | Black = formula | Green = link from another sheet | Yellow fill = biggest value drivers. ALL FIGURES ARE PLACEHOLDERS: replace with local quotes.
A4: Input | B4: Unit | C4: Base | D4: Downside | E4: Upside | F4: LIVE VALUE | G4: Notes / source
A5: GENERAL & SCENARIO
A6: Scenario selector (1=Base, 2=Downside, 3=Upside) | B6: 1/2/3 | F6: 1 | G6: Switches every 'scenario lever' below (levers = section 2).
A7: Currency label (for headers only) | B7: text | F7: USD | G7: PLACEHOLDER. Type your currency; then replace every price with a local quote.
A8: Dairy enterprise on? (1=yes, 0=no) | B8: 1/0 | F8: 1 | G8: Set 0 for a beef-only farm.
A9: Beef breeding enterprise on? (1=yes, 0=no) | B9: 1/0 | F9: 1 | G9: Set 0 for a dairy-only farm.
A10: Farm area | B10: hectares | F10: 150 | G10: User brief: 150 ha.
A11: Carrying capacity | B11: animal units/ha | F11: 0.8 | G11: PLACEHOLDER. 1 AU = 1 adult cow; young stock = 0.5 AU. Use your local agronomist's figure.
A12: Land purchased? (1=buy, 0=lease) | B12: 1/0 | F12: 0 | G12: Default = leased, so land is an operating cost, not capex.
A13: Land purchase price | B13: per ha | F13: 1500 | G13: PLACEHOLDER. Only used if land is purchased.
A14: Land lease | B14: per ha / yr | F14: 40 | G14: PLACEHOLDER. Only used if land is leased.
A15: Price inflation (all sales prices) | B15: % / yr | F15: 0.03 | G15: PLACEHOLDER
A16: Cost inflation (all costs) | B16: % / yr | F16: 0.04 | G16: PLACEHOLDER. Costs rising faster than prices squeezes margin.
A17: Income tax rate | B17: % | F17: 0.25 | G17: PLACEHOLDER. Check local farm tax rules/exemptions. Loss carry-forward IS modelled.
A18: Hurdle rate / discount rate | B18: % | F18: 0.12 | G18: Return you require to justify the risk.
A19: Include terminal value in Year 10 returns? (1/0) | B19: 1/0 | F19: 1 | G19: Terminal value = herd at market value + net book value of assets.
A20: Working capital reserve | B20: months of Yr-1 opex | F20: 3 | G20: Cash cushion funded at start. Checked on Monthly_Y1 sheet.
A21: 2. SCENARIO LEVERS (blue = Base / Downside / Upside inputs; column F = live value used by the model)
A22: Raw milk farm-gate price | B22: per litre | C22: 0.6 | D22: 0.48 | E22: 0.72 | F22: =CHOOSE($F$6,C22,D22,E22) -> 0.6 | G22: PLACEHOLDER: use your local processor / buyer quote.
A23: Milk yield per cow in milk | B23: litres / day | C23: 10 | D23: 8.5 | E23: 12 | F23: =CHOOSE($F$6,C23,D23,E23) -> 10 | G23: PLACEHOLDER: depends on breed (crossbreds 8-12, Holstein-type 15-25).
A24: Feed cost multiplier | B24: x | C24: 1 | D24: 1.2 | E24: 0.92 | F24: =CHOOSE($F$6,C24,D24,E24) -> 1 | G24: Scales every feed line.
A25: Cattle price multiplier | B25: x | C25: 1 | D25: 0.8 | E25: 1.2 | F25: =CHOOSE($F$6,C25,D25,E25) -> 1 | G25: Scales calves, heifers, weaners, culls, purchased animals.
A26: Dairy calving rate | B26: calves / cow / yr | C26: 0.8 | D26: 0.7 | E26: 0.88 | F26: =CHOOSE($F$6,C26,D26,E26) -> 0.8 | G26: 80-90% is good management.
A27: Beef calving rate | B27: calves / cow / yr | C27: 0.75 | D27: 0.65 | E27: 0.85 | F27: =CHOOSE($F$6,C27,D27,E27) -> 0.75
A28: Adult cow mortality | B28: % / yr | C28: 0.03 | D28: 0.05 | E28: 0.02 | F28: =CHOOSE($F$6,C28,D28,E28) -> 0.03
A29: Calf mortality (birth to weaning) | B29: % | C29: 0.08 | D29: 0.15 | E29: 0.05 | F29: =CHOOSE($F$6,C29,D29,E29) -> 0.08
A30: 3. HERD
A31: Dairy cows at start | B31: head | F31: 40 | G31: User brief: 40.
A32: Dairy herd target size | B32: head | F32: 40 | G32: Herd grows to this using own heifers (then bought heifers). Set higher than start to grow.
A33: Beef cows at start | B33: head | F33: 30 | G33: User brief: 30.
A34: Beef herd target size | B34: head | F34: 30
A35: Dairy cull rate | B35: % / yr | F35: 0.2
A36: Beef cull rate | B36: % / yr | F36: 0.15
A37: Share of calves that are female (normal semen) | B37: % | F37: 0.5
A38: Dairy cows served with SEXED dairy semen | B38: % of non-cross cows | F38: 0 | G38: BREEDING LEVER: more heifer calves for sale/replacement.
A39: Female calves from sexed semen | B39: % | F39: 0.9 | G39: Typical claimed accuracy ~90%.
A40: Dairy cows served with BEEF semen (cross-bred calves) | B40: % of dairy cows | F40: 0 | G40: BREEDING LEVER: cross-bred calves sell for far more than pure dairy bull calves.
A41: Effective heifer share of dairy-bred calves | B41: % | F41: =F37*(1-F38)+F39*F38 -> 0.5 | G41: Calculated.
A42: Surplus DAIRY heifers sold as breeding stock | B42: % | F42: 0 | G42: BREEDING LEVER: needs records, health status, a buyer base.
A43: Surplus BEEF heifers sold as breeding stock | B43: % | F43: 0 | G43: BREEDING LEVER
A44: Breeding-stock price premium over ordinary heifer | B44: x | F44: 1.6 | G44: PLACEHOLDER. Ask local seed-stock breeders what they get.
A45: Steers kept and finished for slaughter | B45: % of steers | F45: 0 | G45: Simplification: finishing margin booked in the same year.
A46: Outside cows served by your bulls / AI (service business) | B46: cows / yr | F46: 0 | G46: Breeding services stream.
A47: Cows per bull | B47: cows | F47: 25
A48: 4. MILK & PRODUCTION
A49: Lactation length | B49: days | F49: 300
A50: Share of cows in milk on average | B50: % | F50: 0.85
A51: Share of milk processed (yoghurt / cheese / pasteurised) | B51: % of litres | F51: 0.1 | G51: VALUE-ADD LEVER.
A52: Processed product price vs raw milk | B52: x | F52: 2 | G52: PLACEHOLDER: revenue per raw litre when processed.
A53: Processing cost (packaging, energy, labour) | B53: per raw litre | F53: 0.2 | G53: PLACEHOLDER
A54: 5. ANIMAL PRICES (Year-1, before scenario multiplier)
A55: Dairy bull calf (pure dairy) | B55: per head | F55: 40 | G55: PLACEHOLDER. Often nearly worthless.
A56: Beef-cross calf at ~3 months | B56: per head | F56: 160 | G56: PLACEHOLDER.
A57: Dairy breeding heifer (surplus / replacement) | B57: per head | F57: 700 | G57: PLACEHOLDER.
A58: Beef breeding heifer | B58: per head | F58: 600 | G58: PLACEHOLDER.
A59: Weaner weight | B59: kg live | F59: 200
A60: Weaner price | B60: per kg live | F60: 2.2 | G60: PLACEHOLDER.
A61: Finished steer weight | B61: kg live | F61: 380
A62: Finished steer price | B62: per kg live | F62: 1.9 | G62: PLACEHOLDER.
A63: Dairy cull cow weight | B63: kg live | F63: 420
A64: Beef cull cow weight | B64: kg live | F64: 450
A65: Cull cow price | B65: per kg live | F65: 1.6 | G65: PLACEHOLDER.
A66: Manure / slurry income | B66: per cow / yr | F66: 25 | G66: PLACEHOLDER.
A67: Service fee (bull / AI) per outside cow | B67: per cow | F67: 45 | G67: PLACEHOLDER.
A68: Grant / subsidy income | B68: per yr | F68: 0 | G68: Enter if you have a confirmed programme.
A69: Grant duration | B69: years | F69: 0 | G69: First N years.
A70: Purchase price: dairy cow / in-calf heifer | B70: per head | F70: 1100 | G70: PLACEHOLDER. Used for start herd and bought replacements.
A71: Purchase price: beef cow | B71: per head | F71: 800 | G71: PLACEHOLDER.
A72: Rearing cost of a cross-bred calf to sale (milk, feed, vet) | B72: per head | F72: 40 | G72: PLACEHOLDER. Used on Breeding_Economics.
A73: Bull purchase price | B73: per head | F73: 1200
A74: Bull working life | B74: years | F74: 5
A75: 6. OPERATING COSTS (Year-1)
A76: Feed per dairy cow (concentrate + forage) | B76: per cow / yr | F76: 480 | G76: PLACEHOLDER. Biggest cost line.
A77: Feed per dairy heifer/calf | B77: per head / yr | F77: 150
A78: Feed per beef cow (mostly pasture) | B78: per cow / yr | F78: 120
A79: Feed per beef heifer/calf | B79: per head / yr | F79: 90
A80: Finishing feed per steer | B80: per head | F80: 250
A81: Pasture upkeep (fertiliser, reseeding, weed control) | B81: per ha / yr | F81: 15
A82: Veterinary & medicines | B82: per head / yr | F82: 22
A83: AI / semen & technician | B83: per dairy cow / yr | F83: 18
A84: Sexed semen extra cost | B84: per cow served | F84: 25
A85: Farm manager salary | B85: per yr | F85: 7000 | G85: PLACEHOLDER. Fixed cost; zero if owner-operated (then pay yourself).
A86: Farm worker wage | B86: per FTE / yr | F86: 2400 | G86: PLACEHOLDER.
A87: Dairy cows per worker | B87: cows | F87: 25
A88: Beef cows per worker | B88: cows | F88: 80
A89: Electricity, water, cleaning per dairy cow | B89: per cow / yr | F89: 35
A90: Vehicle fuel & farm running costs | B90: per yr | F90: 1800
A91: Land rates / property tax | B91: per ha / yr | F91: 1.5
A92: Insurance | B92: % of capex | F92: 0.01
A93: Repairs & maintenance | B93: % of infrastructure capex | F93: 0.03
A94: Transport & marketing | B94: % of revenue | F94: 0.02
A95: Admin, accounting, licences | B95: per yr | F95: 2500
A96: Opex contingency | B96: % of opex | F96: 0.05
A97: 7. CAPEX & FINANCING
A98: Infrastructure cost multiplier | B98: x | F98: 1 | G98: KEY LEVER: 0.6 = basic sheds + used equipment. Applies to non-animal, non-land lines.
A99: Capex contingency | B99: % of infrastructure | F99: 0.08
A100: Sustaining capex (replacement of worn assets) | B100: % of infra capex / yr | F100: 0.015
A101: Loan share of initial capex | B101: % | F101: 0.4 | G101: User brief: 40%.
...

Sheet Capex
A1: CAPEX - initial investment (about 30 itemised lines)
A2: Blue = input. 'Flag' switches a line on/off from the enterprise toggles. Infrastructure lines are scaled by the multiplier on Assumptions. All unit costs are PLACEHOLDERS.
A4: Item | B4: Applies to | C4: Qty | D4: Unit | E4: Unit cost | F4: Flag | G4: Cost mult. | H4: Total cost | I4: Life (yrs) | J4: Annual depreciation | K4: Notes | L4: Group
A5: ANIMALS
A6: Dairy cows / in-calf heifers | B6: Dairy | C6: =Assumptions!$F$31 -> 40 | D6: head | E6: =Assumptions!$F$70 -> 1100 | F6: =Assumptions!$F$8 -> 1 | G6: =1 -> 1 | H6: =C6*E6*F6*G6 -> 44000 | I6: 0 | J6: =IF(I6>0,H6/I6,0) -> 0 | K6: Not depreciated; valued in terminal value | L6: Animals
A7: Beef breeding cows | B7: Beef | C7: =Assumptions!$F$33 -> 30 | D7: head | E7: =Assumptions!$F$71 -> 800 | F7: =Assumptions!$F$9 -> 1 | G7: =1 -> 1 | H7: =C7*E7*F7*G7 -> 24000 | I7: 0 | J7: =IF(I7>0,H7/I7,0) -> 0 | K7: Not depreciated | L7: Animals
A8: Beef bulls | B8: Beef | C8: =ROUNDUP(Assumptions!$F$33/Assumptions!$F$47,0) -> 2 | D8: head | E8: =Assumptions!$F$73 -> 1200 | F8: =Assumptions!$F$9 -> 1 | G8: =1 -> 1 | H8: =C8*E8*F8*G8 -> 2400 | I8: 5 | J8: =IF(I8>0,H8/I8,0) -> 480 | L8: Animals
A9: BUILDINGS & DAIRY EQUIPMENT
A10: Cow shed / feeding & resting area | B10: Dairy | C10: =Assumptions!$F$31*5 -> 200 | D10: m2 | E10: 45 | F10: =Assumptions!$F$8 -> 1 | G10: =Assumptions!$F$98 -> 1 | H10: =C10*E10*F10*G10 -> 9000 | I10: 20 | J10: =IF(I10>0,H10/I10,0) -> 450 | K10: 5 m2 per cow | L10: Infrastructure
A11: Milking parlour building | B11: Dairy | C11: 1 | D11: lot | E11: 5000 | F11: =Assumptions!$F$8 -> 1 | G11: =Assumptions!$F$98 -> 1 | H11: =C11*E11*F11*G11 -> 5000 | I11: 20 | J11: =IF(I11>0,H11/I11,0) -> 250 | L11: Infrastructure
A12: Milking machine units | B12: Dairy | C12: =ROUNDUP(Assumptions!$F$31/12,0) -> 4 | D12: units | E12: 3500 | F12: =Assumptions!$F$8 -> 1 | G12: =Assumptions!$F$98 -> 1 | H12: =C12*E12*F12*G12 -> 14000 | I12: 10 | J12: =IF(I12>0,H12/I12,0) -> 1400 | K12: 1 unit per 12 cows | L12: Infrastructure
A13: Milk cooling tank | B13: Dairy | C13: 1 | D13: unit | E13: 6000 | F13: =Assumptions!$F$8 -> 1 | G13: =Assumptions!$F$98 -> 1 | H13: =C13*E13*F13*G13 -> 6000 | I13: 12 | J13: =IF(I13>0,H13/I13,0) -> 500 | L13: Infrastructure
A14: Generator / solar backup | B14: Shared | C14: 1 | D14: unit | E14: 5000 | F14: =1 -> 1 | G14: =Assumptions!$F$98 -> 1 | H14: =C14*E14*F14*G14 -> 5000 | I14: 10 | J14: =IF(I14>0,H14/I14,0) -> 500 | L14: Infrastructure
A15: Calf pens & housing | B15: Dairy | C15: 1 | D15: lot | E15: 2500 | F15: =Assumptions!$F$8 -> 1 | G15: =Assumptions!$F$98 -> 1 | H15: =C15*E15*F15*G15 -> 2500 | I15: 15 | J15: =IF(I15>0,H15/I15,0) -> 166.66667 | L15: Infrastructure
A16: Milk cans, churns, cleaning kit | B16: Dairy | C16: 1 | D16: lot | E16: 1200 | F16: =Assumptions!$F$8 -> 1 | G16: =Assumptions!$F$98 -> 1 | H16: =C16*E16*F16*G16 -> 1200 | I16: 5 | J16: =IF(I16>0,H16/I16,0) -> 240 | L16: Infrastructure
A17: Dairy processing equipment (pasteuriser, yoghurt/cheese) | B17: Processing | C17: 1 | D17: lot | E17: 7000 | F17: =IF(Assumptions!$F$51>0,1,0) -> 1 | G17: =Assumptions!$F$98 -> 1 | H17: =C17*E17*F17*G17 -> 7000 | I17: 10 | J17: =IF(I17>0,H17/I17,0) -> 700 | K17: Only if processed share > 0 | L17: Infrastructure
A18: FEED, WATER & LAND WORKS
A19: Feed store / hay barn | B19: Shared | C19: 1 | D19: lot | E19: 6000 | F19: =1 -> 1 | G19: =Assumptions!$F$98 -> 1 | H19: =C19*E19*F19*G19 -> 6000 | I19: 20 | J19: =IF(I19>0,H19/I19,0) -> 300 | L19: Infrastructure
A20: Forage chopper / silage equipment | B20: Shared | C20: 1 | D20: unit | E20: 4000 | F20: =1 -> 1 | G20: =Assumptions!$F$98 -> 1 | H20: =C20*E20*F20*G20 -> 4000 | I20: 10 | J20: =IF(I20>0,H20/I20,0) -> 400 | L20: Infrastructure
A21: Borehole, pump & power | B21: Shared | C21: 1 | D21: lot | E21: 10000 | F21: =1 -> 1 | G21: =Assumptions!$F$98 -> 1 | H21: =C21*E21*F21*G21 -> 10000 | I21: 15 | J21: =IF(I21>0,H21/I21,0) -> 666.66667 | L21: Infrastructure
A22: Water tanks & troughs | B22: Shared | C22: 1 | D22: lot | E22: 3000 | F22: =1 -> 1 | G22: =Assumptions!$F$98 -> 1 | H22: =C22*E22*F22*G22 -> 3000 | I22: 10 | J22: =IF(I22>0,H22/I22,0) -> 300 | L22: Infrastructure
A23: Water piping / reticulation | B23: Shared | C23: 1 | D23: lot | E23: 4000 | F23: =1 -> 1 | G23: =Assumptions!$F$98 -> 1 | H23: =C23*E23*F23*G23 -> 4000 | I23: 15 | J23: =IF(I23>0,H23/I23,0) -> 266.66667 | L23: Infrastructure
A24: Perimeter fencing | B24: Shared | C24: =ROUNDUP(4*SQRT(Assumptions!$F$10*10000)/1000,1) -> 4.9 | D24: km | E24: 3000 | F24: =1 -> 1 | G24: =Assumptions!$F$98 -> 1 | H24: =C24*E24*F24*G24 -> 14700 | I24: 15 | J24: =IF(I24>0,H24/I24,0) -> 980 | K24: Square-plot perimeter of farm area | L24: Infrastructure
A25: Paddock subdivision / electric fencing | B25: Shared | C25: 8 | D25: km | E25: 800 | F25: =1 -> 1 | G25: =Assumptions!$F$98 -> 1 | H25: =C25*E25*F25*G25 -> 6400 | I25: 10 | J25: =IF(I25>0,H25/I25,0) -> 640 | L25: Infrastructure
A26: Pasture establishment (improved grass) | B26: Shared | C26: =Assumptions!$F$31*0.25*Assumptions!$F$8+Assumptions!$F$33*0.1*Assumptions!$F$9 -> 13 | D26: ha | E26: 500 | F26: =1 -> 1 | G26: =Assumptions!$F$98 -> 1 | H26: =C26*E26*F26*G26 -> 6500 | I26: 10 | J26: =IF(I26>0,H26/I26,0) -> 650 | L26: Infrastructure
A27: BEEF HANDLING
A28: Cattle crush & handling yard | B28: Shared | C28: 1 | D28: lot | E28: 5000 | F28: =1 -> 1 | G28: =Assumptions!$F$98 -> 1 | H28: =C28*E28*F28*G28 -> 5000 | I28: 15 | J28: =IF(I28>0,H28/I28,0) -> 333.33333 | L28: Infrastructure
A29: Beef shelter / loading ramp | B29: Beef | C29: 1 | D29: lot | E29: 2500 | F29: =Assumptions!$F$9 -> 1 | G29: =Assumptions!$F$98 -> 1 | H29: =C29*E29*F29*G29 -> 2500 | I29: 15 | J29: =IF(I29>0,H29/I29,0) -> 166.66667 | L29: Infrastructure
A30: Livestock weighing scale | B30: Beef | C30: 1 | D30: unit | E30: 1000 | F30: =Assumptions!$F$9 -> 1 | G30: =Assumptions!$F$98 -> 1 | H30: =C30*E30*F30*G30 -> 1000 | I30: 10 | J30: =IF(I30>0,H30/I30,0) -> 100 | L30: Infrastructure
A31: VEHICLES & GENERAL
A32: Tractor | B32: Shared | C32: 1 | D32: unit | E32: 18000 | F32: =1 -> 1 | G32: =Assumptions!$F$98 -> 1 | H32: =C32*E32*F32*G32 -> 18000 | I32: 10 | J32: =IF(I32>0,H32/I32,0) -> 1800 | L32: Infrastructure
A33: Trailer & implements | B33: Shared | C33: 1 | D33: lot | E33: 3000 | F33: =1 -> 1 | G33: =Assumptions!$F$98 -> 1 | H33: =C33*E33*F33*G33 -> 3000 | I33: 8 | J33: =IF(I33>0,H33/I33,0) -> 375 | L33: Infrastructure
A34: Pickup truck | B34: Shared | C34: 1 | D34: unit | E34: 14000 | F34: =1 -> 1 | G34: =Assumptions!$F$98 -> 1 | H34: =C34*E34*F34*G34 -> 14000 | I34: 8 | J34: =IF(I34>0,H34/I34,0) -> 1750 | L34: Infrastructure
A35: Motorbike(s) | B35: Shared | C35: 1 | D35: unit | E35: 1800 | F35: =1 -> 1 | G35: =Assumptions!$F$98 -> 1 | H35: =C35*E35*F35*G35 -> 1800 | I35: 5 | J35: =IF(I35>0,H35/I35,0) -> 360 | L35: Infrastructure
A36: Farm office & worker housing | B36: Shared | C36: 1 | D36: lot | E36: 5000 | F36: =1 -> 1 | G36: =Assumptions!$F$98 -> 1 | H36: =C36*E36*F36*G36 -> 5000 | I36: 20 | J36: =IF(I36>0,H36/I36,0) -> 250 | L36: Infrastructure
A37: Hand tools & miscellaneous | B37: Shared | C37: 1 | D37: lot | E37: 1200 | F37: =1 -> 1 | G37: =Assumptions!$F$98 -> 1 | H37: =C37*E37*F37*G37 -> 1200 | I37: 5 | J37: =IF(I37>0,H37/I37,0) -> 240 | L37: Infrastructure
A38: Licences, registration, vet set-up | B38: Shared | C38: 1 | D38: lot | E38: 1500 | F38: =1 -> 1 | G38: =Assumptions!$F$98 -> 1 | H38: =C38*E38*F38*G38 -> 1500 | I38: 5 | J38: =IF(I38>0,H38/I38,0) -> 300 | L38: Infrastructure
A39: LAND & CONTINGENCY
A40: Land purchase | B40: Land | C40: =Assumptions!$F$10 -> 150 | D40: ha | E40: =Assumptions!$F$13 -> 1500 | F40: =Assumptions!$F$12 -> 0 | G40: =1 -> 1 | H40: =C40*E40*F40*G40 -> 0 | I40: 0 | J40: =IF(I40>0,H40/I40,0) -> 0 | K40: Only if 'Land purchased' = 1 | L40: Land
A41: Contingency on infrastructure | B41: Shared | C41: 1 | D41: lot | E41: =Assumptions!$F$99*SUMIF($L$6:$L$40,"Infrastructure",$H$6:$H$40) -> 12584 | F41: =1 -> 1 | G41: =1 -> 1 | H41: =C41*E41*F41*G41 -> 12584 | I41: 10 | J41: =IF(I41>0,H41/I41,0) -> 1258.4 | L41: Contingency
A43: Subtotal: animals | H43: =SUMIF($L$6:$L$41,"Animals",$H$6:$H$41) -> 70400
A44: Subtotal: infrastructure & equipment | H44: =SUMIF($L$6:$L$41,"Infrastructure",$H$6:$H$41) -> 157300
A45: Subtotal: land | H45: =SUMIF($L$6:$L$41,"Land",$H$6:$H$41) -> 0
A46: Subtotal: contingency | H46: =SUMIF($L$6:$L$41,"Contingency",$H$6:$H$41) -> 12584
A47: TOTAL INITIAL CAPEX | H47: =SUM(H6:H41) -> 240284
A48: Total annual depreciation (Year 1) | H48: =SUM(J6:J41) -> 15823.4
A50: Legend: blue cells are inputs. Quantities that link to Assumptions (herd size, hectares) update automatically. Unit costs are placeholders: replace with supplier quotes.

Sheet Herd
A1: HERD MODEL - cows, calves, heifers, culls, litres
A2: Annual model. Own heifers enter the herd 2 years after birth; any shortfall is met by buying heifers. Fractions of animals are allowed.
A3: Line item | B3: Unit | C3: Year 0 | D3: Year 1 | E3: Year 2 | F3: Year 3 | G3: Year 4 | H3: Year 5 | I3: Year 6 | J3: Year 7 | K3: Year 8 | L3: Year 9 | M3: Year 10
A4: Year index | C4: 0 | D4: 1 | E4: 2 | F4: 3 | G4: 4 | H4: 5 | I4: 6 | J4: 7 | K4: 8 | L4: 9 | M4: 10
A6: DAIRY HERD
A7: Opening dairy cows | B7: head | D7: =Assumptions!$F$31*Assumptions!$F$8 -> 40 | E7: =D14 -> 40 | F7: =E14 -> 40 | G7: =F14 -> 40 | H7: =G14 -> 40 | I7: =H14 -> 40 | J7: =I14 -> 40 | K7: =J14 -> 40 | L7: =K14 -> 40 | M7: =L14 -> 40
A8: Cows culled | B8: head | D8: =ROUND(D7*Assumptions!$F$35,0) -> 8 | E8: =ROUND(E7*Assumptions!$F$35,0) -> 8 | F8: =ROUND(F7*Assumptions!$F$35,0) -> 8 | G8: =ROUND(G7*Assumptions!$F$35,0) -> 8 | H8: =ROUND(H7*Assumptions!$F$35,0) -> 8 | I8: =ROUND(I7*Assumptions!$F$35,0) -> 8 | J8: =ROUND(J7*Assumptions!$F$35,0) -> 8 | K8: =ROUND(K7*Assumptions!$F$35,0) -> 8 | ... M8: =ROUND(M7*Assumptions!$F$35,0) -> 8
A9: Cow deaths | B9: head | D9: =ROUND(D7*Assumptions!$F$28,0) -> 1 | E9: =ROUND(E7*Assumptions!$F$28,0) -> 1 | F9: =ROUND(F7*Assumptions!$F$28,0) -> 1 | G9: =ROUND(G7*Assumptions!$F$28,0) -> 1 | H9: =ROUND(H7*Assumptions!$F$28,0) -> 1 | I9: =ROUND(I7*Assumptions!$F$28,0) -> 1 | J9: =ROUND(J7*Assumptions!$F$28,0) -> 1 | K9: =ROUND(K7*Assumptions!$F$28,0) -> 1 | ... M9: =ROUND(M7*Assumptions!$F$28,0) -> 1
A10: Target herd size | B10: head | D10: =Assumptions!$F$32*Assumptions!$F$8 -> 40 | E10: =Assumptions!$F$32*Assumptions!$F$8 -> 40 | F10: =Assumptions!$F$32*Assumptions!$F$8 -> 40 | G10: =Assumptions!$F$32*Assumptions!$F$8 -> 40 | H10: =Assumptions!$F$32*Assumptions!$F$8 -> 40 | I10: =Assumptions!$F$32*Assumptions!$F$8 -> 40 | J10: =Assumptions!$F$32*Assumptions!$F$8 -> 40 | K10: =Assumptions!$F$32*Assumptions!$F$8 -> 40 | ... M10: =Assumptions!$F$32*Assumptions!$F$8 -> 40
A11: Replacements needed to reach target | B11: head | D11: =MAX(0,D10-(D7-D8-D9)) -> 9 | E11: =MAX(0,E10-(E7-E8-E9)) -> 9 | F11: =MAX(0,F10-(F7-F8-F9)) -> 9 | G11: =MAX(0,G10-(G7-G8-G9)) -> 9 | H11: =MAX(0,H10-(H7-H8-H9)) -> 9 | I11: =MAX(0,I10-(I7-I8-I9)) -> 9 | J11: =MAX(0,J10-(J7-J8-J9)) -> 9 | K11: =MAX(0,K10-(K7-K8-K9)) -> 9 | ... M11: =MAX(0,M10-(M7-M8-M9)) -> 9
A12: Own heifers entering herd | B12: head | D12: =MIN(D24,D11) -> 0 | E12: =MIN(E24,E11) -> 0 | F12: =MIN(F24,F11) -> 9 | G12: =MIN(G24,G11) -> 9 | H12: =MIN(H24,H11) -> 9 | I12: =MIN(I24,I11) -> 9 | J12: =MIN(J24,J11) -> 9 | K12: =MIN(K24,K11) -> 9 | ... M12: =MIN(M24,M11) -> 9
A13: Replacement heifers bought in | B13: head | D13: =D11-D12 -> 9 | E13: =E11-E12 -> 9 | F13: =F11-F12 -> 0 | G13: =G11-G12 -> 0 | H13: =H11-H12 -> 0 | I13: =I11-I12 -> 0 | J13: =J11-J12 -> 0 | K13: =K11-K12 -> 0 | ... M13: =M11-M12 -> 0
A14: Closing dairy cows | B14: head | D14: =D7-D8-D9+D12+D13 -> 40 | E14: =E7-E8-E9+E12+E13 -> 40 | F14: =F7-F8-F9+F12+F13 -> 40 | G14: =G7-G8-G9+G12+G13 -> 40 | H14: =H7-H8-H9+H12+H13 -> 40 | I14: =I7-I8-I9+I12+I13 -> 40 | J14: =J7-J8-J9+J12+J13 -> 40 | K14: =K7-K8-K9+K12+K13 -> 40 | ... M14: =M7-M8-M9+M12+M13 -> 40
A15: Average dairy cows | B15: head | D15: =(D7+D14)/2 -> 40 | E15: =(E7+E14)/2 -> 40 | F15: =(F7+F14)/2 -> 40 | G15: =(G7+G14)/2 -> 40 | H15: =(H7+H14)/2 -> 40 | I15: =(I7+I14)/2 -> 40 | J15: =(J7+J14)/2 -> 40 | K15: =(K7+K14)/2 -> 40 | ... M15: =(M7+M14)/2 -> 40
A17: DAIRY CALF CROP
A18: Calves born | B18: head | D18: =D7*Assumptions!$F$26 -> 32 | E18: =E7*Assumptions!$F$26 -> 32 | F18: =F7*Assumptions!$F$26 -> 32 | G18: =G7*Assumptions!$F$26 -> 32 | H18: =H7*Assumptions!$F$26 -> 32 | I18: =I7*Assumptions!$F$26 -> 32 | J18: =J7*Assumptions!$F$26 -> 32 | K18: =K7*Assumptions!$F$26 -> 32 | ... M18: =M7*Assumptions!$F$26 -> 32
A19: of which sired by beef bull (cross-bred) | B19: head | D19: =D18*Assumptions!$F$40 -> 0 | E19: =E18*Assumptions!$F$40 -> 0 | F19: =F18*Assumptions!$F$40 -> 0 | G19: =G18*Assumptions!$F$40 -> 0 | H19: =H18*Assumptions!$F$40 -> 0 | I19: =I18*Assumptions!$F$40 -> 0 | J19: =J18*Assumptions!$F$40 -> 0 | K19: =K18*Assumptions!$F$40 -> 0 | ... M19: =M18*Assumptions!$F$40 -> 0
A20: of which dairy-bred | B20: head | D20: =D18-D19 -> 32 | E20: =E18-E19 -> 32 | F20: =F18-F19 -> 32 | G20: =G18-G19 -> 32 | H20: =H18-H19 -> 32 | I20: =I18-I19 -> 32 | J20: =J18-J19 -> 32 | K20: =K18-K19 -> 32 | ... M20: =M18-M19 -> 32
A21: Heifer calves surviving (dairy-bred) | B21: head | D21: =D20*Assumptions!$F$41*(1-Assumptions!$F$29) -> 14.72 | E21: =E20*Assumptions!$F$41*(1-Assumptions!$F$29) -> 14.72 | F21: =F20*Assumptions!$F$41*(1-Assumptions!$F$29) -> 14.72 | G21: =G20*Assumptions!$F$41*(1-Assumptions!$F$29) -> 14.72 | H21: =H20*Assumptions!$F$41*(1-Assumptions!$F$29) -> 14.72 | I21: =I20*Assumptions!$F$41*(1-Assumptions!$F$29) -> 14.72 | J21: =J20*Assumptions!$F$41*(1-Assumptions!$F$29) -> 14.72 | K21: =K20*Assumptions!$F$41*(1-Assumptions!$F$29) -> 14.72 | ... M21: =M20*Assumptions!$F$41*(1-Assumptions!$F$29) -> 14.72
A22: Bull calves surviving (sold) | B22: head | D22: =D20*(1-Assumptions!$F$41)*(1-Assumptions!$F$29) -> 14.72 | E22: =E20*(1-Assumptions!$F$41)*(1-Assumptions!$F$29) -> 14.72 | F22: =F20*(1-Assumptions!$F$41)*(1-Assumptions!$F$29) -> 14.72 | G22: =G20*(1-Assumptions!$F$41)*(1-Assumptions!$F$29) -> 14.72 | H22: =H20*(1-Assumptions!$F$41)*(1-Assumptions!$F$29) -> 14.72 | I22: =I20*(1-Assumptions!$F$41)*(1-Assumptions!$F$29) -> 14.72 | J22: =J20*(1-Assumptions!$F$41)*(1-Assumptions!$F$29) -> 14.72 | K22: =K20*(1-Assumptions!$F$41)*(1-Assumptions!$F$29) -> 14.72 | ... M22: =M20*(1-Assumptions!$F$41)*(1-Assumptions!$F$29) -> 14.72
A23: Cross-bred calves surviving (sold) | B23: head | D23: =D19*(1-Assumptions!$F$29) -> 0 | E23: =E19*(1-Assumptions!$F$29) -> 0 | F23: =F19*(1-Assumptions!$F$29) -> 0 | G23: =G19*(1-Assumptions!$F$29) -> 0 | H23: =H19*(1-Assumptions!$F$29) -> 0 | I23: =I19*(1-Assumptions!$F$29) -> 0 | J23: =J19*(1-Assumptions!$F$29) -> 0 | K23: =K19*(1-Assumptions!$F$29) -> 0 | ... M23: =M19*(1-Assumptions!$F$29) -> 0
A24: Heifers reaching breeding age (born 2 yrs earlier) | B24: head | D24: =0 -> 0 | E24: =0 -> 0 | F24: =E21 -> 14.72 | G24: =F21 -> 14.72 | H24: =G21 -> 14.72 | I24: =H21 -> 14.72 | J24: =I21 -> 14.72 | K24: =J21 -> 14.72 | L24: =K21 -> 14.72 | M24: =L21 -> 14.72
A25: Surplus heifers sold | B25: head | D25: =D24-D12 -> 0 | E25: =E24-E12 -> 0 | F25: =F24-F12 -> 5.72 | G25: =G24-G12 -> 5.72 | H25: =H24-H12 -> 5.72 | I25: =I24-I12 -> 5.72 | J25: =J24-J12 -> 5.72 | K25: =K24-K12 -> 5.72 | ... M25: =M24-M12 -> 5.72
A26: Young heifers on farm (under 2 yrs) | B26: head | D26: =D21 -> 14.72 | E26: =E21+D21 -> 29.44 | F26: =F21+E21 -> 29.44 | G26: =G21+F21 -> 29.44 | H26: =H21+G21 -> 29.44 | I26: =I21+H21 -> 29.44 | J26: =J21+I21 -> 29.44 | K26: =K21+J21 -> 29.44 | L26: =L21+K21 -> 29.44 | M26: =M21+L21 -> 29.44
A28: MILK PRODUCTION
A29: Total milk produced | B29: litres | D29: =D15*Assumptions!$F$50*Assumptions!$F$23*Assumptions!$F$49 -> 102000 | E29: =E15*Assumptions!$F$50*Assumptions!$F$23*Assumptions!$F$49 -> 102000 | F29: =F15*Assumptions!$F$50*Assumptions!$F$23*Assumptions!$F$49 -> 102000 | G29: =G15*Assumptions!$F$50*Assumptions!$F$23*Assumptions!$F$49 -> 102000 | H29: =H15*Assumptions!$F$50*Assumptions!$F$23*Assumptions!$F$49 -> 102000 | I29: =I15*Assumptions!$F$50*Assumptions!$F$23*Assumptions!$F$49 -> 102000 | J29: =J15*Assumptions!$F$50*Assumptions!$F$23*Assumptions!$F$49 -> 102000 | K29: =K15*Assumptions!$F$50*Assumptions!$F$23*Assumptions!$F$49 -> 102000 | ... M29: =M15*Assumptions!$F$50*Assumptions!$F$23*Assumptions!$F$49 -> 102000
A30: processed on farm | B30: litres | D30: =D29*Assumptions!$F$51 -> 10200 | E30: =E29*Assumptions!$F$51 -> 10200 | F30: =F29*Assumptions!$F$51 -> 10200 | G30: =G29*Assumptions!$F$51 -> 10200 | H30: =H29*Assumptions!$F$51 -> 10200 | I30: =I29*Assumptions!$F$51 -> 10200 | J30: =J29*Assumptions!$F$51 -> 10200 | K30: =K29*Assumptions!$F$51 -> 10200 | ... M30: =M29*Assumptions!$F$51 -> 10200
A31: sold raw | B31: litres | D31: =D29-D30 -> 91800 | E31: =E29-E30 -> 91800 | F31: =F29-F30 -> 91800 | G31: =G29-G30 -> 91800 | H31: =H29-H30 -> 91800 | I31: =I29-I30 -> 91800 | J31: =J29-J30 -> 91800 | K31: =K29-K30 -> 91800 | ... M31: =M29-M30 -> 91800
A33: BEEF BREEDING HERD
A34: Opening beef cows | B34: head | D34: =Assumptions!$F$33*Assumptions!$F$9 -> 30 | E34: =D41 -> 30 | F34: =E41 -> 30 | G34: =F41 -> 30 | H34: =G41 -> 30 | I34: =H41 -> 30 | J34: =I41 -> 30 | K34: =J41 -> 30 | L34: =K41 -> 30 | M34: =L41 -> 30
A35: Cows culled | B35: head | D35: =ROUND(D34*Assumptions!$F$36,0) -> 5 | E35: =ROUND(E34*Assumptions!$F$36,0) -> 5 | F35: =ROUND(F34*Assumptions!$F$36,0) -> 5 | G35: =ROUND(G34*Assumptions!$F$36,0) -> 5 | H35: =ROUND(H34*Assumptions!$F$36,0) -> 5 | I35: =ROUND(I34*Assumptions!$F$36,0) -> 5 | J35: =ROUND(J34*Assumptions!$F$36,0) -> 5 | K35: =ROUND(K34*Assumptions!$F$36,0) -> 5 | ... M35: =ROUND(M34*Assumptions!$F$36,0) -> 5
A36: Cow deaths | B36: head | D36: =ROUND(D34*Assumptions!$F$28,0) -> 1 | E36: =ROUND(E34*Assumptions!$F$28,0) -> 1 | F36: =ROUND(F34*Assumptions!$F$28,0) -> 1 | G36: =ROUND(G34*Assumptions!$F$28,0) -> 1 | H36: =ROUND(H34*Assumptions!$F$28,0) -> 1 | I36: =ROUND(I34*Assumptions!$F$28,0) -> 1 | J36: =ROUND(J34*Assumptions!$F$28,0) -> 1 | K36: =ROUND(K34*Assumptions!$F$28,0) -> 1 | ... M36: =ROUND(M34*Assumptions!$F$28,0) -> 1
A37: Target herd size | B37: head | D37: =Assumptions!$F$34*Assumptions!$F$9 -> 30 | E37: =Assumptions!$F$34*Assumptions!$F$9 -> 30 | F37: =Assumptions!$F$34*Assumptions!$F$9 -> 30 | G37: =Assumptions!$F$34*Assumptions!$F$9 -> 30 | H37: =Assumptions!$F$34*Assumptions!$F$9 -> 30 | I37: =Assumptions!$F$34*Assumptions!$F$9 -> 30 | J37: =Assumptions!$F$34*Assumptions!$F$9 -> 30 | K37: =Assumptions!$F$34*Assumptions!$F$9 -> 30 | ... M37: =Assumptions!$F$34*Assumptions!$F$9 -> 30
A38: Replacements needed to reach target | B38: head | D38: =MAX(0,D37-(D34-D35-D36)) -> 6 | E38: =MAX(0,E37-(E34-E35-E36)) -> 6 | F38: =MAX(0,F37-(F34-F35-F36)) -> 6 | G38: =MAX(0,G37-(G34-G35-G36)) -> 6 | H38: =MAX(0,H37-(H34-H35-H36)) -> 6 | I38: =MAX(0,I37-(I34-I35-I36)) -> 6 | J38: =MAX(0,J37-(J34-J35-J36)) -> 6 | K38: =MAX(0,K37-(K34-K35-K36)) -> 6 | ... M38: =MAX(0,M37-(M34-M35-M36)) -> 6
A39: Own heifers entering herd | B39: head | D39: =MIN(D51,D38) -> 0 | E39: =MIN(E51,E38) -> 0 | F39: =MIN(F51,F38) -> 6 | G39: =MIN(G51,G38) -> 6 | H39: =MIN(H51,H38) -> 6 | I39: =MIN(I51,I38) -> 6 | J39: =MIN(J51,J38) -> 6 | K39: =MIN(K51,K38) -> 6 | ... M39: =MIN(M51,M38) -> 6
A40: Replacement heifers bought in | B40: head | D40: =D38-D39 -> 6 | E40: =E38-E39 -> 6 | F40: =F38-F39 -> 0 | G40: =G38-G39 -> 0 | H40: =H38-H39 -> 0 | I40: =I38-I39 -> 0 | J40: =J38-J39 -> 0 | K40: =K38-K39 -> 0 | ... M40: =M38-M39 -> 0
A41: Closing beef cows | B41: head | D41: =D34-D35-D36+D39+D40 -> 30 | E41: =E34-E35-E36+E39+E40 -> 30 | F41: =F34-F35-F36+F39+F40 -> 30 | G41: =G34-G35-G36+G39+G40 -> 30 | H41: =H34-H35-H36+H39+H40 -> 30 | I41: =I34-I35-I36+I39+I40 -> 30 | J41: =J34-J35-J36+J39+J40 -> 30 | K41: =K34-K35-K36+K39+K40 -> 30 | ... M41: =M34-M35-M36+M39+M40 -> 30
A42: Average beef cows | B42: head | D42: =(D34+D41)/2 -> 30 | E42: =(E34+E41)/2 -> 30 | F42: =(F34+F41)/2 -> 30 | G42: =(G34+G41)/2 -> 30 | H42: =(H34+H41)/2 -> 30 | I42: =(I34+I41)/2 -> 30 | J42: =(J34+J41)/2 -> 30 | K42: =(K34+K41)/2 -> 30 | ... M42: =(M34+M41)/2 -> 30
A44: BEEF CALF CROP
A45: Calves born | B45: head | D45: =D34*Assumptions!$F$27 -> 22.5 | E45: =E34*Assumptions!$F$27 -> 22.5 | F45: =F34*Assumptions!$F$27 -> 22.5 | G45: =G34*Assumptions!$F$27 -> 22.5 | H45: =H34*Assumptions!$F$27 -> 22.5 | I45: =I34*Assumptions!$F$27 -> 22.5 | J45: =J34*Assumptions!$F$27 -> 22.5 | K45: =K34*Assumptions!$F$27 -> 22.5 | ... M45: =M34*Assumptions!$F$27 -> 22.5
A46: Calves surviving to weaning | B46: head | D46: =D45*(1-Assumptions!$F$29) -> 20.7 | E46: =E45*(1-Assumptions!$F$29) -> 20.7 | F46: =F45*(1-Assumptions!$F$29) -> 20.7 | G46: =G45*(1-Assumptions!$F$29) -> 20.7 | H46: =H45*(1-Assumptions!$F$29) -> 20.7 | I46: =I45*(1-Assumptions!$F$29) -> 20.7 | J46: =J45*(1-Assumptions!$F$29) -> 20.7 | K46: =K45*(1-Assumptions!$F$29) -> 20.7 | ... M46: =M45*(1-Assumptions!$F$29) -> 20.7
A47: Heifer calves | B47: head | D47: =D46*Assumptions!$F$37 -> 10.35 | E47: =E46*Assumptions!$F$37 -> 10.35 | F47: =F46*Assumptions!$F$37 -> 10.35 | G47: =G46*Assumptions!$F$37 -> 10.35 | H47: =H46*Assumptions!$F$37 -> 10.35 | I47: =I46*Assumptions!$F$37 -> 10.35 | J47: =J46*Assumptions!$F$37 -> 10.35 | K47: =K46*Assumptions!$F$37 -> 10.35 | ... M47: =M46*Assumptions!$F$37 -> 10.35
A48: Steer calves | B48: head | D48: =D46-D47 -> 10.35 | E48: =E46-E47 -> 10.35 | F48: =F46-F47 -> 10.35 | G48: =G46-G47 -> 10.35 | H48: =H46-H47 -> 10.35 | I48: =I46-I47 -> 10.35 | J48: =J46-J47 -> 10.35 | K48: =K46-K47 -> 10.35 | ... M48: =M46-M47 -> 10.35
A49: Steers sold as weaners | B49: head | D49: =D48*(1-Assumptions!$F$45) -> 10.35 | E49: =E48*(1-Assumptions!$F$45) -> 10.35 | F49: =F48*(1-Assumptions!$F$45) -> 10.35 | G49: =G48*(1-Assumptions!$F$45) -> 10.35 | H49: =H48*(1-Assumptions!$F$45) -> 10.35 | I49: =I48*(1-Assumptions!$F$45) -> 10.35 | J49: =J48*(1-Assumptions!$F$45) -> 10.35 | K49: =K48*(1-Assumptions!$F$45) -> 10.35 | ... M49: =M48*(1-Assumptions!$F$45) -> 10.35
A50: Steers kept and finished | B50: head | D50: =D48*Assumptions!$F$45 -> 0 | E50: =E48*Assumptions!$F$45 -> 0 | F50: =F48*Assumptions!$F$45 -> 0 | G50: =G48*Assumptions!$F$45 -> 0 | H50: =H48*Assumptions!$F$45 -> 0 | I50: =I48*Assumptions!$F$45 -> 0 | J50: =J48*Assumptions!$F$45 -> 0 | K50: =K48*Assumptions!$F$45 -> 0 | ... M50: =M48*Assumptions!$F$45 -> 0
A51: Heifers reaching breeding age (born 2 yrs earlier) | B51: head | D51: =0 -> 0 | E51: =0 -> 0 | F51: =E47 -> 10.35 | G51: =F47 -> 10.35 | H51: =G47 -> 10.35 | I51: =H47 -> 10.35 | J51: =I47 -> 10.35 | K51: =J47 -> 10.35 | L51: =K47 -> 10.35 | M51: =L47 -> 10.35
A52: Surplus heifers sold | B52: head | D52: =D51-D39 -> 0 | E52: =E51-E39 -> 0 | F52: =F51-F39 -> 4.35 | G52: =G51-G39 -> 4.35 | H52: =H51-H39 -> 4.35 | I52: =I51-I39 -> 4.35 | J52: =J51-J39 -> 4.35 | K52: =K51-K39 -> 4.35 | ... M52: =M51-M39 -> 4.35
A53: Young heifers on farm | B53: head | D53: =D47 -> 10.35 | E53: =E47+D47 -> 20.7 | F53: =F47+E47 -> 20.7 | G53: =G47+F47 -> 20.7 | H53: =H47+G47 -> 20.7 | I53: =I47+H47 -> 20.7 | J53: =J47+I47 -> 20.7 | K53: =K47+J47 -> 20.7 | L53: =L47+K47 -> 20.7 | M53: =M47+L47 -> 20.7
A54: Bulls needed | B54: head | D54: =ROUNDUP(D42/Assumptions!$F$47,0) -> 2 | E54: =ROUNDUP(E42/Assumptions!$F$47,0) -> 2 | F54: =ROUNDUP(F42/Assumptions!$F$47,0) -> 2 | G54: =ROUNDUP(G42/Assumptions!$F$47,0) -> 2 | H54: =ROUNDUP(H42/Assumptions!$F$47,0) -> 2 | I54: =ROUNDUP(I42/Assumptions!$F$47,0) -> 2 | J54: =ROUNDUP(J42/Assumptions!$F$47,0) -> 2 | K54: =ROUNDUP(K42/Assumptions!$F$47,0) -> 2 | ... M54: =ROUNDUP(M42/Assumptions!$F$47,0) -> 2
A56: LAND CHECK
A57: Animal units on farm | B57: AU | D57: =D15+D42+D54+0.5*(D26+D53) -> 84.535 | E57: =E15+E42+E54+0.5*(E26+E53) -> 97.07 | F57: =F15+F42+F54+0.5*(F26+F53) -> 97.07 | G57: =G15+G42+G54+0.5*(G26+G53) -> 97.07 | H57: =H15+H42+H54+0.5*(H26+H53) -> 97.07 | I57: =I15+I42+I54+0.5*(I26+I53) -> 97.07 | J57: =J15+J42+J54+0.5*(J26+J53) -> 97.07 | K57: =K15+K42+K54+0.5*(K26+K53) -> 97.07 | ... M57: =M15+M42+M54+0.5*(M26+M53) -> 97.07
A58: Carrying capacity of land | B58: AU | D58: =Assumptions!$F$10*Assumptions!$F$11 -> 120 | E58: =Assumptions!$F$10*Assumptions!$F$11 -> 120 | F58: =Assumptions!$F$10*Assumptions!$F$11 -> 120 | G58: =Assumptions!$F$10*Assumptions!$F$11 -> 120 | H58: =Assumptions!$F$10*Assumptions!$F$11 -> 120 | I58: =Assumptions!$F$10*Assumptions!$F$11 -> 120 | J58: =Assumptions!$F$10*Assumptions!$F$11 -> 120 | K58: =Assumptions!$F$10*Assumptions!$F$11 -> 120 | ... M58: =Assumptions!$F$10*Assumptions!$F$11 -> 120
A59: Land utilisation | B59: % | D59: =IF(D58=0,0,D57/D58) -> 0.70445833 | E59: =IF(E58=0,0,E57/E58) -> 0.80891667 | F59: =IF(F58=0,0,F57/F58) -> 0.80891667 | G59: =IF(G58=0,0,G57/G58) -> 0.80891667 | H59: =IF(H58=0,0,H57/H58) -> 0.80891667 | I59: =IF(I58=0,0,I57/I58) -> 0.80891667 | J59: =IF(J58=0,0,J57/J58) -> 0.80891667 | K59: =IF(K58=0,0,K57/K58) -> 0.80891667 | ... M59: =IF(M58=0,0,M57/M58) -> 0.80891667
A60: Status | D60: =IF(D59>1,"WARNING","OK") -> OK | E60: =IF(E59>1,"WARNING","OK") -> OK | F60: =IF(F59>1,"WARNING","OK") -> OK | G60: =IF(G59>1,"WARNING","OK") -> OK | H60: =IF(H59>1,"WARNING","OK") -> OK | I60: =IF(I59>1,"WARNING","OK") -> OK | J60: =IF(J59>1,"WARNING","OK") -> OK | K60: =IF(K59>1,"WARNING","OK") -> OK | ... M60: =IF(M59>1,"WARNING","OK") -> OK
A62: WARNING = herd (plus young stock) exceeds the land's carrying capacity in that year: cut herd targets, add land, or budget bought-in feed.

Sheet Revenue
A1: REVENUE - streams by year
A2: Volume from Herd sheet x price (Year-1 price x price inflation x scenario multiplier).
A3: Line item | B3: Unit | C3: Year 0 | D3: Year 1 | E3: Year 2 | F3: Year 3 | G3: Year 4 | H3: Year 5 | I3: Year 6 | J3: Year 7 | K3: Year 8 | L3: Year 9 | M3: Year 10
A4: Year index | C4: 0 | D4: 1 | E4: 2 | F4: 3 | G4: 4 | H4: 5 | I4: 6 | J4: 7 | K4: 8 | L4: 9 | M4: 10
A6: Price inflation factor | B6: index | D6: =(1+Assumptions!$F$15)^(D$4-1) -> 1 | E6: =(1+Assumptions!$F$15)^(E$4-1) -> 1.03 | F6: =(1+Assumptions!$F$15)^(F$4-1) -> 1.0609 | G6: =(1+Assumptions!$F$15)^(G$4-1) -> 1.092727 | H6: =(1+Assumptions!$F$15)^(H$4-1) -> 1.1255088 | I6: =(1+Assumptions!$F$15)^(I$4-1) -> 1.1592741 | J6: =(1+Assumptions!$F$15)^(J$4-1) -> 1.1940523 | K6: =(1+Assumptions!$F$15)^(K$4-1) -> 1.2298739 | ... M6: =(1+Assumptions!$F$15)^(M$4-1) -> 1.3047732
A7: DAIRY REVENUE
A8: 1. Raw milk sales | B8: money | D8: =Herd!D31*Assumptions!$F$22*D$6 -> 55080 | E8: =Herd!E31*Assumptions!$F$22*E$6 -> 56732.4 | F8: =Herd!F31*Assumptions!$F$22*F$6 -> 58434.372 | G8: =Herd!G31*Assumptions!$F$22*G$6 -> 60187.403 | H8: =Herd!H31*Assumptions!$F$22*H$6 -> 61993.025 | I8: =Herd!I31*Assumptions!$F$22*I$6 -> 63852.816 | J8: =Herd!J31*Assumptions!$F$22*J$6 -> 65768.4 | K8: =Herd!K31*Assumptions!$F$22*K$6 -> 67741.453 | ... M8: =Herd!M31*Assumptions!$F$22*M$6 -> 71866.907
A9: 2. Processed dairy products (yoghurt, cheese...) | B9: money | D9: =Herd!D30*Assumptions!$F$22*Assumptions!$F$52*D$6 -> 12240 | E9: =Herd!E30*Assumptions!$F$22*Assumptions!$F$52*E$6 -> 12607.2 | F9: =Herd!F30*Assumptions!$F$22*Assumptions!$F$52*F$6 -> 12985.416 | G9: =Herd!G30*Assumptions!$F$22*Assumptions!$F$52*G$6 -> 13374.978 | H9: =Herd!H30*Assumptions!$F$22*Assumptions!$F$52*H$6 -> 13776.228 | I9: =Herd!I30*Assumptions!$F$22*Assumptions!$F$52*I$6 -> 14189.515 | J9: =Herd!J30*Assumptions!$F$22*Assumptions!$F$52*J$6 -> 14615.2 | K9: =Herd!K30*Assumptions!$F$22*Assumptions!$F$52*K$6 -> 15053.656 | ... M9: =Herd!M30*Assumptions!$F$22*Assumptions!$F$52*M$6 -> 15970.424
A10: 3. Dairy bull calves | B10: money | D10: =Herd!D22*Assumptions!$F$55*Assumptions!$F$25*D$6 -> 588.8 | E10: =Herd!E22*Assumptions!$F$55*Assumptions!$F$25*E$6 -> 606.464 | F10: =Herd!F22*Assumptions!$F$55*Assumptions!$F$25*F$6 -> 624.65792 | G10: =Herd!G22*Assumptions!$F$55*Assumptions!$F$25*G$6 -> 643.39766 | H10: =Herd!H22*Assumptions!$F$55*Assumptions!$F$25*H$6 -> 662.69959 | I10: =Herd!I22*Assumptions!$F$55*Assumptions!$F$25*I$6 -> 682.58057 | J10: =Herd!J22*Assumptions!$F$55*Assumptions!$F$25*J$6 -> 703.05799 | K10: =Herd!K22*Assumptions!$F$55*Assumptions!$F$25*K$6 -> 724.14973 | ... M10: =Herd!M22*Assumptions!$F$55*Assumptions!$F$25*M$6 -> 768.25045
A11: 4. Beef-cross calves (from beef semen on dairy cows) | B11: money | D11: =Herd!D23*Assumptions!$F$56*Assumptions!$F$25*D$6 -> 0 | E11: =Herd!E23*Assumptions!$F$56*Assumptions!$F$25*E$6 -> 0 | F11: =Herd!F23*Assumptions!$F$56*Assumptions!$F$25*F$6 -> 0 | G11: =Herd!G23*Assumptions!$F$56*Assumptions!$F$25*G$6 -> 0 | H11: =Herd!H23*Assumptions!$F$56*Assumptions!$F$25*H$6 -> 0 | I11: =Herd!I23*Assumptions!$F$56*Assumptions!$F$25*I$6 -> 0 | J11: =Herd!J23*Assumptions!$F$56*Assumptions!$F$25*J$6 -> 0 | K11: =Herd!K23*Assumptions!$F$56*Assumptions!$F$25*K$6 -> 0 | ... M11: =Herd!M23*Assumptions!$F$56*Assumptions!$F$25*M$6 -> 0
A12: 5a. Surplus dairy heifers - ordinary | B12: money | D12: =Herd!D25*(1-Assumptions!$F$42)*Assumptions!$F$57*Assumptions!$F$25*D$6 -> 0 | E12: =Herd!E25*(1-Assumptions!$F$42)*Assumptions!$F$57*Assumptions!$F$25*E$6 -> 0 | F12: =Herd!F25*(1-Assumptions!$F$42)*Assumptions!$F$57*Assumptions!$F$25*F$6 -> 4247.8436 | G12: =Herd!G25*(1-Assumptions!$F$42)*Assumptions!$F$57*Assumptions!$F$25*G$6 -> 4375.2789 | H12: =Herd!H25*(1-Assumptions!$F$42)*Assumptions!$F$57*Assumptions!$F$25*H$6 -> 4506.5373 | I12: =Herd!I25*(1-Assumptions!$F$42)*Assumptions!$F$57*Assumptions!$F$25*I$6 -> 4641.7334 | J12: =Herd!J25*(1-Assumptions!$F$42)*Assumptions!$F$57*Assumptions!$F$25*J$6 -> 4780.9854 | K12: =Herd!K25*(1-Assumptions!$F$42)*Assumptions!$F$57*Assumptions!$F$25*K$6 -> 4924.415 | ... M12: =Herd!M25*(1-Assumptions!$F$42)*Assumptions!$F$57*Assumptions!$F$25*M$6 -> 5224.3118
A13: 5b. Surplus dairy heifers - breeding stock | B13: money | D13: =Herd!D25*Assumptions!$F$42*Assumptions!$F$57*Assumptions!$F$44*Assumptions!$F$25*D$6 -> 0 | E13: =Herd!E25*Assumptions!$F$42*Assumptions!$F$57*Assumptions!$F$44*Assumptions!$F$25*E$6 -> 0 | F13: =Herd!F25*Assumptions!$F$42*Assumptions!$F$57*Assumptions!$F$44*Assumptions!$F$25*F$6 -> 0 | G13: =Herd!G25*Assumptions!$F$42*Assumptions!$F$57*Assumptions!$F$44*Assumptions!$F$25*G$6 -> 0 | H13: =Herd!H25*Assumptions!$F$42*Assumptions!$F$57*Assumptions!$F$44*Assumptions!$F$25*H$6 -> 0 | I13: =Herd!I25*Assumptions!$F$42*Assumptions!$F$57*Assumptions!$F$44*Assumptions!$F$25*I$6 -> 0 | J13: =Herd!J25*Assumptions!$F$42*Assumptions!$F$57*Assumptions!$F$44*Assumptions!$F$25*J$6 -> 0 | K13: =Herd!K25*Assumptions!$F$42*Assumptions!$F$57*Assumptions!$F$44*Assumptions!$F$25*K$6 -> 0 | ... M13: =Herd!M25*Assumptions!$F$42*Assumptions!$F$57*Assumptions!$F$44*Assumptions!$F$25*M$6 -> 0
A14: 6. Dairy cull cows | B14: money | D14: =Herd!D8*Assumptions!$F$63*Assumptions!$F$65*Assumptions!$F$25*D$6 -> 5376 | E14: =Herd!E8*Assumptions!$F$63*Assumptions!$F$65*Assumptions!$F$25*E$6 -> 5537.28 | F14: =Herd!F8*Assumptions!$F$63*Assumptions!$F$65*Assumptions!$F$25*F$6 -> 5703.3984 | G14: =Herd!G8*Assumptions!$F$63*Assumptions!$F$65*Assumptions!$F$25*G$6 -> 5874.5004 | H14: =Herd!H8*Assumptions!$F$63*Assumptions!$F$65*Assumptions!$F$25*H$6 -> 6050.7354 | I14: =Herd!I8*Assumptions!$F$63*Assumptions!$F$65*Assumptions!$F$25*I$6 -> 6232.2574 | J14: =Herd!J8*Assumptions!$F$63*Assumptions!$F$65*Assumptions!$F$25*J$6 -> 6419.2251 | K14: =Herd!K8*Assumptions!$F$63*Assumptions!$F$65*Assumptions!$F$25*K$6 -> 6611.8019 | ... M14: =Herd!M8*Assumptions!$F$63*Assumptions!$F$65*Assumptions!$F$25*M$6 -> 7014.4606
A16: BEEF REVENUE
A17: 7. Beef weaners (steers) | B17: money | D17: =Herd!D49*Assumptions!$F$59*Assumptions!$F$60*Assumptions!$F$25*D$6 -> 4554 | E17: =Herd!E49*Assumptions!$F$59*Assumptions!$F$60*Assumptions!$F$25*E$6 -> 4690.62 | F17: =Herd!F49*Assumptions!$F$59*Assumptions!$F$60*Assumptions!$F$25*F$6 -> 4831.3386 | G17: =Herd!G49*Assumptions!$F$59*Assumptions!$F$60*Assumptions!$F$25*G$6 -> 4976.2788 | H17: =Herd!H49*Assumptions!$F$59*Assumptions!$F$60*Assumptions!$F$25*H$6 -> 5125.5671 | I17: =Herd!I49*Assumptions!$F$59*Assumptions!$F$60*Assumptions!$F$25*I$6 -> 5279.3341 | J17: =Herd!J49*Assumptions!$F$59*Assumptions!$F$60*Assumptions!$F$25*J$6 -> 5437.7142 | K17: =Herd!K49*Assumptions!$F$59*Assumptions!$F$60*Assumptions!$F$25*K$6 -> 5600.8456 | ... M17: =Herd!M49*Assumptions!$F$59*Assumptions!$F$60*Assumptions!$F$25*M$6 -> 5941.9371
A18: 8. Finished steers for slaughter | B18: money | D18: =Herd!D50*Assumptions!$F$61*Assumptions!$F$62*Assumptions!$F$25*D$6 -> 0 | E18: =Herd!E50*Assumptions!$F$61*Assumptions!$F$62*Assumptions!$F$25*E$6 -> 0 | F18: =Herd!F50*Assumptions!$F$61*Assumptions!$F$62*Assumptions!$F$25*F$6 -> 0 | G18: =Herd!G50*Assumptions!$F$61*Assumptions!$F$62*Assumptions!$F$25*G$6 -> 0 | H18: =Herd!H50*Assumptions!$F$61*Assumptions!$F$62*Assumptions!$F$25*H$6 -> 0 | I18: =Herd!I50*Assumptions!$F$61*Assumptions!$F$62*Assumptions!$F$25*I$6 -> 0 | J18: =Herd!J50*Assumptions!$F$61*Assumptions!$F$62*Assumptions!$F$25*J$6 -> 0 | K18: =Herd!K50*Assumptions!$F$61*Assumptions!$F$62*Assumptions!$F$25*K$6 -> 0 | ... M18: =Herd!M50*Assumptions!$F$61*Assumptions!$F$62*Assumptions!$F$25*M$6 -> 0
A19: 9a. Surplus beef heifers - ordinary | B19: money | D19: =Herd!D52*(1-Assumptions!$F$43)*Assumptions!$F$58*Assumptions!$F$25*D$6 -> 0 | E19: =Herd!E52*(1-Assumptions!$F$43)*Assumptions!$F$58*Assumptions!$F$25*E$6 -> 0 | F19: =Herd!F52*(1-Assumptions!$F$43)*Assumptions!$F$58*Assumptions!$F$25*F$6 -> 2768.949 | G19: =Herd!G52*(1-Assumptions!$F$43)*Assumptions!$F$58*Assumptions!$F$25*G$6 -> 2852.0175 | H19: =Herd!H52*(1-Assumptions!$F$43)*Assumptions!$F$58*Assumptions!$F$25*H$6 -> 2937.578 | I19: =Herd!I52*(1-Assumptions!$F$43)*Assumptions!$F$58*Assumptions!$F$25*I$6 -> 3025.7053 | J19: =Herd!J52*(1-Assumptions!$F$43)*Assumptions!$F$58*Assumptions!$F$25*J$6 -> 3116.4765 | K19: =Herd!K52*(1-Assumptions!$F$43)*Assumptions!$F$58*Assumptions!$F$25*K$6 -> 3209.9708 | ... M19: =Herd!M52*(1-Assumptions!$F$43)*Assumptions!$F$58*Assumptions!$F$25*M$6 -> 3405.458
A20: 9b. Surplus beef heifers - breeding stock | B20: money | D20: =Herd!D52*Assumptions!$F$43*Assumptions!$F$58*Assumptions!$F$44*Assumptions!$F$25*D$6 -> 0 | E20: =Herd!E52*Assumptions!$F$43*Assumptions!$F$58*Assumptions!$F$44*Assumptions!$F$25*E$6 -> 0 | F20: =Herd!F52*Assumptions!$F$43*Assumptions!$F$58*Assumptions!$F$44*Assumptions!$F$25*F$6 -> 0 | G20: =Herd!G52*Assumptions!$F$43*Assumptions!$F$58*Assumptions!$F$44*Assumptions!$F$25*G$6 -> 0 | H20: =Herd!H52*Assumptions!$F$43*Assumptions!$F$58*Assumptions!$F$44*Assumptions!$F$25*H$6 -> 0 | I20: =Herd!I52*Assumptions!$F$43*Assumptions!$F$58*Assumptions!$F$44*Assumptions!$F$25*I$6 -> 0 | J20: =Herd!J52*Assumptions!$F$43*Assumptions!$F$58*Assumptions!$F$44*Assumptions!$F$25*J$6 -> 0 | K20: =Herd!K52*Assumptions!$F$43*Assumptions!$F$58*Assumptions!$F$44*Assumptions!$F$25*K$6 -> 0 | ... M20: =Herd!M52*Assumptions!$F$43*Assumptions!$F$58*Assumptions!$F$44*Assumptions!$F$25*M$6 -> 0
A21: 10. Beef cull cows | B21: money | D21: =Herd!D35*Assumptions!$F$64*Assumptions!$F$65*Assumptions!$F$25*D$6 -> 3600 | E21: =Herd!E35*Assumptions!$F$64*Assumptions!$F$65*Assumptions!$F$25*E$6 -> 3708 | F21: =Herd!F35*Assumptions!$F$64*Assumptions!$F$65*Assumptions!$F$25*F$6 -> 3819.24 | G21: =Herd!G35*Assumptions!$F$64*Assumptions!$F$65*Assumptions!$F$25*G$6 -> 3933.8172 | H21: =Herd!H35*Assumptions!$F$64*Assumptions!$F$65*Assumptions!$F$25*H$6 -> 4051.8317 | I21: =Herd!I35*Assumptions!$F$64*Assumptions!$F$65*Assumptions!$F$25*I$6 -> 4173.3867 | J21: =Herd!J35*Assumptions!$F$64*Assumptions!$F$65*Assumptions!$F$25*J$6 -> 4298.5883 | K21: =Herd!K35*Assumptions!$F$64*Assumptions!$F$65*Assumptions!$F$25*K$6 -> 4427.5459 | ... M21: =Herd!M35*Assumptions!$F$64*Assumptions!$F$65*Assumptions!$F$25*M$6 -> 4697.1835
A23: OTHER REVENUE
A24: 11. Manure / slurry | B24: money | D24: =(Herd!D15+Herd!D42)*Assumptions!$F$66*D$6 -> 1750 | E24: =(Herd!E15+Herd!E42)*Assumptions!$F$66*E$6 -> 1802.5 | F24: =(Herd!F15+Herd!F42)*Assumptions!$F$66*F$6 -> 1856.575 | G24: =(Herd!G15+Herd!G42)*Assumptions!$F$66*G$6 -> 1912.2722 | H24: =(Herd!H15+Herd!H42)*Assumptions!$F$66*H$6 -> 1969.6404 | I24: =(Herd!I15+Herd!I42)*Assumptions!$F$66*I$6 -> 2028.7296 | J24: =(Herd!J15+Herd!J42)*Assumptions!$F$66*J$6 -> 2089.5915 | K24: =(Herd!K15+Herd!K42)*Assumptions!$F$66*K$6 -> 2152.2793 | ... M24: =(Herd!M15+Herd!M42)*Assumptions!$F$66*M$6 -> 2283.3531
A25: 12. Breeding services (bull hire / AI for outside cows) | B25: money | D25: =Assumptions!$F$46*Assumptions!$F$67*Assumptions!$F$9*D$6 -> 0 | E25: =Assumptions!$F$46*Assumptions!$F$67*Assumptions!$F$9*E$6 -> 0 | F25: =Assumptions!$F$46*Assumptions!$F$67*Assumptions!$F$9*F$6 -> 0 | G25: =Assumptions!$F$46*Assumptions!$F$67*Assumptions!$F$9*G$6 -> 0 | H25: =Assumptions!$F$46*Assumptions!$F$67*Assumptions!$F$9*H$6 -> 0 | I25: =Assumptions!$F$46*Assumptions!$F$67*Assumptions!$F$9*I$6 -> 0 | J25: =Assumptions!$F$46*Assumptions!$F$67*Assumptions!$F$9*J$6 -> 0 | K25: =Assumptions!$F$46*Assumptions!$F$67*Assumptions!$F$9*K$6 -> 0 | ... M25: =Assumptions!$F$46*Assumptions!$F$67*Assumptions!$F$9*M$6 -> 0
A26: 13. Grants / subsidies | B26: money | D26: =IF(D$4<=Assumptions!$F$69,Assumptions!$F$68,0) -> 0 | E26: =IF(E$4<=Assumptions!$F$69,Assumptions!$F$68,0) -> 0 | F26: =IF(F$4<=Assumptions!$F$69,Assumptions!$F$68,0) -> 0 | G26: =IF(G$4<=Assumptions!$F$69,Assumptions!$F$68,0) -> 0 | H26: =IF(H$4<=Assumptions!$F$69,Assumptions!$F$68,0) -> 0 | I26: =IF(I$4<=Assumptions!$F$69,Assumptions!$F$68,0) -> 0 | J26: =IF(J$4<=Assumptions!$F$69,Assumptions!$F$68,0) -> 0 | K26: =IF(K$4<=Assumptions!$F$69,Assumptions!$F$68,0) -> 0 | ... M26: =IF(M$4<=Assumptions!$F$69,Assumptions!$F$68,0) -> 0
A28: TOTAL REVENUE | B28: money | D28: =D8+D9+D10+D11+D12+D13+D14+D17+D18+D19+D20+D21+D24+D25+D26 -> 83188.8 | E28: =E8+E9+E10+E11+E12+E13+E14+E17+E18+E19+E20+E21+E24+E25+E26 -> 85684.464 | F28: =F8+F9+F10+F11+F12+F13+F14+F17+F18+F19+F20+F21+F24+F25+F26 -> 95271.791 | G28: =G8+G9+G10+G11+G12+G13+G14+G17+G18+G19+G20+G21+G24+G25+G26 -> 98129.944 | H28: =H8+H9+H10+H11+H12+H13+H14+H17+H18+H19+H20+H21+H24+H25+H26 -> 101073.84 | I28: =I8+I9+I10+I11+I12+I13+I14+I17+I18+I19+I20+I21+I24+I25+I26 -> 104106.06 | J28: =J8+J9+J10+J11+J12+J13+J14+J17+J18+J19+J20+J21+J24+J25+J26 -> 107229.24 | K28: =K8+K9+K10+K11+K12+K13+K14+K17+K18+K19+K20+K21+K24+K25+K26 -> 110446.12 | ... M28: =M8+M9+M10+M11+M12+M13+M14+M17+M18+M19+M20+M21+M24+M25+M26 -> 117172.29
A30: SUMMARY BY GROUP (chart data)
A31: Milk (raw + processed) | B31: money | D31: =D8+D9 -> 67320 | E31: =E8+E9 -> 69339.6 | F31: =F8+F9 -> 71419.788 | G31: =G8+G9 -> 73562.382 | H31: =H8+H9 -> 75769.253 | I31: =I8+I9 -> 78042.331 | J31: =J8+J9 -> 80383.601 | K31: =K8+K9 -> 82795.109 | ... M31: =M8+M9 -> 87837.331
A32: Calves (bull + cross-bred) | B32: money | D32: =D10+D11 -> 588.8 | E32: =E10+E11 -> 606.464 | F32: =F10+F11 -> 624.65792 | G32: =G10+G11 -> 643.39766 | H32: =H10+H11 -> 662.69959 | I32: =I10+I11 -> 682.58057 | J32: =J10+J11 -> 703.05799 | K32: =K10+K11 -> 724.14973 | ... M32: =M10+M11 -> 768.25045
A33: Surplus heifers (all) | B33: money | D33: =D12+D13+D19+D20 -> 0 | E33: =E12+E13+E19+E20 -> 0 | F33: =F12+F13+F19+F20 -> 7016.7926 | G33: =G12+G13+G19+G20 -> 7227.2964 | H33: =H12+H13+H19+H20 -> 7444.1153 | I33: =I12+I13+I19+I20 -> 7667.4387 | J33: =J12+J13+J19+J20 -> 7897.4619 | K33: =K12+K13+K19+K20 -> 8134.3857 | ... M33: =M12+M13+M19+M20 -> 8629.7698
A34: Cull cows (all) | B34: money | D34: =D14+D21 -> 8976 | E34: =E14+E21 -> 9245.28 | F34: =F14+F21 -> 9522.6384 | G34: =G14+G21 -> 9808.3176 | H34: =H14+H21 -> 10102.567 | I34: =I14+I21 -> 10405.644 | J34: =J14+J21 -> 10717.813 | K34: =K14+K21 -> 11039.348 | ... M34: =M14+M21 -> 11711.644
A35: Beef weaners & finished steers | B35: money | D35: =D17+D18 -> 4554 | E35: =E17+E18 -> 4690.62 | F35: =F17+F18 -> 4831.3386 | G35: =G17+G18 -> 4976.2788 | H35: =H17+H18 -> 5125.5671 | I35: =I17+I18 -> 5279.3341 | J35: =J17+J18 -> 5437.7142 | K35: =K17+K18 -> 5600.8456 | ... M35: =M17+M18 -> 5941.9371
A36: Manure, services, grants | B36: money | D36: =D24+D25+D26 -> 1750 | E36: =E24+E25+E26 -> 1802.5 | F36: =F24+F25+F26 -> 1856.575 | G36: =G24+G25+G26 -> 1912.2722 | H36: =H24+H25+H26 -> 1969.6404 | I36: =I24+I25+I26 -> 2028.7296 | J36: =J24+J25+J26 -> 2089.5915 | K36: =K24+K25+K26 -> 2152.2793 | ... M36: =M24+M25+M26 -> 2283.3531
A38: Dairy revenue (streams 1-6) | B38: money | D38: =D8+D9+D10+D11+D12+D13+D14 -> 73284.8 | E38: =E8+E9+E10+E11+E12+E13+E14 -> 75483.344 | F38: =F8+F9+F10+F11+F12+F13+F14 -> 81995.688 | G38: =G8+G9+G10+G11+G12+G13+G14 -> 84455.559 | H38: =H8+H9+H10+H11+H12+H13+H14 -> 86989.225 | I38: =I8+I9+I10+I11+I12+I13+I14 -> 89598.902 | J38: =J8+J9+J10+J11+J12+J13+J14 -> 92286.869 | K38: =K8+K9+K10+K11+K12+K13+K14 -> 95055.475 | ... M38: =M8+M9+M10+M11+M12+M13+M14 -> 100844.35
A39: Beef revenue (streams 7-10) | B39: money | D39: =D17+D18+D19+D20+D21 -> 8154 | E39: =E17+E18+E19+E20+E21 -> 8398.62 | F39: =F17+F18+F19+F20+F21 -> 11419.528 | G39: =G17+G18+G19+G20+G21 -> 11762.113 | H39: =H17+H18+H19+H20+H21 -> 12114.977 | I39: =I17+I18+I19+I20+I21 -> 12478.426 | J39: =J17+J18+J19+J20+J21 -> 12852.779 | K39: =K17+K18+K19+K20+K21 -> 13238.362 | ... M39: =M17+M18+M19+M20+M21 -> 14044.579
A40: Dairy share of revenue | B40: % | D40: =IF(D28=0,0,D38/D28) -> 0.88094551 | E40: =IF(E28=0,0,E38/E28) -> 0.88094551 | F40: =IF(F28=0,0,F38/F28) -> 0.86065022 | G40: =IF(G28=0,0,G38/G28) -> 0.86065022 | H40: =IF(H28=0,0,H38/H28) -> 0.86065022 | I40: =IF(I28=0,0,I38/I28) -> 0.86065022 | J40: =IF(J28=0,0,J38/J28) -> 0.86065022 | K40: =IF(K28=0,0,K38/K28) -> 0.86065022 | ... M40: =IF(M28=0,0,M38/M28) -> 0.86065022
A41: Animal sales (calves, heifers, culls, weaners) share of revenue | B41: % | D41: =IF(D28=0,0,(D32+D33+D34+D35)/D28) -> 0.16971996 | E41: =IF(E28=0,0,(E32+E33+E34+E35)/E28) -> 0.16971996 | F41: =IF(F28=0,0,(F32+F33+F34+F35)/F28) -> 0.23087031 | G41: =IF(G28=0,0,(G32+G33+G34+G35)/G28) -> 0.23087031 | H41: =IF(H28=0,0,(H32+H33+H34+H35)/H28) -> 0.23087031 | I41: =IF(I28=0,0,(I32+I33+I34+I35)/I28) -> 0.23087031 | J41: =IF(J28=0,0,(J32+J33+J34+J35)/J28) -> 0.23087031 | K41: =IF(K28=0,0,(K32+K33+K34+K35)/K28) -> 0.23087031 | ... M41: =IF(M28=0,0,(M32+M33+M34+M35)/M28) -> 0.23087031

Sheet Opex
A1: OPERATING COSTS - by year
A2: Year-1 unit costs x cost inflation. Feed lines also x scenario feed multiplier.
A3: Line item | B3: Unit | C3: Year 0 | D3: Year 1 | E3: Year 2 | F3: Year 3 | G3: Year 4 | H3: Year 5 | I3: Year 6 | J3: Year 7 | K3: Year 8 | L3: Year 9 | M3: Year 10
A4: Year index | C4: 0 | D4: 1 | E4: 2 | F4: 3 | G4: 4 | H4: 5 | I4: 6 | J4: 7 | K4: 8 | L4: 9 | M4: 10
A6: Cost inflation factor | B6: index | D6: =(1+Assumptions!$F$16)^(D$4-1) -> 1 | E6: =(1+Assumptions!$F$16)^(E$4-1) -> 1.04 | F6: =(1+Assumptions!$F$16)^(F$4-1) -> 1.0816 | G6: =(1+Assumptions!$F$16)^(G$4-1) -> 1.124864 | H6: =(1+Assumptions!$F$16)^(H$4-1) -> 1.1698586 | I6: =(1+Assumptions!$F$16)^(I$4-1) -> 1.2166529 | J6: =(1+Assumptions!$F$16)^(J$4-1) -> 1.265319 | K6: =(1+Assumptions!$F$16)^(K$4-1) -> 1.3159318 | ... M6: =(1+Assumptions!$F$16)^(M$4-1) -> 1.4233118
A7: FEED
A8: Dairy cow feed | B8: money | D8: =Herd!D15*Assumptions!$F$76*Assumptions!$F$24*D$6 -> 19200 | E8: =Herd!E15*Assumptions!$F$76*Assumptions!$F$24*E$6 -> 19968 | F8: =Herd!F15*Assumptions!$F$76*Assumptions!$F$24*F$6 -> 20766.72 | G8: =Herd!G15*Assumptions!$F$76*Assumptions!$F$24*G$6 -> 21597.389 | H8: =Herd!H15*Assumptions!$F$76*Assumptions!$F$24*H$6 -> 22461.284 | I8: =Herd!I15*Assumptions!$F$76*Assumptions!$F$24*I$6 -> 23359.736 | J8: =Herd!J15*Assumptions!$F$76*Assumptions!$F$24*J$6 -> 24294.125 | K8: =Herd!K15*Assumptions!$F$76*Assumptions!$F$24*K$6 -> 25265.89 | ... M8: =Herd!M15*Assumptions!$F$76*Assumptions!$F$24*M$6 -> 27327.587
A9: Dairy heifer & calf feed | B9: money | D9: =Herd!D26*Assumptions!$F$77*Assumptions!$F$24*D$6 -> 2208 | E9: =Herd!E26*Assumptions!$F$77*Assumptions!$F$24*E$6 -> 4592.64 | F9: =Herd!F26*Assumptions!$F$77*Assumptions!$F$24*F$6 -> 4776.3456 | G9: =Herd!G26*Assumptions!$F$77*Assumptions!$F$24*G$6 -> 4967.3994 | H9: =Herd!H26*Assumptions!$F$77*Assumptions!$F$24*H$6 -> 5166.0954 | I9: =Herd!I26*Assumptions!$F$77*Assumptions!$F$24*I$6 -> 5372.7392 | J9: =Herd!J26*Assumptions!$F$77*Assumptions!$F$24*J$6 -> 5587.6488 | K9: =Herd!K26*Assumptions!$F$77*Assumptions!$F$24*K$6 -> 5811.1547 | ... M9: =Herd!M26*Assumptions!$F$77*Assumptions!$F$24*M$6 -> 6285.345
A10: Beef cow feed | B10: money | D10: =Herd!D42*Assumptions!$F$78*Assumptions!$F$24*D$6 -> 3600 | E10: =Herd!E42*Assumptions!$F$78*Assumptions!$F$24*E$6 -> 3744 | F10: =Herd!F42*Assumptions!$F$78*Assumptions!$F$24*F$6 -> 3893.76 | G10: =Herd!G42*Assumptions!$F$78*Assumptions!$F$24*G$6 -> 4049.5104 | H10: =Herd!H42*Assumptions!$F$78*Assumptions!$F$24*H$6 -> 4211.4908 | I10: =Herd!I42*Assumptions!$F$78*Assumptions!$F$24*I$6 -> 4379.9504 | J10: =Herd!J42*Assumptions!$F$78*Assumptions!$F$24*J$6 -> 4555.1485 | K10: =Herd!K42*Assumptions!$F$78*Assumptions!$F$24*K$6 -> 4737.3544 | ... M10: =Herd!M42*Assumptions!$F$78*Assumptions!$F$24*M$6 -> 5123.9225
A11: Beef heifer & calf feed | B11: money | D11: =Herd!D53*Assumptions!$F$79*Assumptions!$F$24*D$6 -> 931.5 | E11: =Herd!E53*Assumptions!$F$79*Assumptions!$F$24*E$6 -> 1937.52 | F11: =Herd!F53*Assumptions!$F$79*Assumptions!$F$24*F$6 -> 2015.0208 | G11: =Herd!G53*Assumptions!$F$79*Assumptions!$F$24*G$6 -> 2095.6216 | H11: =Herd!H53*Assumptions!$F$79*Assumptions!$F$24*H$6 -> 2179.4465 | I11: =Herd!I53*Assumptions!$F$79*Assumptions!$F$24*I$6 -> 2266.6244 | J11: =Herd!J53*Assumptions!$F$79*Assumptions!$F$24*J$6 -> 2357.2893 | K11: =Herd!K53*Assumptions!$F$79*Assumptions!$F$24*K$6 -> 2451.5809 | ... M11: =Herd!M53*Assumptions!$F$79*Assumptions!$F$24*M$6 -> 2651.6299
A12: Finishing feed (steers) | B12: money | D12: =Herd!D50*Assumptions!$F$80*Assumptions!$F$24*D$6 -> 0 | E12: =Herd!E50*Assumptions!$F$80*Assumptions!$F$24*E$6 -> 0 | F12: =Herd!F50*Assumptions!$F$80*Assumptions!$F$24*F$6 -> 0 | G12: =Herd!G50*Assumptions!$F$80*Assumptions!$F$24*G$6 -> 0 | H12: =Herd!H50*Assumptions!$F$80*Assumptions!$F$24*H$6 -> 0 | I12: =Herd!I50*Assumptions!$F$80*Assumptions!$F$24*I$6 -> 0 | J12: =Herd!J50*Assumptions!$F$80*Assumptions!$F$24*J$6 -> 0 | K12: =Herd!K50*Assumptions!$F$80*Assumptions!$F$24*K$6 -> 0 | ... M12: =Herd!M50*Assumptions!$F$80*Assumptions!$F$24*M$6 -> 0
A13: Pasture upkeep | B13: money | D13: =Assumptions!$F$10*Assumptions!$F$81*D$6 -> 2250 | E13: =Assumptions!$F$10*Assumptions!$F$81*E$6 -> 2340 | F13: =Assumptions!$F$10*Assumptions!$F$81*F$6 -> 2433.6 | G13: =Assumptions!$F$10*Assumptions!$F$81*G$6 -> 2530.944 | H13: =Assumptions!$F$10*Assumptions!$F$81*H$6 -> 2632.1818 | I13: =Assumptions!$F$10*Assumptions!$F$81*I$6 -> 2737.469 | J13: =Assumptions!$F$10*Assumptions!$F$81*J$6 -> 2846.9678 | K13: =Assumptions!$F$10*Assumptions!$F$81*K$6 -> 2960.8465 | ... M13: =Assumptions!$F$10*Assumptions!$F$81*M$6 -> 3202.4516
A14: Total feed | B14: money | D14: =SUM(D8:D13) -> 28189.5 | E14: =SUM(E8:E13) -> 32582.16 | F14: =SUM(F8:F13) -> 33885.446 | G14: =SUM(G8:G13) -> 35240.864 | H14: =SUM(H8:H13) -> 36650.499 | I14: =SUM(I8:I13) -> 38116.519 | J14: =SUM(J8:J13) -> 39641.18 | K14: =SUM(K8:K13) -> 41226.827 | ... M14: =SUM(M8:M13) -> 44590.936
A16: HEALTH, BREEDING & REPLACEMENT STOCK
A17: Veterinary & medicines | B17: money | D17: =(Herd!D15+Herd!D42+Herd!D26+Herd!D53)*Assumptions!$F$82*D$6 -> 2091.54 | E17: =(Herd!E15+Herd!E42+Herd!E26+Herd!E53)*Assumptions!$F$82*E$6 -> 2748.8032 | F17: =(Herd!F15+Herd!F42+Herd!F26+Herd!F53)*Assumptions!$F$82*F$6 -> 2858.7553 | G17: =(Herd!G15+Herd!G42+Herd!G26+Herd!G53)*Assumptions!$F$82*G$6 -> 2973.1055 | H17: =(Herd!H15+Herd!H42+Herd!H26+Herd!H53)*Assumptions!$F$82*H$6 -> 3092.0298 | I17: =(Herd!I15+Herd!I42+Herd!I26+Herd!I53)*Assumptions!$F$82*I$6 -> 3215.711 | J17: =(Herd!J15+Herd!J42+Herd!J26+Herd!J53)*Assumptions!$F$82*J$6 -> 3344.3394 | K17: =(Herd!K15+Herd!K42+Herd!K26+Herd!K53)*Assumptions!$F$82*K$6 -> 3478.113 | ... M17: =(Herd!M15+Herd!M42+Herd!M26+Herd!M53)*Assumptions!$F$82*M$6 -> 3761.927
A18: AI / semen (incl. sexed premium) | B18: money | D18: =Herd!D15*(Assumptions!$F$83+Assumptions!$F$38*Assumptions!$F$84)*D$6 -> 720 | E18: =Herd!E15*(Assumptions!$F$83+Assumptions!$F$38*Assumptions!$F$84)*E$6 -> 748.8 | F18: =Herd!F15*(Assumptions!$F$83+Assumptions!$F$38*Assumptions!$F$84)*F$6 -> 778.752 | G18: =Herd!G15*(Assumptions!$F$83+Assumptions!$F$38*Assumptions!$F$84)*G$6 -> 809.90208 | H18: =Herd!H15*(Assumptions!$F$83+Assumptions!$F$38*Assumptions!$F$84)*H$6 -> 842.29816 | I18: =Herd!I15*(Assumptions!$F$83+Assumptions!$F$38*Assumptions!$F$84)*I$6 -> 875.99009 | J18: =Herd!J15*(Assumptions!$F$83+Assumptions!$F$38*Assumptions!$F$84)*J$6 -> 911.02969 | K18: =Herd!K15*(Assumptions!$F$83+Assumptions!$F$38*Assumptions!$F$84)*K$6 -> 947.47088 | ... M18: =Herd!M15*(Assumptions!$F$83+Assumptions!$F$38*Assumptions!$F$84)*M$6 -> 1024.7845
A19: Bull replacement (annualised) | B19: money | D19: =Herd!D54*Assumptions!$F$73/Assumptions!$F$74*D$6 -> 480 | E19: =Herd!E54*Assumptions!$F$73/Assumptions!$F$74*E$6 -> 499.2 | F19: =Herd!F54*Assumptions!$F$73/Assumptions!$F$74*F$6 -> 519.168 | G19: =Herd!G54*Assumptions!$F$73/Assumptions!$F$74*G$6 -> 539.93472 | H19: =Herd!H54*Assumptions!$F$73/Assumptions!$F$74*H$6 -> 561.53211 | I19: =Herd!I54*Assumptions!$F$73/Assumptions!$F$74*I$6 -> 583.99339 | J19: =Herd!J54*Assumptions!$F$73/Assumptions!$F$74*J$6 -> 607.35313 | K19: =Herd!K54*Assumptions!$F$73/Assumptions!$F$74*K$6 -> 631.64725 | ... M19: =Herd!M54*Assumptions!$F$73/Assumptions!$F$74*M$6 -> 683.18967
A20: Replacement dairy heifers bought | B20: money | D20: =Herd!D13*Assumptions!$F$70*Assumptions!$F$25*Revenue!D6 -> 9900 | E20: =Herd!E13*Assumptions!$F$70*Assumptions!$F$25*Revenue!E6 -> 10197 | F20: =Herd!F13*Assumptions!$F$70*Assumptions!$F$25*Revenue!F6 -> 0 | G20: =Herd!G13*Assumptions!$F$70*Assumptions!$F$25*Revenue!G6 -> 0 | H20: =Herd!H13*Assumptions!$F$70*Assumptions!$F$25*Revenue!H6 -> 0 | I20: =Herd!I13*Assumptions!$F$70*Assumptions!$F$25*Revenue!I6 -> 0 | J20: =Herd!J13*Assumptions!$F$70*Assumptions!$F$25*Revenue!J6 -> 0 | K20: =Herd!K13*Assumptions!$F$70*Assumptions!$F$25*Revenue!K6 -> 0 | ... M20: =Herd!M13*Assumptions!$F$70*Assumptions!$F$25*Revenue!M6 -> 0
A21: Replacement beef heifers bought | B21: money | D21: =Herd!D40*Assumptions!$F$71*Assumptions!$F$25*Revenue!D6 -> 4800 | E21: =Herd!E40*Assumptions!$F$71*Assumptions!$F$25*Revenue!E6 -> 4944 | F21: =Herd!F40*Assumptions!$F$71*Assumptions!$F$25*Revenue!F6 -> 0 | G21: =Herd!G40*Assumptions!$F$71*Assumptions!$F$25*Revenue!G6 -> 0 | H21: =Herd!H40*Assumptions!$F$71*Assumptions!$F$25*Revenue!H6 -> 0 | I21: =Herd!I40*Assumptions!$F$71*Assumptions!$F$25*Revenue!I6 -> 0 | J21: =Herd!J40*Assumptions!$F$71*Assumptions!$F$25*Revenue!J6 -> 0 | K21: =Herd!K40*Assumptions!$F$71*Assumptions!$F$25*Revenue!K6 -> 0 | ... M21: =Herd!M40*Assumptions!$F$71*Assumptions!$F$25*Revenue!M6 -> 0
A22: Total health, breeding & replacements | B22: money | D22: =SUM(D17:D21) -> 17991.54 | E22: =SUM(E17:E21) -> 19137.803 | F22: =SUM(F17:F21) -> 4156.6753 | G22: =SUM(G17:G21) -> 4322.9423 | H22: =SUM(H17:H21) -> 4495.86 | I22: =SUM(I17:I21) -> 4675.6944 | J22: =SUM(J17:J21) -> 4862.7222 | K22: =SUM(K17:K21) -> 5057.2311 | ... M22: =SUM(M17:M21) -> 5469.9012
A24: LABOUR
A25: Farm manager | B25: money | D25: =Assumptions!$F$85*D$6 -> 7000 | E25: =Assumptions!$F$85*E$6 -> 7280 | F25: =Assumptions!$F$85*F$6 -> 7571.2 | G25: =Assumptions!$F$85*G$6 -> 7874.048 | H25: =Assumptions!$F$85*H$6 -> 8189.0099 | I25: =Assumptions!$F$85*I$6 -> 8516.5703 | J25: =Assumptions!$F$85*J$6 -> 8857.2331 | K25: =Assumptions!$F$85*K$6 -> 9211.5225 | ... M25: =Assumptions!$F$85*M$6 -> 9963.1827
A26: Farm workers (milkers, herders) | B26: money | D26: =(Herd!D15/Assumptions!$F$87+Herd!D42/Assumptions!$F$88)*Assumptions!$F$86*D$6 -> 4740 | E26: =(Herd!E15/Assumptions!$F$87+Herd!E42/Assumptions!$F$88)*Assumptions!$F$86*E$6 -> 4929.6 | F26: =(Herd!F15/Assumptions!$F$87+Herd!F42/Assumptions!$F$88)*Assumptions!$F$86*F$6 -> 5126.784 | G26: =(Herd!G15/Assumptions!$F$87+Herd!G42/Assumptions!$F$88)*Assumptions!$F$86*G$6 -> 5331.8554 | H26: =(Herd!H15/Assumptions!$F$87+Herd!H42/Assumptions!$F$88)*Assumptions!$F$86*H$6 -> 5545.1296 | I26: =(Herd!I15/Assumptions!$F$87+Herd!I42/Assumptions!$F$88)*Assumptions!$F$86*I$6 -> 5766.9348 | J26: =(Herd!J15/Assumptions!$F$87+Herd!J42/Assumptions!$F$88)*Assumptions!$F$86*J$6 -> 5997.6121 | K26: =(Herd!K15/Assumptions!$F$87+Herd!K42/Assumptions!$F$88)*Assumptions!$F$86*K$6 -> 6237.5166 | ... M26: =(Herd!M15/Assumptions!$F$87+Herd!M42/Assumptions!$F$88)*Assumptions!$F$86*M$6 -> 6746.498
A27: Total labour | B27: money | D27: =D25+D26 -> 11740 | E27: =E25+E26 -> 12209.6 | F27: =F25+F26 -> 12697.984 | G27: =G25+G26 -> 13205.903 | H27: =H25+H26 -> 13734.139 | I27: =I25+I26 -> 14283.505 | J27: =J25+J26 -> 14854.845 | K27: =K25+K26 -> 15449.039 | ... M27: =M25+M26 -> 16709.681
A29: PROCESSING, UTILITIES & OVERHEADS
A30: Milk processing & packaging | B30: money | D30: =Herd!D30*Assumptions!$F$53*D$6 -> 2040 | E30: =Herd!E30*Assumptions!$F$53*E$6 -> 2121.6 | F30: =Herd!F30*Assumptions!$F$53*F$6 -> 2206.464 | G30: =Herd!G30*Assumptions!$F$53*G$6 -> 2294.7226 | H30: =Herd!H30*Assumptions!$F$53*H$6 -> 2386.5115 | I30: =Herd!I30*Assumptions!$F$53*I$6 -> 2481.9719 | J30: =Herd!J30*Assumptions!$F$53*J$6 -> 2581.2508 | K30: =Herd!K30*Assumptions!$F$53*K$6 -> 2684.5008 | ... M30: =Herd!M30*Assumptions!$F$53*M$6 -> 2903.5561
A31: Electricity, water & cleaning (per cow) | B31: money | D31: =Herd!D15*Assumptions!$F$89*D$6 -> 1400 | E31: =Herd!E15*Assumptions!$F$89*E$6 -> 1456 | F31: =Herd!F15*Assumptions!$F$89*F$6 -> 1514.24 | G31: =Herd!G15*Assumptions!$F$89*G$6 -> 1574.8096 | H31: =Herd!H15*Assumptions!$F$89*H$6 -> 1637.802 | I31: =Herd!I15*Assumptions!$F$89*I$6 -> 1703.3141 | J31: =Herd!J15*Assumptions!$F$89*J$6 -> 1771.4466 | K31: =Herd!K15*Assumptions!$F$89*K$6 -> 1842.3045 | ... M31: =Herd!M15*Assumptions!$F$89*M$6 -> 1992.6365
A32: Vehicle fuel & running costs | B32: money | D32: =Assumptions!$F$90*D$6 -> 1800 | E32: =Assumptions!$F$90*E$6 -> 1872 | F32: =Assumptions!$F$90*F$6 -> 1946.88 | G32: =Assumptions!$F$90*G$6 -> 2024.7552 | H32: =Assumptions!$F$90*H$6 -> 2105.7454 | I32: =Assumptions!$F$90*I$6 -> 2189.9752 | J32: =Assumptions!$F$90*J$6 -> 2277.5742 | K32: =Assumptions!$F$90*K$6 -> 2368.6772 | ... M32: =Assumptions!$F$90*M$6 -> 2561.9613
A33: Insurance | B33: money | D33: =Assumptions!$F$92*Capex!$H$47 -> 2402.84 | E33: =Assumptions!$F$92*Capex!$H$47 -> 2402.84 | F33: =Assumptions!$F$92*Capex!$H$47 -> 2402.84 | G33: =Assumptions!$F$92*Capex!$H$47 -> 2402.84 | H33: =Assumptions!$F$92*Capex!$H$47 -> 2402.84 | I33: =Assumptions!$F$92*Capex!$H$47 -> 2402.84 | J33: =Assumptions!$F$92*Capex!$H$47 -> 2402.84 | K33: =Assumptions!$F$92*Capex!$H$47 -> 2402.84 | ... M33: =Assumptions!$F$92*Capex!$H$47 -> 2402.84
A34: Repairs & maintenance | B34: money | D34: =Assumptions!$F$93*Capex!$H$44*D$6 -> 4719 | E34: =Assumptions!$F$93*Capex!$H$44*E$6 -> 4907.76 | F34: =Assumptions!$F$93*Capex!$H$44*F$6 -> 5104.0704 | G34: =Assumptions!$F$93*Capex!$H$44*G$6 -> 5308.2332 | H34: =Assumptions!$F$93*Capex!$H$44*H$6 -> 5520.5625 | I34: =Assumptions!$F$93*Capex!$H$44*I$6 -> 5741.385 | J34: =Assumptions!$F$93*Capex!$H$44*J$6 -> 5971.0404 | K34: =Assumptions!$F$93*Capex!$H$44*K$6 -> 6209.8821 | ... M34: =Assumptions!$F$93*Capex!$H$44*M$6 -> 6716.6084
A35: Transport & marketing | B35: money | D35: =Assumptions!$F$94*Revenue!D28 -> 1663.776 | E35: =Assumptions!$F$94*Revenue!E28 -> 1713.6893 | F35: =Assumptions!$F$94*Revenue!F28 -> 1905.4358 | G35: =Assumptions!$F$94*Revenue!G28 -> 1962.5989 | H35: =Assumptions!$F$94*Revenue!H28 -> 2021.4769 | I35: =Assumptions!$F$94*Revenue!I28 -> 2082.1212 | J35: =Assumptions!$F$94*Revenue!J28 -> 2144.5848 | K35: =Assumptions!$F$94*Revenue!K28 -> 2208.9223 | ... M35: =Assumptions!$F$94*Revenue!M28 -> 2343.4457
A36: Admin, accounting, licences | B36: money | D36: =Assumptions!$F$95*D$6 -> 2500 | E36: =Assumptions!$F$95*E$6 -> 2600 | F36: =Assumptions!$F$95*F$6 -> 2704 | G36: =Assumptions!$F$95*G$6 -> 2812.16 | H36: =Assumptions!$F$95*H$6 -> 2924.6464 | I36: =Assumptions!$F$95*I$6 -> 3041.6323 | J36: =Assumptions!$F$95*J$6 -> 3163.2975 | K36: =Assumptions!$F$95*K$6 -> 3289.8294 | ... M36: =Assumptions!$F$95*M$6 -> 3558.2795
A37: Total processing & overheads | B37: money | D37: =SUM(D30:D36) -> 16525.616 | E37: =SUM(E30:E36) -> 17073.889 | F37: =SUM(F30:F36) -> 17783.93 | G37: =SUM(G30:G36) -> 18380.119 | H37: =SUM(H30:H36) -> 18999.585 | I37: =SUM(I30:I36) -> 19643.24 | J37: =SUM(J30:J36) -> 20312.034 | K37: =SUM(K30:K36) -> 21006.956 | ... M37: =SUM(M30:M36) -> 22479.328
A39: LAND
A40: Land lease | B40: money | D40: =Assumptions!$F$10*Assumptions!$F$14*(1-Assumptions!$F$12)*D$6 -> 6000 | E40: =Assumptions!$F$10*Assumptions!$F$14*(1-Assumptions!$F$12)*E$6 -> 6240 | F40: =Assumptions!$F$10*Assumptions!$F$14*(1-Assumptions!$F$12)*F$6 -> 6489.6 | G40: =Assumptions!$F$10*Assumptions!$F$14*(1-Assumptions!$F$12)*G$6 -> 6749.184 | H40: =Assumptions!$F$10*Assumptions!$F$14*(1-Assumptions!$F$12)*H$6 -> 7019.1514 | I40: =Assumptions!$F$10*Assumptions!$F$14*(1-Assumptions!$F$12)*I$6 -> 7299.9174 | J40: =Assumptions!$F$10*Assumptions!$F$14*(1-Assumptions!$F$12)*J$6 -> 7591.9141 | K40: =Assumptions!$F$10*Assumptions!$F$14*(1-Assumptions!$F$12)*K$6 -> 7895.5907 | ... M40: =Assumptions!$F$10*Assumptions!$F$14*(1-Assumptions!$F$12)*M$6 -> 8539.8709
A41: Land rates / property tax | B41: money | D41: =Assumptions!$F$10*Assumptions!$F$91*D$6 -> 225 | E41: =Assumptions!$F$10*Assumptions!$F$91*E$6 -> 234 | F41: =Assumptions!$F$10*Assumptions!$F$91*F$6 -> 243.36 | G41: =Assumptions!$F$10*Assumptions!$F$91*G$6 -> 253.0944 | H41: =Assumptions!$F$10*Assumptions!$F$91*H$6 -> 263.21818 | I41: =Assumptions!$F$10*Assumptions!$F$91*I$6 -> 273.7469 | J41: =Assumptions!$F$10*Assumptions!$F$91*J$6 -> 284.69678 | K41: =Assumptions!$F$10*Assumptions!$F$91*K$6 -> 296.08465 | ... M41: =Assumptions!$F$10*Assumptions!$F$91*M$6 -> 320.24516
A42: Total land costs | B42: money | D42: =D40+D41 -> 6225 | E42: =E40+E41 -> 6474 | F42: =F40+F41 -> 6732.96 | G42: =G40+G41 -> 7002.2784 | H42: =H40+H41 -> 7282.3695 | I42: =I40+I41 -> 7573.6643 | J42: =J40+J41 -> 7876.6109 | K42: =K40+K41 -> 8191.6753 | ... M42: =M40+M41 -> 8860.116
A44: Subtotal before contingency | B44: money | D44: =D14+D22+D27+D37+D42 -> 80671.656 | E44: =E14+E22+E27+E37+E42 -> 87477.452 | F44: =F14+F22+F27+F37+F42 -> 75256.996 | G44: =G14+G22+G27+G37+G42 -> 78152.108 | H44: =H14+H22+H27+H37+H42 -> 81162.453 | I44: =I14+I22+I27+I37+I42 -> 84292.622 | J44: =J14+J22+J27+J37+J42 -> 87547.392 | K44: =K14+K22+K27+K37+K42 -> 90931.729 | ... M44: =M14+M22+M27+M37+M42 -> 98109.961
A45: Contingency | B45: money | D45: =Assumptions!$F$96*D44 -> 4033.5828 | E45: =Assumptions!$F$96*E44 -> 4373.8726 | F45: =Assumptions!$F$96*F44 -> 3762.8498 | G45: =Assumptions!$F$96*G44 -> 3907.6054 | H45: =Assumptions!$F$96*H44 -> 4058.1226 | I45: =Assumptions!$F$96*I44 -> 4214.6311 | J45: =Assumptions!$F$96*J44 -> 4377.3696 | K45: =Assumptions!$F$96*K44 -> 4546.5864 | ... M45: =Assumptions!$F$96*M44 -> 4905.4981
A46: TOTAL OPERATING COSTS | B46: money | D46: =D44+D45 -> 84705.239 | E46: =E44+E45 -> 91851.325 | F46: =F44+F45 -> 79019.846 | G46: =G44+G45 -> 82059.713 | H46: =H44+H45 -> 85220.575 | I46: =I44+I45 -> 88507.253 | J46: =J44+J45 -> 91924.762 | K46: =K44+K45 -> 95478.315 | ... M46: =M44+M45 -> 103015.46
A47: Opex per breeding cow | B47: money | D47: =IF((Herd!D14+Herd!D41)=0,0,D46/(Herd!D14+Herd!D41)) -> 1210.0748 | E47: =IF((Herd!E14+Herd!E41)=0,0,E46/(Herd!E14+Herd!E41)) -> 1312.1618 | F47: =IF((Herd!F14+Herd!F41)=0,0,F46/(Herd!F14+Herd!F41)) -> 1128.8549 | G47: =IF((Herd!G14+Herd!G41)=0,0,G46/(Herd!G14+Herd!G41)) -> 1172.2816 | H47: =IF((Herd!H14+Herd!H41)=0,0,H46/(Herd!H14+Herd!H41)) -> 1217.4368 | I47: =IF((Herd!I14+Herd!I41)=0,0,I46/(Herd!I14+Herd!I41)) -> 1264.3893 | J47: =IF((Herd!J14+Herd!J41)=0,0,J46/(Herd!J14+Herd!J41)) -> 1313.2109 | K47: =IF((Herd!K14+Herd!K41)=0,0,K46/(Herd!K14+Herd!K41)) -> 1363.9759 | ... M47: =IF((Herd!M14+Herd!M41)=0,0,M46/(Herd!M14+Herd!M41)) -> 1471.6494
A48: Opex as % of revenue | B48: % | D48: =IF(Revenue!D28=0,0,D46/Revenue!D28) -> 1.0182289 | E48: =IF(Revenue!E28=0,0,E46/Revenue!E28) -> 1.0719718 | F48: =IF(Revenue!F28=0,0,F46/Revenue!F28) -> 0.82941493 | G48: =IF(Revenue!G28=0,0,G46/Revenue!G28) -> 0.8362352 | H48: =IF(Revenue!H28=0,0,H46/Revenue!H28) -> 0.84315163 | I48: =IF(Revenue!I28=0,0,I46/Revenue!I28) -> 0.8501643 | J48: =IF(Revenue!J28=0,0,J46/Revenue!J28) -> 0.85727328 | K48: =IF(Revenue!K28=0,0,K46/Revenue!K28) -> 0.8644787 | ... M48: =IF(Revenue!M28=0,0,M46/Revenue!M28) -> 0.8791794

Sheet Financials
A1: FINANCIALS - income statement, loan, tax and cash flow
A2: Tax includes loss carry-forward. Project cash flow is unlevered; equity cash flow is after loan drawdown and repayments.
A3: Line item | B3: Unit | C3: Year 0 | D3: Year 1 | E3: Year 2 | F3: Year 3 | G3: Year 4 | H3: Year 5 | I3: Year 6 | J3: Year 7 | K3: Year 8 | L3: Year 9 | M3: Year 10
A4: Year index | C4: 0 | D4: 1 | E4: 2 | F4: 3 | G4: 4 | H4: 5 | I4: 6 | J4: 7 | K4: 8 | L4: 9 | M4: 10
A6: INCOME STATEMENT
A7: Revenue | B7: money | D7: =Revenue!D28 -> 83188.8 | E7: =Revenue!E28 -> 85684.464 | F7: =Revenue!F28 -> 95271.791 | G7: =Revenue!G28 -> 98129.944 | H7: =Revenue!H28 -> 101073.84 | I7: =Revenue!I28 -> 104106.06 | J7: =Revenue!J28 -> 107229.24 | K7: =Revenue!K28 -> 110446.12 | ... M7: =Revenue!M28 -> 117172.29
A8: Operating costs | B8: money | D8: =Opex!D46 -> 84705.239 | E8: =Opex!E46 -> 91851.325 | F8: =Opex!F46 -> 79019.846 | G8: =Opex!G46 -> 82059.713 | H8: =Opex!H46 -> 85220.575 | I8: =Opex!I46 -> 88507.253 | J8: =Opex!J46 -> 91924.762 | K8: =Opex!K46 -> 95478.315 | ... M8: =Opex!M46 -> 103015.46
A9: EBITDA (profit before interest, tax, depreciation) | B9: money | D9: =D7-D8 -> -1516.4388 | E9: =E7-E8 -> -6166.8611 | F9: =F7-F8 -> 16251.945 | G9: =G7-G8 -> 16070.231 | H9: =H7-H8 -> 15853.267 | I9: =I7-I8 -> 15598.804 | J9: =J7-J8 -> 15304.478 | K9: =K7-K8 -> 14967.802 | ... M9: =M7-M8 -> 14156.826
A10: EBITDA margin | B10: % | D10: =IF(D7=0,0,D9/D7) -> -0.018228882 | E10: =IF(E7=0,0,E9/E7) -> -0.071971753 | F10: =IF(F7=0,0,F9/F7) -> 0.17058507 | G10: =IF(G7=0,0,G9/G7) -> 0.1637648 | H10: =IF(H7=0,0,H9/H7) -> 0.15684837 | I10: =IF(I7=0,0,I9/I7) -> 0.1498357 | J10: =IF(J7=0,0,J9/J7) -> 0.14272672 | K10: =IF(K7=0,0,K9/K7) -> 0.1355213 | ... M10: =IF(M7=0,0,M9/M7) -> 0.1208206
A11: Depreciation | B11: money | D11: =SUMPRODUCT((Capex!$I$6:$I$41>=D$4)*Capex!$J$6:$J$41) -> 15823.4 | E11: =SUMPRODUCT((Capex!$I$6:$I$41>=E$4)*Capex!$J$6:$J$41) -> 15823.4 | F11: =SUMPRODUCT((Capex!$I$6:$I$41>=F$4)*Capex!$J$6:$J$41) -> 15823.4 | G11: =SUMPRODUCT((Capex!$I$6:$I$41>=G$4)*Capex!$J$6:$J$41) -> 15823.4 | H11: =SUMPRODUCT((Capex!$I$6:$I$41>=H$4)*Capex!$J$6:$J$41) -> 15823.4 | I11: =SUMPRODUCT((Capex!$I$6:$I$41>=I$4)*Capex!$J$6:$J$41) -> 14203.4 | J11: =SUMPRODUCT((Capex!$I$6:$I$41>=J$4)*Capex!$J$6:$J$41) -> 14203.4 | K11: =SUMPRODUCT((Capex!$I$6:$I$41>=K$4)*Capex!$J$6:$J$41) -> 14203.4 | ... M11: =SUMPRODUCT((Capex!$I$6:$I$41>=M$4)*Capex!$J$6:$J$41) -> 12078.4
A12: EBIT | B12: money | D12: =D9-D11 -> -17339.839 | E12: =E9-E11 -> -21990.261 | F12: =F9-F11 -> 428.54478 | G12: =G9-G11 -> 246.83103 | H12: =H9-H11 -> 29.867394 | I12: =I9-I11 -> 1395.4045 | J12: =J9-J11 -> 1101.0776 | K12: =K9-K11 -> 764.40173 | ... M12: =M9-M11 -> 2078.426
A13: Interest | B13: money | D13: =D36 -> 11533.632 | E13: =E36 -> 11533.632 | F13: =F36 -> 9885.9703 | G13: =G36 -> 8238.3086 | H13: =H36 -> 6590.6469 | I13: =I36 -> 4942.9851 | J13: =J36 -> 3295.3234 | K13: =K36 -> 1647.6617 | ... M13: =M36 -> 0
A14: Profit before tax | B14: money | D14: =D12-D13 -> -28873.471 | E14: =E12-E13 -> -33523.893 | F14: =F12-F13 -> -9457.4255 | G14: =G12-G13 -> -7991.4775 | H14: =H12-H13 -> -6560.7795 | I14: =I12-I13 -> -3547.5807 | J14: =J12-J13 -> -2194.2458 | K14: =K12-K13 -> -883.25998 | ... M14: =M12-M13 -> 2078.426
A15: Tax losses brought forward | B15: money | D15: =0 -> 0 | E15: =D18 -> 28873.471 | F15: =E18 -> 62397.364 | G15: =F18 -> 71854.789 | H15: =G18 -> 79846.267 | I15: =H18 -> 86407.046 | J15: =I18 -> 89954.627 | K15: =J18 -> 92148.873 | L15: =K18 -> 93032.133 | M15: =L18 -> 90524.367
A16: Losses used this year | B16: money | D16: =MIN(D15,MAX(D14,0)) -> 0 | E16: =MIN(E15,MAX(E14,0)) -> 0 | F16: =MIN(F15,MAX(F14,0)) -> 0 | G16: =MIN(G15,MAX(G14,0)) -> 0 | H16: =MIN(H15,MAX(H14,0)) -> 0 | I16: =MIN(I15,MAX(I14,0)) -> 0 | J16: =MIN(J15,MAX(J14,0)) -> 0 | K16: =MIN(K15,MAX(K14,0)) -> 0 | ... M16: =MIN(M15,MAX(M14,0)) -> 2078.426
A17: Losses added this year | B17: money | D17: =MAX(-D14,0) -> 28873.471 | E17: =MAX(-E14,0) -> 33523.893 | F17: =MAX(-F14,0) -> 9457.4255 | G17: =MAX(-G14,0) -> 7991.4775 | H17: =MAX(-H14,0) -> 6560.7795 | I17: =MAX(-I14,0) -> 3547.5807 | J17: =MAX(-J14,0) -> 2194.2458 | K17: =MAX(-K14,0) -> 883.25998 | ... M17: =MAX(-M14,0) -> 0
A18: Tax losses carried forward | B18: money | D18: =D15-D16+D17 -> 28873.471 | E18: =E15-E16+E17 -> 62397.364 | F18: =F15-F16+F17 -> 71854.789 | G18: =G15-G16+G17 -> 79846.267 | H18: =H15-H16+H17 -> 86407.046 | I18: =I15-I16+I17 -> 89954.627 | J18: =J15-J16+J17 -> 92148.873 | K18: =K15-K16+K17 -> 93032.133 | ... M18: =M15-M16+M17 -> 88445.941
A19: Taxable profit | B19: money | D19: =MAX(D14,0)-D16 -> 0 | E19: =MAX(E14,0)-E16 -> 0 | F19: =MAX(F14,0)-F16 -> 0 | G19: =MAX(G14,0)-G16 -> 0 | H19: =MAX(H14,0)-H16 -> 0 | I19: =MAX(I14,0)-I16 -> 0 | J19: =MAX(J14,0)-J16 -> 0 | K19: =MAX(K14,0)-K16 -> 0 | ... M19: =MAX(M14,0)-M16 -> 0
A20: Income tax | B20: money | D20: =D19*Assumptions!$F$17 -> 0 | E20: =E19*Assumptions!$F$17 -> 0 | F20: =F19*Assumptions!$F$17 -> 0 | G20: =G19*Assumptions!$F$17 -> 0 | H20: =H19*Assumptions!$F$17 -> 0 | I20: =I19*Assumptions!$F$17 -> 0 | J20: =J19*Assumptions!$F$17 -> 0 | K20: =K19*Assumptions!$F$17 -> 0 | ... M20: =M19*Assumptions!$F$17 -> 0
A21: NET PROFIT | B21: money | D21: =D14-D20 -> -28873.471 | E21: =E14-E20 -> -33523.893 | F21: =F14-F20 -> -9457.4255 | G21: =G14-G20 -> -7991.4775 | H21: =H14-H20 -> -6560.7795 | I21: =I14-I20 -> -3547.5807 | J21: =J14-J20 -> -2194.2458 | K21: =K14-K20 -> -883.25998 | ... M21: =M14-M20 -> 2078.426
A23: ENTERPRISE GROSS MARGINS (revenue less direct feed, breeding & replacement costs)
A24: Dairy revenue | B24: money | D24: =Revenue!D38 -> 73284.8 | E24: =Revenue!E38 -> 75483.344 | F24: =Revenue!F38 -> 81995.688 | G24: =Revenue!G38 -> 84455.559 | H24: =Revenue!H38 -> 86989.225 | I24: =Revenue!I38 -> 89598.902 | J24: =Revenue!J38 -> 92286.869 | K24: =Revenue!K38 -> 95055.475 | ... M24: =Revenue!M38 -> 100844.35
A25: Dairy direct costs | B25: money | D25: =Opex!D8+Opex!D9+Opex!D18+Opex!D30+Opex!D20 -> 34068 | E25: =Opex!E8+Opex!E9+Opex!E18+Opex!E30+Opex!E20 -> 37628.04 | F25: =Opex!F8+Opex!F9+Opex!F18+Opex!F30+Opex!F20 -> 28528.282 | G25: =Opex!G8+Opex!G9+Opex!G18+Opex!G30+Opex!G20 -> 29669.413 | H25: =Opex!H8+Opex!H9+Opex!H18+Opex!H30+Opex!H20 -> 30856.189 | I25: =Opex!I8+Opex!I9+Opex!I18+Opex!I30+Opex!I20 -> 32090.437 | J25: =Opex!J8+Opex!J9+Opex!J18+Opex!J30+Opex!J20 -> 33374.054 | K25: =Opex!K8+Opex!K9+Opex!K18+Opex!K30+Opex!K20 -> 34709.017 | ... M25: =Opex!M8+Opex!M9+Opex!M18+Opex!M30+Opex!M20 -> 37541.272
A26: Dairy gross margin | B26: money | D26: =D24-D25 -> 39216.8 | E26: =E24-E25 -> 37855.304 | F26: =F24-F25 -> 53467.406 | G26: =G24-G25 -> 54786.146 | H26: =H24-H25 -> 56133.036 | I26: =I24-I25 -> 57508.465 | J26: =J24-J25 -> 58912.815 | K26: =K24-K25 -> 60346.459 | ... M26: =M24-M25 -> 63303.081
A27: Dairy gross margin % | B27: % | D27: =IF(D24=0,0,D26/D24) -> 0.5351287 | E27: =IF(E24=0,0,E26/E24) -> 0.50150539 | F27: =IF(F24=0,0,F26/F24) -> 0.65207583 | G27: =IF(G24=0,0,G26/G24) -> 0.64869793 | H27: =IF(H24=0,0,H26/H24) -> 0.64528723 | I27: =IF(I24=0,0,I26/I24) -> 0.64184341 | J27: =IF(J24=0,0,J26/J24) -> 0.63836616 | K27: =IF(K24=0,0,K26/K24) -> 0.63485516 | ... M27: =IF(M24=0,0,M26/M24) -> 0.62773055
A28: Beef revenue (incl. services) | B28: money | D28: =Revenue!D39+Revenue!D25 -> 8154 | E28: =Revenue!E39+Revenue!E25 -> 8398.62 | F28: =Revenue!F39+Revenue!F25 -> 11419.528 | G28: =Revenue!G39+Revenue!G25 -> 11762.113 | H28: =Revenue!H39+Revenue!H25 -> 12114.977 | I28: =Revenue!I39+Revenue!I25 -> 12478.426 | J28: =Revenue!J39+Revenue!J25 -> 12852.779 | K28: =Revenue!K39+Revenue!K25 -> 13238.362 | ... M28: =Revenue!M39+Revenue!M25 -> 14044.579
A29: Beef direct costs | B29: money | D29: =Opex!D10+Opex!D11+Opex!D12+Opex!D19+Opex!D21 -> 9811.5 | E29: =Opex!E10+Opex!E11+Opex!E12+Opex!E19+Opex!E21 -> 11124.72 | F29: =Opex!F10+Opex!F11+Opex!F12+Opex!F19+Opex!F21 -> 6427.9488 | G29: =Opex!G10+Opex!G11+Opex!G12+Opex!G19+Opex!G21 -> 6685.0668 | H29: =Opex!H10+Opex!H11+Opex!H12+Opex!H19+Opex!H21 -> 6952.4694 | I29: =Opex!I10+Opex!I11+Opex!I12+Opex!I19+Opex!I21 -> 7230.5682 | J29: =Opex!J10+Opex!J11+Opex!J12+Opex!J19+Opex!J21 -> 7519.7909 | K29: =Opex!K10+Opex!K11+Opex!K12+Opex!K19+Opex!K21 -> 7820.5826 | ... M29: =Opex!M10+Opex!M11+Opex!M12+Opex!M19+Opex!M21 -> 8458.7421
A30: Beef gross margin | B30: money | D30: =D28-D29 -> -1657.5 | E30: =E28-E29 -> -2726.1 | F30: =F28-F29 -> 4991.5788 | G30: =G28-G29 -> 5077.0467 | H30: =H28-H29 -> 5162.5074 | I30: =I28-I29 -> 5247.8579 | J30: =J28-J29 -> 5332.988 | K30: =K28-K29 -> 5417.7797 | ... M30: =M28-M29 -> 5585.8364
A31: Beef gross margin % | B31: % | D31: =IF(D28=0,0,D30/D28) -> -0.20327447 | E31: =IF(E28=0,0,E30/E28) -> -0.32458904 | F31: =IF(F28=0,0,F30/F28) -> 0.43710904 | G31: =IF(G28=0,0,G30/G28) -> 0.43164408 | H31: =IF(H28=0,0,H30/H28) -> 0.42612607 | I31: =IF(I28=0,0,I30/I28) -> 0.42055447 | J31: =IF(J28=0,0,J30/J28) -> 0.41492879 | K31: =IF(K28=0,0,K30/K28) -> 0.40924849 | ... M31: =IF(M28=0,0,M30/M28) -> 0.3977219
A33: LOAN SCHEDULE
A34: Loan drawdown | B34: money | C34: =Assumptions!$F$101*Capex!$H$47 -> 96113.6
A35: Opening balance | B35: money | D35: =C38 -> 96113.6 | E35: =D38 -> 96113.6 | F35: =E38 -> 82383.086 | G35: =F38 -> 68652.571 | H35: =G38 -> 54922.057 | I35: =H38 -> 41191.543 | J35: =I38 -> 27461.029 | K35: =J38 -> 13730.514 | ... M35: =L38 -> 0
A36: Interest | B36: money | D36: =D35*Assumptions!$F$102 -> 11533.632 | E36: =E35*Assumptions!$F$102 -> 11533.632 | F36: =F35*Assumptions!$F$102 -> 9885.9703 | G36: =G35*Assumptions!$F$102 -> 8238.3086 | H36: =H35*Assumptions!$F$102 -> 6590.6469 | I36: =I35*Assumptions!$F$102 -> 4942.9851 | J36: =J35*Assumptions!$F$102 -> 3295.3234 | K36: =K35*Assumptions!$F$102 -> 1647.6617 | ... M36: =M35*Assumptions!$F$102 -> 0
A37: Principal repayment | B37: money | D37: =IF(D$4<=Assumptions!$F$104,0,MIN(D35,$C$34/MAX(1,Assumptions!$F$103-Assumptions!$F$104))) -> 0 | E37: =IF(E$4<=Assumptions!$F$104,0,MIN(E35,$C$34/MAX(1,Assumptions!$F$103-Assumptions!$F$104))) -> 13730.514 | F37: =IF(F$4<=Assumptions!$F$104,0,MIN(F35,$C$34/MAX(1,Assumptions!$F$103-Assumptions!$F$104))) -> 13730.514 | G37: =IF(G$4<=Assumptions!$F$104,0,MIN(G35,$C$34/MAX(1,Assumptions!$F$103-Assumptions!$F$104))) -> 13730.514 | H37: =IF(H$4<=Assumptions!$F$104,0,MIN(H35,$C$34/MAX(1,Assumptions!$F$103-Assumptions!$F$104))) -> 13730.514 | I37: =IF(I$4<=Assumptions!$F$104,0,MIN(I35,$C$34/MAX(1,Assumptions!$F$103-Assumptions!$F$104))) -> 13730.514 | J37: =IF(J$4<=Assumptions!$F$104,0,MIN(J35,$C$34/MAX(1,Assumptions!$F$103-Assumptions!$F$104))) -> 13730.514 | K37: =IF(K$4<=Assumptions!$F$104,0,MIN(K35,$C$34/MAX(1,Assumptions!$F$103-Assumptions!$F$104))) -> 13730.514 | ... M37: =IF(M$4<=Assumptions!$F$104,0,MIN(M35,$C$34/MAX(1,Assumptions!$F$103-Assumptions!$F$104))) -> 0
A38: Closing balance | B38: money | C38: =C34 -> 96113.6 | D38: =D35-D37 -> 96113.6 | E38: =E35-E37 -> 82383.086 | F38: =F35-F37 -> 68652.571 | G38: =G35-G37 -> 54922.057 | H38: =H35-H37 -> 41191.543 | I38: =I35-I37 -> 27461.029 | J38: =J35-J37 -> 13730.514 | K38: =K35-K37 -> 0 | ... M38: =M35-M37 -> 0
A40: TERMINAL VALUE (Year 10 only)
A41: Breeding herd at market value | B41: money | M41: =Herd!M14*Assumptions!$F$70*Assumptions!$F$25*Revenue!M6+Herd!M41*Assumptions!$F$71*Assumptions!$F$25*Revenue!M6 -> 88724.577
A42: Net book value of assets | B42: money | M42: =MAX(0,Capex!$H$47-Capex!$H$43-SUM(D11:M11)) -> 24000
A43: Terminal value included in returns | B43: money | M43: =Assumptions!$F$19*(M41+M42) -> 112724.58
A45: CASH FLOW
A46: EBITDA | B46: money | C46: =C9 -> 0 | D46: =D9 -> -1516.4388 | E46: =E9 -> -6166.8611 | F46: =F9 -> 16251.945 | G46: =G9 -> 16070.231 | H46: =H9 -> 15853.267 | I46: =I9 -> 15598.804 | J46: =J9 -> 15304.478 | ... M46: =M9 -> 14156.826
A47: Income tax paid | B47: money | C47: =-C20 -> 0 | D47: =-D20 -> 0 | E47: =-E20 -> 0 | F47: =-F20 -> 0 | G47: =-G20 -> 0 | H47: =-H20 -> 0 | I47: =-I20 -> 0 | J47: =-J20 -> 0 | ... M47: =-M20 -> 0
A48: Interest paid | B48: money | C48: =-C36 -> 0 | D48: =-D36 -> -11533.632 | E48: =-E36 -> -11533.632 | F48: =-F36 -> -9885.9703 | G48: =-G36 -> -8238.3086 | H48: =-H36 -> -6590.6469 | I48: =-I36 -> -4942.9851 | J48: =-J36 -> -3295.3234 | ... M48: =-M36 -> 0
A49: Principal repaid | B49: money | C49: =-C37 -> 0 | D49: =-D37 -> 0 | E49: =-E37 -> -13730.514 | F49: =-F37 -> -13730.514 | G49: =-G37 -> -13730.514 | H49: =-H37 -> -13730.514 | I49: =-I37 -> -13730.514 | J49: =-J37 -> -13730.514 | ... M49: =-M37 -> 0
A50: Capex (Yr 0 initial; then sustaining) | B50: money | C50: =-Capex!$H$47 -> -240284 | D50: =-Assumptions!$F$100*Capex!$H$44*Revenue!D6 -> -2359.5 | E50: =-Assumptions!$F$100*Capex!$H$44*Revenue!E6 -> -2430.285 | F50: =-Assumptions!$F$100*Capex!$H$44*Revenue!F6 -> -2503.1935 | G50: =-Assumptions!$F$100*Capex!$H$44*Revenue!G6 -> -2578.2894 | H50: =-Assumptions!$F$100*Capex!$H$44*Revenue!H6 -> -2655.638 | I50: =-Assumptions!$F$100*Capex!$H$44*Revenue!I6 -> -2735.3072 | J50: =-Assumptions!$F$100*Capex!$H$44*Revenue!J6 -> -2817.3664 | K50: =-Assumptions!$F$100*Capex!$H$44*Revenue!K6 -> -2901.8874 | ... M50: =-Assumptions!$F$100*Capex!$H$44*Revenue!M6 -> -3078.6123
A51: Working capital reserve (funded Yr 0, released Yr 10) | B51: money | C51: =IF(C$4=0,-Assumptions!$F$20/12*Opex!$D$46,IF(C$4=10,Assumptions!$F$20/12*Opex!$D$46,0)) -> -21176.31 | D51: =IF(D$4=0,-Assumptions!$F$20/12*Opex!$D$46,IF(D$4=10,Assumptions!$F$20/12*Opex!$D$46,0)) -> 0 | E51: =IF(E$4=0,-Assumptions!$F$20/12*Opex!$D$46,IF(E$4=10,Assumptions!$F$20/12*Opex!$D$46,0)) -> 0 | F51: =IF(F$4=0,-Assumptions!$F$20/12*Opex!$D$46,IF(F$4=10,Assumptions!$F$20/12*Opex!$D$46,0)) -> 0 | G51: =IF(G$4=0,-Assumptions!$F$20/12*Opex!$D$46,IF(G$4=10,Assumptions!$F$20/12*Opex!$D$46,0)) -> 0 | H51: =IF(H$4=0,-Assumptions!$F$20/12*Opex!$D$46,IF(H$4=10,Assumptions!$F$20/12*Opex!$D$46,0)) -> 0 | I51: =IF(I$4=0,-Assumptions!$F$20/12*Opex!$D$46,IF(I$4=10,Assumptions!$F$20/12*Opex!$D$46,0)) -> 0 | J51: =IF(J$4=0,-Assumptions!$F$20/12*Opex!$D$46,IF(J$4=10,Assumptions!$F$20/12*Opex!$D$46,0)) -> 0 | ... M51: =IF(M$4=0,-Assumptions!$F$20/12*Opex!$D$46,IF(M$4=10,Assumptions!$F$20/12*Opex!$D$46,0)) -> 21176.31
A52: Loan drawdown | B52: money | C52: =C34 -> 96113.6 | D52: =D34 -> 0 | E52: =E34 -> 0 | F52: =F34 -> 0 | G52: =G34 -> 0 | H52: =H34 -> 0 | I52: =I34 -> 0 | J52: =J34 -> 0 | ... M52: =M34 -> 0
A53: Terminal value | B53: money | C53: =IF(C$4=10,$M$43,0) -> 0 | D53: =IF(D$4=10,$M$43,0) -> 0 | E53: =IF(E$4=10,$M$43,0) -> 0 | F53: =IF(F$4=10,$M$43,0) -> 0 | G53: =IF(G$4=10,$M$43,0) -> 0 | H53: =IF(H$4=10,$M$43,0) -> 0 | I53: =IF(I$4=10,$M$43,0) -> 0 | J53: =IF(J$4=10,$M$43,0) -> 0 | ... M53: =IF(M$4=10,$M$43,0) -> 112724.58
A54: Repay any loan outstanding at end of Year 10 | B54: money | C54: =-IF(C$4=10,C38,0) -> 0 | D54: =-IF(D$4=10,D38,0) -> 0 | E54: =-IF(E$4=10,E38,0) -> 0 | F54: =-IF(F$4=10,F38,0) -> 0 | G54: =-IF(G$4=10,G38,0) -> 0 | H54: =-IF(H$4=10,H38,0) -> 0 | I54: =-IF(I$4=10,I38,0) -> 0 | J54: =-IF(J$4=10,J38,0) -> 0 | ... M54: =-IF(M$4=10,M38,0) -> 0
A55: Memo: tax on EBIT (unlevered, for project cash flow) | B55: money | C55: =-MAX(0,C12)*Assumptions!$F$17 -> 0 | D55: =-MAX(0,D12)*Assumptions!$F$17 -> 0 | E55: =-MAX(0,E12)*Assumptions!$F$17 -> 0 | F55: =-MAX(0,F12)*Assumptions!$F$17 -> -107.1362 | G55: =-MAX(0,G12)*Assumptions!$F$17 -> -61.707757 | H55: =-MAX(0,H12)*Assumptions!$F$17 -> -7.4668485 | I55: =-MAX(0,I12)*Assumptions!$F$17 -> -348.85111 | J55: =-MAX(0,J12)*Assumptions!$F$17 -> -275.2694 | ... M55: =-MAX(0,M12)*Assumptions!$F$17 -> -519.6065
A57: PROJECT CASH FLOW excl. terminal value | B57: money | C57: =C46+C55+C50+C51 -> -261460.31 | D57: =D46+D55+D50+D51 -> -3875.9388 | E57: =E46+E55+E50+E51 -> -8597.1461 | F57: =F46+F55+F50+F51 -> 13641.615 | G57: =G46+G55+G50+G51 -> 13430.234 | H57: =H46+H55+H50+H51 -> 13190.163 | I57: =I46+I55+I50+I51 -> 12514.646 | J57: =J46+J55+J50+J51 -> 12211.842 | ... M57: =M46+M55+M50+M51 -> 31734.917
A58: PROJECT CASH FLOW incl. terminal value | B58: money | C58: =C57+C53 -> -261460.31 | D58: =D57+D53 -> -3875.9388 | E58: =E57+E53 -> -8597.1461 | F58: =F57+F53 -> 13641.615 | G58: =G57+G53 -> 13430.234 | H58: =H57+H53 -> 13190.163 | I58: =I57+I53 -> 12514.646 | J58: =J57+J53 -> 12211.842 | ... M58: =M57+M53 -> 144459.49
A59: EQUITY CASH FLOW (after loan) | B59: money | C59: =C46+C47+C48+C49+C50+C51+C52+C53+C54 -> -165346.71 | D59: =D46+D47+D48+D49+D50+D51+D52+D53+D54 -> -15409.571 | E59: =E46+E47+E48+E49+E50+E51+E52+E53+E54 -> -33861.292 | F59: =F46+F47+F48+F49+F50+F51+F52+F53+F54 -> -9867.7333 | G59: =G46+G47+G48+G49+G50+G51+G52+G53+G54 -> -8476.8812 | H59: =H46+H47+H48+H49+H50+H51+H52+H53+H54 -> -7123.5318 | I59: =I46+I47+I48+I49+I50+I51+I52+I53+I54 -> -5810.0022 | J59: =J46+J47+J48+J49+J50+J51+J52+J53+J54 -> -4538.7265 | ... M59: =M46+M47+M48+M49+M50+M51+M52+M53+M54 -> 144979.1
A60: Cumulative project cash flow (excl. TV) | B60: money | C60: =C57 -> -261460.31 | D60: =C60+D57 -> -265336.25 | E60: =D60+E57 -> -273933.39 | F60: =E60+F57 -> -260291.78 | G60: =F60+G57 -> -246861.55 | H60: =G60+H57 -> -233671.38 | I60: =H60+I57 -> -221156.74 | J60: =I60+J57 -> -208944.9 | K60: =J60+K57 -> -197070.08 | ... M60: =L60+M57 -> -154364.88
A61: Cumulative project cash flow (incl. TV) | B61: money | C61: =C58 -> -261460.31 | D61: =C61+D58 -> -265336.25 | E61: =D61+E58 -> -273933.39 | F61: =E61+F58 -> -260291.78 | G61: =F61+G58 -> -246861.55 | H61: =G61+H58 -> -233671.38 | I61: =H61+I58 -> -221156.74 | J61: =I61+J58 -> -208944.9 | K61: =J61+K58 -> -197070.08 | ... M61: =L61+M58 -> -41640.308
A62: Cumulative equity cash flow | B62: money | C62: =C59 -> -165346.71 | D62: =C62+D59 -> -180756.28 | E62: =D62+E59 -> -214617.57 | F62: =E62+F59 -> -224485.31 | G62: =F62+G59 -> -232962.19 | H62: =G62+H59 -> -240085.72 | I62: =H62+I59 -> -245895.72 | J62: =I62+J59 -> -250434.45 | K62: =J62+K59 -> -253746.71 | ... M62: =L62+M59 -> -97170.388
A63: Payback helper (year when cumulative turns positive) | B63: yrs | D63: =IF(AND(D60>=0,C60<0),(D$4-1)+(-C60)/D57,"") | E63: =IF(AND(E60>=0,D60<0),(E$4-1)+(-D60)/E57,"") | F63: =IF(AND(F60>=0,E60<0),(F$4-1)+(-E60)/F57,"") | G63: =IF(AND(G60>=0,F60<0),(G$4-1)+(-F60)/G57,"") | H63: =IF(AND(H60>=0,G60<0),(H$4-1)+(-G60)/H57,"") | I63: =IF(AND(I60>=0,H60<0),(I$4-1)+(-H60)/I57,"") | J63: =IF(AND(J60>=0,I60<0),(J$4-1)+(-I60)/J57,"") | K63: =IF(AND(K60>=0,J60<0),(K$4-1)+(-J60)/K57,"") | ... M63: =IF(AND(M60>=0,L60<0),(M$4-1)+(-L60)/M57,"")
A65: DEBT COVER
A66: Cash after debt service (before terminal items) | B66: money | D66: =D46+D47+D48+D49+D50 -> -15409.571 | E66: =E46+E47+E48+E49+E50 -> -33861.292 | F66: =F46+F47+F48+F49+F50 -> -9867.7333 | G66: =G46+G47+G48+G49+G50 -> -8476.8812 | H66: =H46+H47+H48+H49+H50 -> -7123.5318 | I66: =I46+I47+I48+I49+I50 -> -5810.0022 | J66: =J46+J47+J48+J49+J50 -> -4538.7265 | K66: =K46+K47+K48+K49+K50 -> -3312.2617 | ... M66: =M46+M47+M48+M49+M50 -> 11078.214
A67: Debt service cover ratio (DSCR) | B67: x | D67: =IF((D36+D37)=0,"",(D9-D20)/(D36+D37)) -> -0.13147973 | E67: =IF((E36+E37)=0,"",(E9-E20)/(E36+E37)) -> -0.24409537 | F67: =IF((F36+F37)=0,"",(F9-F20)/(F36+F37)) -> 0.68816105 | G67: =IF((G36+G37)=0,"",(G9-G20)/(G36+G37)) -> 0.73150169 | H67: =IF((H36+H37)=0,"",(H9-H20)/(H36+H37)) -> 0.7801359 | I67: =IF((I36+I37)=0,"",(I9-I20)/(I36+I37)) -> 0.83534447 | J67: =IF((J36+J37)=0,"",(J9-J20)/(J36+J37)) -> 0.89889719 | K67: =IF((K36+K37)=0,"",(K9-K20)/(K36+K37)) -> 0.9733145 | ... M67: =IF((M36+M37)=0,"",(M9-M20)/(M36+M37))

Sheet Returns
A1: RETURNS - investment, IRR, NPV, payback, break-even
A2: All values are live and follow the scenario selector on Assumptions. Currency = placeholder.
A4: Active scenario
A5: Scenario running | B5: =CHOOSE(Assumptions!$F$6,"Base","Downside","Upside") -> Base
A7: INVESTMENT
A8: Initial capex (animals + infrastructure + land + contingency) | B8: =Capex!$H$47 -> 240284
A9: Working capital reserve | B9: =-Financials!C51 -> 21176.31
A10: TOTAL INITIAL INVESTMENT | B10: =B8+B9 -> 261460.31
A11: Investment per breeding cow | B11: =IF((Assumptions!$F$31*Assumptions!$F$8+Assumptions!$F$33*Assumptions!$F$9)=0,0,B10/(Assumptions!$F$31*Assumptions!$F$8+Assumptions!$F$33*Assumptions!$F$9)) -> 3735.1473
A12: Loan | B12: =Financials!C34 -> 96113.6
A13: Equity required | B13: =B10-B12 -> 165346.71
A15: OPERATING RESULT (Year 5, Year-5 money)
A16: Year 5 revenue | B16: =Financials!H7 -> 101073.84
A17: Year 5 EBITDA | B17: =Financials!H9 -> 15853.267
A18: Year 5 EBITDA margin | B18: =Financials!H10 -> 0.15684837
A19: Year 5 net profit | B19: =Financials!H21 -> -6560.7795
A20: Year 5 share of revenue from animal sales (calves, heifers, culls, weaners) | B20: =Revenue!H41 -> 0.23087031
A22: RETURNS
A23: Project IRR (incl. terminal value) | B23: =IFERROR(IRR(Financials!C58:M58),IFERROR(IRR(Financials!C58:M58,-0.2),"n/a")) -> -0.019414222 | C23: Unlevered; compare with hurdle rate
A24: Project IRR (excl. terminal value, cash only) | B24: =IFERROR(IRR(Financials!C57:M57),IFERROR(IRR(Financials!C57:M57,-0.2),"n/a")) -> -0.10841321 | C24: Harsh test: ignores the value of the herd and assets at Year 10
A25: Equity IRR (after loan) | B25: =IFERROR(IRR(Financials!C59:M59),IFERROR(IRR(Financials!C59:M59,-0.2),"n/a")) -> -0.05375369
A26: Hurdle rate | B26: =Assumptions!$F$18 -> 0.12
A27: Project NPV at hurdle rate (incl. TV) | B27: =Financials!C58+NPV(Assumptions!$F$18,Financials!D58:M58) -> -178916.67 | C27: Positive = beats hurdle rate
A28: Payback (years, excl. TV) | B28: =IF(COUNT(Financials!D63:M63)=0,"> 10 yrs",MIN(Financials!D63:M63)) -> > 10 yrs
A29: Minimum DSCR (Years 1-10) | B29: =IF(COUNT(Financials!D67:M67)=0,"n/a",MIN(Financials!D67:M67)) -> -0.24409537 | C29: Banks usually want 1.3x or more
A30: Deepest cumulative equity cash position | B30: =MIN(Financials!C62:M62) -> -253746.71 | C30: Cash you need to survive before it turns around
A32: BREAK-EVEN (Year 5, before tax, Year-1 price terms)
A33: Break-even raw milk price - cash (EBITDA = 0) | B33: =IF(Herd!H31*Revenue!H6=0,"n/a",Assumptions!$F$22-Financials!H9/(Herd!H31*Revenue!H6)) -> 0.44656402 | C33: Per litre. Compare with your actual milk price.
A34: Break-even raw milk price - full cost (after depreciation & interest) | B34: =IF(Herd!H31*Revenue!H6=0,"n/a",Assumptions!$F$22-(Financials!H9-Financials!H11-Financials!H13)/(Herd!H31*Revenue!H6)) -> 0.66349856
A36: CHECKS
A37: Land carrying capacity | B37: =IF(COUNTIF(Herd!D60:M60,"WARNING")>0,"WARNING: herd exceeds land in some year","OK") -> OK
A38: Year-1 working capital reserve | B38: =Monthly_Y1!B22 -> OK - reserve covers Year 1

Sheet Breeding_Economics
A1: BREEDING ECONOMICS - what does one cow earn from calves vs milk / weaners?
A2: Per-cow, Year-1 prices, live scenario. Answers: 'if my cows calve, can I make more money from the calves?' Blue cells in this sheet are strategy inputs you can change.
A4: A. DAIRY COW: calf strategy (income per cow per year)
A5: Per dairy cow per year | B5: A. Pure dairy (as designed) | C5: B. Sexed semen (mostly heifers) | D5: C. All beef-cross calves | E5: D. 30% sexed + 70% beef-cross
A6: Share of cows served with BEEF semen | B6: 0 | C6: 0 | D6: 1 | E6: 0.7
A7: Share of cows served with SEXED dairy semen | B7: 0 | C7: 1 | D7: 0 | E7: 0.3
A8: Calves surviving per cow | B8: =Assumptions!$F$26*(1-Assumptions!$F$29) -> 0.736 | C8: =Assumptions!$F$26*(1-Assumptions!$F$29) -> 0.736 | D8: =Assumptions!$F$26*(1-Assumptions!$F$29) -> 0.736 | E8: =Assumptions!$F$26*(1-Assumptions!$F$29) -> 0.736
A9: Heifer calves per cow | B9: =B8*(B7*Assumptions!$F$39+(1-B6-B7)*Assumptions!$F$37) -> 0.368 | C9: =C8*(C7*Assumptions!$F$39+(1-C6-C7)*Assumptions!$F$37) -> 0.6624 | D9: =D8*(D7*Assumptions!$F$39+(1-D6-D7)*Assumptions!$F$37) -> 0 | E9: =E8*(E7*Assumptions!$F$39+(1-E6-E7)*Assumptions!$F$37) -> 0.19872
A10: Pure dairy bull calves per cow | B10: =B8*(B7*(1-Assumptions!$F$39)+(1-B6-B7)*(1-Assumptions!$F$37)) -> 0.368 | C10: =C8*(C7*(1-Assumptions!$F$39)+(1-C6-C7)*(1-Assumptions!$F$37)) -> 0.0736 | D10: =D8*(D7*(1-Assumptions!$F$39)+(1-D6-D7)*(1-Assumptions!$F$37)) -> 0 | E10: =E8*(E7*(1-Assumptions!$F$39)+(1-E6-E7)*(1-Assumptions!$F$37)) -> 0.02208
A11: Beef-cross calves per cow | B11: =B8*B6 -> 0 | C11: =C8*C6 -> 0 | D11: =D8*D6 -> 0.736 | E11: =E8*E6 -> 0.5152
A12: Replacement heifers needed per cow (culls + deaths) | B12: =Assumptions!$F$35+Assumptions!$F$28 -> 0.23 | C12: =Assumptions!$F$35+Assumptions!$F$28 -> 0.23 | D12: =Assumptions!$F$35+Assumptions!$F$28 -> 0.23 | E12: =Assumptions!$F$35+Assumptions!$F$28 -> 0.23
A13: Surplus (+) / shortfall (-) heifers per cow | B13: =B9-B12 -> 0.138 | C13: =C9-C12 -> 0.4324 | D13: =D9-D12 -> -0.23 | E13: =E9-E12 -> -0.03128
A15: Income: bull calves | B15: =B10*Assumptions!$F$55*Assumptions!$F$25 -> 14.72 | C15: =C10*Assumptions!$F$55*Assumptions!$F$25 -> 2.944 | D15: =D10*Assumptions!$F$55*Assumptions!$F$25 -> 0 | E15: =E10*Assumptions!$F$55*Assumptions!$F$25 -> 0.8832
A16: Income: beef-cross calves | B16: =B11*Assumptions!$F$56*Assumptions!$F$25 -> 0 | C16: =C11*Assumptions!$F$56*Assumptions!$F$25 -> 0 | D16: =D11*Assumptions!$F$56*Assumptions!$F$25 -> 117.76 | E16: =E11*Assumptions!$F$56*Assumptions!$F$25 -> 82.432
A17: Income: net heifers (surplus sold, shortfall bought) | B17: =B13*Assumptions!$F$57*Assumptions!$F$25 -> 96.6 | C17: =C13*Assumptions!$F$57*Assumptions!$F$25 -> 302.68 | D17: =D13*Assumptions!$F$57*Assumptions!$F$25 -> -161 | E17: =E13*Assumptions!$F$57*Assumptions!$F$25 -> -21.896
A18: Cost: rear heifers to 2 years (feed + vet) | B18: =-B9*2*(Assumptions!$F$77*Assumptions!$F$24+Assumptions!$F$82) -> -126.592 | C18: =-C9*2*(Assumptions!$F$77*Assumptions!$F$24+Assumptions!$F$82) -> -227.8656 | D18: =-D9*2*(Assumptions!$F$77*Assumptions!$F$24+Assumptions!$F$82) -> 0 | E18: =-E9*2*(Assumptions!$F$77*Assumptions!$F$24+Assumptions!$F$82) -> -68.35968
A19: Cost: rear cross-bred calves to sale (milk, feed, vet) | B19: =-B11*Assumptions!$F$72 -> 0 | C19: =-C11*Assumptions!$F$72 -> 0 | D19: =-D11*Assumptions!$F$72 -> -29.44 | E19: =-E11*Assumptions!$F$72 -> -20.608
A20: Cost: sexed semen premium | B20: =-B7*Assumptions!$F$84 -> 0 | C20: =-C7*Assumptions!$F$84 -> -25 | D20: =-D7*Assumptions!$F$84 -> 0 | E20: =-E7*Assumptions!$F$84 -> -7.5
A21: NET CALF CONTRIBUTION per cow per year | B21: =SUM(B15:B20) -> -15.272 | C21: =SUM(C15:C20) -> 52.7584 | D21: =SUM(D15:D20) -> -72.68 | E21: =SUM(E15:E20) -> -35.04848
A23: B. DAIRY COW: total contribution (per cow, Year 1)
A24: Milk per cow per year (litres) | B24: =Assumptions!$F$50*Assumptions!$F$23*Assumptions!$F$49 -> 2550 | C24: =Assumptions!$F$50*Assumptions!$F$23*Assumptions!$F$49 -> 2550 | D24: =Assumptions!$F$50*Assumptions!$F$23*Assumptions!$F$49 -> 2550 | E24: =Assumptions!$F$50*Assumptions!$F$23*Assumptions!$F$49 -> 2550
A25: Milk income (net of processing cost) | B25: =B24*(Assumptions!$F$22*(1-Assumptions!$F$51)+Assumptions!$F$22*Assumptions!$F$52*Assumptions!$F$51-Assumptions!$F$53*Assumptions!$F$51) -> 1632 | C25: =C24*(Assumptions!$F$22*(1-Assumptions!$F$51)+Assumptions!$F$22*Assumptions!$F$52*Assumptions!$F$51-Assumptions!$F$53*Assumptions!$F$51) -> 1632 | D25: =D24*(Assumptions!$F$22*(1-Assumptions!$F$51)+Assumptions!$F$22*Assumptions!$F$52*Assumptions!$F$51-Assumptions!$F$53*Assumptions!$F$51) -> 1632 | E25: =E24*(Assumptions!$F$22*(1-Assumptions!$F$51)+Assumptions!$F$22*Assumptions!$F$52*Assumptions!$F$51-Assumptions!$F$53*Assumptions!$F$51) -> 1632
A26: Cull cow income (cull rate x weight x price) | B26: =Assumptions!$F$35*Assumptions!$F$63*Assumptions!$F$65*Assumptions!$F$25 -> 134.4 | C26: =Assumptions!$F$35*Assumptions!$F$63*Assumptions!$F$65*Assumptions!$F$25 -> 134.4 | D26: =Assumptions!$F$35*Assumptions!$F$63*Assumptions!$F$65*Assumptions!$F$25 -> 134.4 | E26: =Assumptions!$F$35*Assumptions!$F$63*Assumptions!$F$65*Assumptions!$F$25 -> 134.4
A27: Net calf contribution (from above) | B27: =B21 -> -15.272 | C27: =C21 -> 52.7584 | D27: =D21 -> -72.68 | E27: =E21 -> -35.04848
A28: Feed | B28: =-Assumptions!$F$76*Assumptions!$F$24 -> -480 | C28: =-Assumptions!$F$76*Assumptions!$F$24 -> -480 | D28: =-Assumptions!$F$76*Assumptions!$F$24 -> -480 | E28: =-Assumptions!$F$76*Assumptions!$F$24 -> -480
A29: Vet, AI, utilities | B29: =-(Assumptions!$F$82+Assumptions!$F$83+Assumptions!$F$89) -> -75 | C29: =-(Assumptions!$F$82+Assumptions!$F$83+Assumptions!$F$89) -> -75 | D29: =-(Assumptions!$F$82+Assumptions!$F$83+Assumptions!$F$89) -> -75 | E29: =-(Assumptions!$F$82+Assumptions!$F$83+Assumptions!$F$89) -> -75
A30: Labour (variable: wage / cows per worker) | B30: =-Assumptions!$F$86/Assumptions!$F$87 -> -96 | C30: =-Assumptions!$F$86/Assumptions!$F$87 -> -96 | D30: =-Assumptions!$F$86/Assumptions!$F$87 -> -96 | E30: =-Assumptions!$F$86/Assumptions!$F$87 -> -96
A31: CONTRIBUTION per dairy cow (before fixed farm costs) | B31: =SUM(B25:B30) -> 1100.128 | C31: =SUM(C25:C30) -> 1168.1584 | D31: =SUM(D25:D30) -> 1042.72 | E31: =SUM(E25:E30) -> 1080.3515
A32: Calves as % of total cow income | B32: =IF((B25+B26+B15+B16+B17)=0,0,(B15+B16+B17)/(B25+B26+B15+B16+B17)) -> 0.059284664 | C32: =IF((C25+C26+C15+C16+C17)=0,0,(C15+C16+C17)/(C25+C26+C15+C16+C17)) -> 0.14750022 | D32: =IF((D25+D26+D15+D16+D17)=0,0,(D15+D16+D17)/(D25+D26+D15+D16+D17)) -> -0.025093433 | E32: =IF((E25+E26+E15+E16+E17)=0,0,(E15+E16+E17)/(E25+E26+E15+E16+E17)) -> 0.033602448
A34: C. HOW MANY DAIRY COWS TO COVER THE FIXED COSTS? (scale effect)
A35: Fixed cash costs of the farm (Year 1: manager, fuel, insurance, R&M, admin, land, pasture) | B35: =Opex!$D$25+Opex!$D$32+Opex!$D$33+Opex!$D$34+Opex!$D$36+Opex!$D$40+Opex!$D$41+Opex!$D$13 -> 26896.84 | C35: =Opex!$D$25+Opex!$D$32+Opex!$D$33+Opex!$D$34+Opex!$D$36+Opex!$D$40+Opex!$D$41+Opex!$D$13 -> 26896.84 | D35: =Opex!$D$25+Opex!$D$32+Opex!$D$33+Opex!$D$34+Opex!$D$36+Opex!$D$40+Opex!$D$41+Opex!$D$13 -> 26896.84 | E35: =Opex!$D$25+Opex!$D$32+Opex!$D$33+Opex!$D$34+Opex!$D$36+Opex!$D$40+Opex!$D$41+Opex!$D$13 -> 26896.84
A36: Fixed cash costs + depreciation + loan interest (Year 1) | B36: =Opex!$D$25+Opex!$D$32+Opex!$D$33+Opex!$D$34+Opex!$D$36+Opex!$D$40+Opex!$D$41+Opex!$D$13+Financials!$D$11+Financials!$D$36 -> 54253.872 | C36: =Opex!$D$25+Opex!$D$32+Opex!$D$33+Opex!$D$34+Opex!$D$36+Opex!$D$40+Opex!$D$41+Opex!$D$13+Financials!$D$11+Financials!$D$36 -> 54253.872 | D36: =Opex!$D$25+Opex!$D$32+Opex!$D$33+Opex!$D$34+Opex!$D$36+Opex!$D$40+Opex!$D$41+Opex!$D$13+Financials!$D$11+Financials!$D$36 -> 54253.872 | E36: =Opex!$D$25+Opex!$D$32+Opex!$D$33+Opex!$D$34+Opex!$D$36+Opex!$D$40+Opex!$D$41+Opex!$D$13+Financials!$D$11+Financials!$D$36 -> 54253.872
A37: Dairy cows needed to cover fixed CASH costs | B37: =IF(B31<=0,"never",B35/B31) -> 24.448828 | C37: =IF(C31<=0,"never",C35/C31) -> 23.024994 | D37: =IF(D31<=0,"never",D35/D31) -> 25.794883 | E37: =IF(E31<=0,"never",E35/E31) -> 24.896378
A38: Dairy cows needed to cover FULL costs (incl. depreciation & interest) | B38: =IF(B31<=0,"never",B36/B31) -> 49.315963 | C38: =IF(C31<=0,"never",C36/C31) -> 46.443934 | D38: =IF(D31<=0,"never",D36/D31) -> 52.031103 | E38: =IF(E31<=0,"never",E36/E31) -> 50.218721
A39: Reading: if these numbers are far above your herd size, the farm is too small for its fixed costs. Calves help, but milk yield, price and herd size matter more.
A41: D. BEEF COW: weaner strategy (per cow per year)
A42: Per beef cow per year | B42: A. Sell steers as weaners | C42: B. Finish half the steers | D42: C. Breeding-stock heifers (50%) | E42: D. Finish 50% + breeding stock
A43: Share of steers finished | B43: 0 | C43: 0.5 | D43: 0 | E43: 0.5
A44: Share of surplus heifers sold as breeding stock | B44: 0 | C44: 0 | D44: 0.5 | E44: 0.5
A45: Calves surviving per cow | B45: =Assumptions!$F$27*(1-Assumptions!$F$29) -> 0.69 | C45: =Assumptions!$F$27*(1-Assumptions!$F$29) -> 0.69 | D45: =Assumptions!$F$27*(1-Assumptions!$F$29) -> 0.69 | E45: =Assumptions!$F$27*(1-Assumptions!$F$29) -> 0.69
A46: Steers per cow | B46: =B45*(1-Assumptions!$F$37) -> 0.345 | C46: =C45*(1-Assumptions!$F$37) -> 0.345 | D46: =D45*(1-Assumptions!$F$37) -> 0.345 | E46: =E45*(1-Assumptions!$F$37) -> 0.345
A47: Heifers per cow | B47: =B45*Assumptions!$F$37 -> 0.345 | C47: =C45*Assumptions!$F$37 -> 0.345 | D47: =D45*Assumptions!$F$37 -> 0.345 | E47: =E45*Assumptions!$F$37 -> 0.345
A48: Replacement heifers needed per cow | B48: =Assumptions!$F$36+Assumptions!$F$28 -> 0.18 | C48: =Assumptions!$F$36+Assumptions!$F$28 -> 0.18 | D48: =Assumptions!$F$36+Assumptions!$F$28 -> 0.18 | E48: =Assumptions!$F$36+Assumptions!$F$28 -> 0.18
A49: Income: weaner steers | B49: =B46*(1-B43)*Assumptions!$F$59*Assumptions!$F$60*Assumptions!$F$25 -> 151.8 | C49: =C46*(1-C43)*Assumptions!$F$59*Assumptions!$F$60*Assumptions!$F$25 -> 75.9 | D49: =D46*(1-D43)*Assumptions!$F$59*Assumptions!$F$60*Assumptions!$F$25 -> 151.8 | E49: =E46*(1-E43)*Assumptions!$F$59*Assumptions!$F$60*Assumptions!$F$25 -> 75.9
A50: Income: finished steers less finishing feed | B50: =B46*B43*(Assumptions!$F$61*Assumptions!$F$62*Assumptions!$F$25-Assumptions!$F$80*Assumptions!$F$24) -> 0 | C50: =C46*C43*(Assumptions!$F$61*Assumptions!$F$62*Assumptions!$F$25-Assumptions!$F$80*Assumptions!$F$24) -> 81.42 | D50: =D46*D43*(Assumptions!$F$61*Assumptions!$F$62*Assumptions!$F$25-Assumptions!$F$80*Assumptions!$F$24) -> 0 | E50: =E46*E43*(Assumptions!$F$61*Assumptions!$F$62*Assumptions!$F$25-Assumptions!$F$80*Assumptions!$F$24) -> 81.42
A51: Income: net heifers (incl. breeding premium) | B51: =(B47-B48)*Assumptions!$F$58*Assumptions!$F$25*(1+B44*(Assumptions!$F$44-1)) -> 99 | C51: =(C47-C48)*Assumptions!$F$58*Assumptions!$F$25*(1+C44*(Assumptions!$F$44-1)) -> 99 | D51: =(D47-D48)*Assumptions!$F$58*Assumptions!$F$25*(1+D44*(Assumptions!$F$44-1)) -> 128.7 | E51: =(E47-E48)*Assumptions!$F$58*Assumptions!$F$25*(1+E44*(Assumptions!$F$44-1)) -> 128.7
A52: Income: cull cows | B52: =Assumptions!$F$36*Assumptions!$F$64*Assumptions!$F$65*Assumptions!$F$25 -> 108 | C52: =Assumptions!$F$36*Assumptions!$F$64*Assumptions!$F$65*Assumptions!$F$25 -> 108 | D52: =Assumptions!$F$36*Assumptions!$F$64*Assumptions!$F$65*Assumptions!$F$25 -> 108 | E52: =Assumptions!$F$36*Assumptions!$F$64*Assumptions!$F$65*Assumptions!$F$25 -> 108
A53: Cost: feed (cow + heifers reared 2 yrs) | B53: =-(Assumptions!$F$78+B47*2*Assumptions!$F$79)*Assumptions!$F$24 -> -182.1 | C53: =-(Assumptions!$F$78+C47*2*Assumptions!$F$79)*Assumptions!$F$24 -> -182.1 | D53: =-(Assumptions!$F$78+D47*2*Assumptions!$F$79)*Assumptions!$F$24 -> -182.1 | E53: =-(Assumptions!$F$78+E47*2*Assumptions!$F$79)*Assumptions!$F$24 -> -182.1
A54: Cost: vet, bull cost per cow | B54: =-(Assumptions!$F$82+Assumptions!$F$73/Assumptions!$F$74/Assumptions!$F$47) -> -31.6 | C54: =-(Assumptions!$F$82+Assumptions!$F$73/Assumptions!$F$74/Assumptions!$F$47) -> -31.6 | D54: =-(Assumptions!$F$82+Assumptions!$F$73/Assumptions!$F$74/Assumptions!$F$47) -> -31.6 | E54: =-(Assumptions!$F$82+Assumptions!$F$73/Assumptions!$F$74/Assumptions!$F$47) -> -31.6
A55: Cost: labour (variable) | B55: =-Assumptions!$F$86/Assumptions!$F$88 -> -30 | C55: =-Assumptions!$F$86/Assumptions!$F$88 -> -30 | D55: =-Assumptions!$F$86/Assumptions!$F$88 -> -30 | E55: =-Assumptions!$F$86/Assumptions!$F$88 -> -30
A56: CONTRIBUTION per beef cow (before fixed farm costs) | B56: =SUM(B49:B55) -> 115.1 | C56: =SUM(C49:C55) -> 120.62 | D56: =SUM(D49:D55) -> 144.8 | E56: =SUM(E49:E55) -> 150.32
A57: Beef cows needed to cover fixed cash costs (Year-1 fixed list above) | B57: =IF(B56<=0,"never",B35/B56) -> 233.68236 | C57: =IF(C56<=0,"never",C35/C56) -> 222.98823 | D57: =IF(D56<=0,"never",D35/D56) -> 185.75166 | E57: =IF(E56<=0,"never",E35/E56) -> 178.93055

Sheet Monthly_Y1
A1: MONTHLY CASH FLOW - Year 1
A2: Checks that the working capital reserve covers the first-year cash trough. Milk starts in the month set on Assumptions; other sales start later.
A4: Line item | B4: Year 1 total | C4: Start | D4: 1 | E4: 2 | F4: 3 | G4: 4 | H4: 5 | I4: 6 | J4: 7 | K4: 8 | L4: 9 | M4: 10 | N4: 11 | O4: 12
A6: Milk-selling month flag | D6: =IF(D$4>=Assumptions!$F$106,1,0) -> 0 | E6: =IF(E$4>=Assumptions!$F$106,1,0) -> 1 | F6: =IF(F$4>=Assumptions!$F$106,1,0) -> 1 | G6: =IF(G$4>=Assumptions!$F$106,1,0) -> 1 | H6: =IF(H$4>=Assumptions!$F$106,1,0) -> 1 | I6: =IF(I$4>=Assumptions!$F$106,1,0) -> 1 | J6: =IF(J$4>=Assumptions!$F$106,1,0) -> 1 | K6: =IF(K$4>=Assumptions!$F$106,1,0) -> 1 | ... O6: =IF(O$4>=Assumptions!$F$106,1,0) -> 1
A7: Other-sales month flag | D7: =IF(D$4>=Assumptions!$F$107,1,0) -> 0 | E7: =IF(E$4>=Assumptions!$F$107,1,0) -> 0 | F7: =IF(F$4>=Assumptions!$F$107,1,0) -> 0 | G7: =IF(G$4>=Assumptions!$F$107,1,0) -> 1 | H7: =IF(H$4>=Assumptions!$F$107,1,0) -> 1 | I7: =IF(I$4>=Assumptions!$F$107,1,0) -> 1 | J7: =IF(J$4>=Assumptions!$F$107,1,0) -> 1 | K7: =IF(K$4>=Assumptions!$F$107,1,0) -> 1 | ... O7: =IF(O$4>=Assumptions!$F$107,1,0) -> 1
A8: Milk revenue (raw + processed) | B8: =SUM(D8:O8) -> 67320 | D8: =IF(SUM($D$6:$O$6)=0,0,Revenue!D31*D6/SUM($D$6:$O$6)) -> 0 | E8: =IF(SUM($D$6:$O$6)=0,0,Revenue!D31*E6/SUM($D$6:$O$6)) -> 6120 | F8: =IF(SUM($D$6:$O$6)=0,0,Revenue!D31*F6/SUM($D$6:$O$6)) -> 6120 | G8: =IF(SUM($D$6:$O$6)=0,0,Revenue!D31*G6/SUM($D$6:$O$6)) -> 6120 | H8: =IF(SUM($D$6:$O$6)=0,0,Revenue!D31*H6/SUM($D$6:$O$6)) -> 6120 | I8: =IF(SUM($D$6:$O$6)=0,0,Revenue!D31*I6/SUM($D$6:$O$6)) -> 6120 | J8: =IF(SUM($D$6:$O$6)=0,0,Revenue!D31*J6/SUM($D$6:$O$6)) -> 6120 | K8: =IF(SUM($D$6:$O$6)=0,0,Revenue!D31*K6/SUM($D$6:$O$6)) -> 6120 | L8: =IF(SUM($D$6:$O$6)=0,0,Revenue!D31*L6/SUM($D$6:$O$6)) -> 6120 | M8: =IF(SUM($D$6:$O$6)=0,0,Revenue!D31*M6/SUM($D$6:$O$6)) -> 6120 | N8: =IF(SUM($D$6:$O$6)=0,0,Revenue!D31*N6/SUM($D$6:$O$6)) -> 6120 | O8: =IF(SUM($D$6:$O$6)=0,0,Revenue!D31*O6/SUM($D$6:$O$6)) -> 6120
A9: Animal & other revenue | B9: =SUM(D9:O9) -> 15868.8 | D9: =IF(SUM($D$7:$O$7)=0,0,(Revenue!D28-Revenue!D31)*D7/SUM($D$7:$O$7)) -> 0 | E9: =IF(SUM($D$7:$O$7)=0,0,(Revenue!D28-Revenue!D31)*E7/SUM($D$7:$O$7)) -> 0 | F9: =IF(SUM($D$7:$O$7)=0,0,(Revenue!D28-Revenue!D31)*F7/SUM($D$7:$O$7)) -> 0 | G9: =IF(SUM($D$7:$O$7)=0,0,(Revenue!D28-Revenue!D31)*G7/SUM($D$7:$O$7)) -> 1763.2 | H9: =IF(SUM($D$7:$O$7)=0,0,(Revenue!D28-Revenue!D31)*H7/SUM($D$7:$O$7)) -> 1763.2 | I9: =IF(SUM($D$7:$O$7)=0,0,(Revenue!D28-Revenue!D31)*I7/SUM($D$7:$O$7)) -> 1763.2 | J9: =IF(SUM($D$7:$O$7)=0,0,(Revenue!D28-Revenue!D31)*J7/SUM($D$7:$O$7)) -> 1763.2 | K9: =IF(SUM($D$7:$O$7)=0,0,(Revenue!D28-Revenue!D31)*K7/SUM($D$7:$O$7)) -> 1763.2 | L9: =IF(SUM($D$7:$O$7)=0,0,(Revenue!D28-Revenue!D31)*L7/SUM($D$7:$O$7)) -> 1763.2 | M9: =IF(SUM($D$7:$O$7)=0,0,(Revenue!D28-Revenue!D31)*M7/SUM($D$7:$O$7)) -> 1763.2 | N9: =IF(SUM($D$7:$O$7)=0,0,(Revenue!D28-Revenue!D31)*N7/SUM($D$7:$O$7)) -> 1763.2 | O9: =IF(SUM($D$7:$O$7)=0,0,(Revenue!D28-Revenue!D31)*O7/SUM($D$7:$O$7)) -> 1763.2
A10: Total cash in | B10: =SUM(D10:O10) -> 83188.8 | D10: =D8+D9 -> 0 | E10: =E8+E9 -> 6120 | F10: =F8+F9 -> 6120 | G10: =G8+G9 -> 7883.2 | H10: =H8+H9 -> 7883.2 | I10: =I8+I9 -> 7883.2 | J10: =J8+J9 -> 7883.2 | K10: =K8+K9 -> 7883.2 | ... O10: =O8+O9 -> 7883.2
A11: Operating costs | B11: =SUM(D11:O11) -> -84705.239 | D11: =-Opex!D46/12 -> -7058.7699 | E11: =-Opex!D46/12 -> -7058.7699 | F11: =-Opex!D46/12 -> -7058.7699 | G11: =-Opex!D46/12 -> -7058.7699 | H11: =-Opex!D46/12 -> -7058.7699 | I11: =-Opex!D46/12 -> -7058.7699 | J11: =-Opex!D46/12 -> -7058.7699 | K11: =-Opex!D46/12 -> -7058.7699 | L11: =-Opex!D46/12 -> -7058.7699 | M11: =-Opex!D46/12 -> -7058.7699 | N11: =-Opex!D46/12 -> -7058.7699 | O11: =-Opex!D46/12 -> -7058.7699
A12: Interest | B12: =SUM(D12:O12) -> -11533.632 | D12: =-Financials!D36/12 -> -961.136 | E12: =-Financials!D36/12 -> -961.136 | F12: =-Financials!D36/12 -> -961.136 | G12: =-Financials!D36/12 -> -961.136 | H12: =-Financials!D36/12 -> -961.136 | I12: =-Financials!D36/12 -> -961.136 | J12: =-Financials!D36/12 -> -961.136 | K12: =-Financials!D36/12 -> -961.136 | L12: =-Financials!D36/12 -> -961.136 | M12: =-Financials!D36/12 -> -961.136 | N12: =-Financials!D36/12 -> -961.136 | O12: =-Financials!D36/12 -> -961.136
A13: Principal | B13: =SUM(D13:O13) -> 0 | D13: =-Financials!D37/12 -> 0 | E13: =-Financials!D37/12 -> 0 | F13: =-Financials!D37/12 -> 0 | G13: =-Financials!D37/12 -> 0 | H13: =-Financials!D37/12 -> 0 | I13: =-Financials!D37/12 -> 0 | J13: =-Financials!D37/12 -> 0 | K13: =-Financials!D37/12 -> 0 | L13: =-Financials!D37/12 -> 0 | M13: =-Financials!D37/12 -> 0 | N13: =-Financials!D37/12 -> 0 | O13: =-Financials!D37/12 -> 0
A14: Sustaining capex | B14: =SUM(D14:O14) -> -2359.5 | D14: =Financials!D50/12 -> -196.625 | E14: =Financials!D50/12 -> -196.625 | F14: =Financials!D50/12 -> -196.625 | G14: =Financials!D50/12 -> -196.625 | H14: =Financials!D50/12 -> -196.625 | I14: =Financials!D50/12 -> -196.625 | J14: =Financials!D50/12 -> -196.625 | K14: =Financials!D50/12 -> -196.625 | L14: =Financials!D50/12 -> -196.625 | M14: =Financials!D50/12 -> -196.625 | N14: =Financials!D50/12 -> -196.625 | O14: =Financials!D50/12 -> -196.625
A15: Tax (paid month 12) | B15: =SUM(D15:O15) -> 0 | D15: =IF(D$4=12,Financials!D47,0) -> 0 | E15: =IF(E$4=12,Financials!D47,0) -> 0 | F15: =IF(F$4=12,Financials!D47,0) -> 0 | G15: =IF(G$4=12,Financials!D47,0) -> 0 | H15: =IF(H$4=12,Financials!D47,0) -> 0 | I15: =IF(I$4=12,Financials!D47,0) -> 0 | J15: =IF(J$4=12,Financials!D47,0) -> 0 | K15: =IF(K$4=12,Financials!D47,0) -> 0 | L15: =IF(L$4=12,Financials!D47,0) -> 0 | M15: =IF(M$4=12,Financials!D47,0) -> 0 | N15: =IF(N$4=12,Financials!D47,0) -> 0 | O15: =IF(O$4=12,Financials!D47,0) -> 0
A16: Total cash out | B16: =SUM(D16:O16) -> -98598.371 | D16: =SUM(D11:D15) -> -8216.5309 | E16: =SUM(E11:E15) -> -8216.5309 | F16: =SUM(F11:F15) -> -8216.5309 | G16: =SUM(G11:G15) -> -8216.5309 | H16: =SUM(H11:H15) -> -8216.5309 | I16: =SUM(I11:I15) -> -8216.5309 | J16: =SUM(J11:J15) -> -8216.5309 | K16: =SUM(K11:K15) -> -8216.5309 | ... O16: =SUM(O11:O15) -> -8216.5309
A17: Net cash flow | B17: =SUM(D17:O17) -> -15409.571 | D17: =D10+D16 -> -8216.5309 | E17: =E10+E16 -> -2096.5309 | F17: =F10+F16 -> -2096.5309 | G17: =G10+G16 -> -333.3309 | H17: =H10+H16 -> -333.3309 | I17: =I10+I16 -> -333.3309 | J17: =J10+J16 -> -333.3309 | K17: =K10+K16 -> -333.3309 | ... O17: =O10+O16 -> -333.3309
A18: Closing cash balance | C18: =-Financials!C51 -> 21176.31 | D18: =C18+D17 -> 12959.779 | E18: =D18+E17 -> 10863.248 | F18: =E18+F17 -> 8766.717 | G18: =F18+G17 -> 8433.3861 | H18: =G18+H17 -> 8100.0552 | I18: =H18+I17 -> 7766.7243 | J18: =I18+J17 -> 7433.3934 | K18: =J18+K17 -> 7100.0625 | ... O18: =N18+O17 -> 5766.7389
A20: Lowest month-end cash balance | B20: =MIN(D18:O18) -> 5766.7389
A21: Extra reserve needed (0 = reserve is enough) | B21: =MAX(0,-B20) -> 0
A22: Result | B22: =IF(B20>=0,"OK - reserve covers Year 1","SHORTFALL - raise reserve") -> OK - reserve covers Year 1

Sheet Scenarios
A1: SCENARIOS & STRATEGIES - static comparison snapshot
A2: STATIC VALUES generated by re-running this model with the changes listed. They do NOT update. To refresh: change inputs on Assumptions and read the live figures on Returns.
A4: Strategy | B4: What changes vs the default case | C4: Total investment | D4: Investment per breeding cow | E4: Year 5 revenue | F4: Year 5 EBITDA | G4: EBITDA margin | H4: Project IRR (incl. TV) | I4: Project IRR (cash only) | J4: NPV @ hurdle | K4: Payback (yrs) | L4: Break-even milk price (cash) | M4: Land check
A5: 1. Mixed farm - as designed (Base) | B5: Dairy 40 + beef 30, pure dairy calves, leased land | C5: 261460.31 | D5: 3735.1473 | E5: 101073.84 | F5: 15853.267 | G5: 0.15684837 | H5: -0.019414222 | I5: -0.10841321 | J5: -178916.67 | K5: > 10 yrs | L5: 0.44656402 | M5: OK
A6: 2. Mixed farm - Downside | B6: Lower prices, higher feed cost, lower calving/yield, higher mortality | C6: 262016.94 | D6: 3743.0991 | E6: 67179.82 | F6: -22038.812 | G6: -0.32805702 | H6: -0.27069808 | I6: n/a | J6: -385654.63 | K6: > 10 yrs | L6: 0.73094449 | M6: OK
A7: 3. Mixed farm - Upside | B7: Higher prices, cheaper feed, better calving/yield | C7: 262102.64 | D7: 3744.3234 | E7: 143553.88 | F7: 58557.669 | G7: 0.40791423 | H7: 0.12336642 | I7: 0.088992536 | J7: 4812.4679 | K7: 6.8403071 | L7: 0.2477076 | M7: OK
A8: 4. Dairy only (40 cows) | B8: Beef enterprise switched off | C8: 226445.92 | D8: 5661.1481 | E8: 88114.734 | F8: 13460.165 | G8: 0.15275726 | H8: -0.026500889 | I8: -0.10750001 | J8: -154766.22 | K8: > 10 yrs | L8: 0.46972568 | M8: OK
A9: 5. Beef breeding only (70 cows) | B9: Dairy off; 70 beef cows | C9: 199020.24 | D9: 2843.1462 | E9: 30372.981 | F9: -23118.975 | G9: -0.76116913 | H9: n/a | I9: n/a | J9: -334258.74 | K9: > 10 yrs | L9: n/a | M9: OK
A10: 6. Mixed + breeding upgrade | B10: 50% of dairy cows to beef semen, 40% sexed on the rest, 50% of surplus heifers as breeding stock, half of steers finished, 30 outside cows served | C10: 261704.03 | D10: 3738.6289 | E10: 103556.46 | F10: 18318.023 | G10: 0.17688923 | H10: -0.0081584236 | I10: -0.089590799 | J10: -164285.88 | K10: > 10 yrs | L10: 0.42270887 | M10: OK
A11: 7. Mixed + lean capex (0.6x) | B11: Basic sheds and used equipment: infrastructure cost x 0.6 | C11: 192832.84 | D11: 2754.7548 | E11: 101073.84 | F11: 18885.416 | G11: 0.18684771 | H11: 0.022803185 | I11: -0.052240782 | J11: -99751.538 | K11: > 10 yrs | L11: 0.41721734 | M11: OK
A12: 8. Dairy 100 cows, lean + breeding | B12: 100 dairy cows, capex x 0.7, 50% beef-cross, 40% sexed, 50% breeding heifers, 30% of milk processed | C12: 291421.72 | D12: 2914.2172 | E12: 250313.79 | F12: 102924.44 | G12: 0.41118168 | H12: 0.22752106 | I12: 0.20671489 | J12: 179259.99 | K12: 4.3884267 | L12: 0.087691678 | M12: WARNING: herd exceeds land in some year
A13: 9. Beef 90 cows, lean + breeding | B13: 90 beef cows, capex x 0.7, half of steers finished, 50% breeding heifers, 30 outside cows served | C13: 181963.51 | D13: 2021.8168 | E13: 48035.647 | F13: -15542.266 | G13: -0.32355692 | H13: -0.19371718 | I13: n/a | J13: -278109.28 | K13: > 10 yrs | L13: n/a | M13: WARNING: herd exceeds land in some year
A15: All prices are generic placeholders in USD. Use this table to compare the SHAPE of each strategy, not as a forecast. Re-run with local prices before deciding.
