Workbook

Sheet Assumptions
A1: Ghana National Gas Company (GNGC) — Integrated Control Room Budget: Assumptions & Controls
A2: Edit the yellow cells below (Subtotal and VAT Rate). Every cost-centre sheet recalculates automatically from these values.
A4: Global Assumption | B4: Value | C4: Notes
A5: Blended VAT / NHIL / GETFund rate (indicative) | B5: 0.15 | C5: Used only to split each tax-inclusive subtotal into Net Cost + Tax on the cost-centre sheets. Adjust to GNGC's actual blended rate if different.
A6: Target Grand Total (tax-inclusive, GH¢) | B6: 16000000 | C6: Reference figure only — for information. The actual project total is the sum of the seven Subtotal cells below.
A8: Cost Centre | B8: Subtotal — GH¢ (tax-inclusive) | C8: % of Total | D8: Linked Sheet
A9: 1. Control Room Space Re-Engineering — Fixtures & Fittings | B9: 3200000 | C9: =B9/$B$16 -> 0.2 | D9: 1. Control Room Space
A10: 2. Procurement of UAVs (Long-Range & Short-Range) | B10: 3600000 | C10: =B10/$B$16 -> 0.225 | D10: 2. UAV Procurement
A11: 3. Software Development and Deployment | B11: 4000000 | C11: =B11/$B$16 -> 0.25 | D11: 3. Software Dev & Deploy
A12: 4. Procurement of Vehicles (Pick-Up) | B12: 1200000 | C12: =B12/$B$16 -> 0.075 | D12: 4. Vehicle Procurement
A13: 5. Training and Capacity Building | B13: 1200000 | C13: =B13/$B$16 -> 0.075 | D13: 5. Training & Capacity
A14: 6. Project Management | B14: 1600000 | C14: =B14/$B$16 -> 0.1 | D14: 6. Project Management
A15: 7. Contingency | B15: 1200000 | C15: =B15/$B$16 -> 0.075 | D15: 7. Contingency
A16: GRAND TOTAL — Integrated Control Room Budget | B16: =SUM(B9:B15) -> 16000000 | C16: =SUM(C9:C15) -> 1
A17: Variance vs Target Grand Total | B17: =B16-B6 -> 0 | C17: Should read GH¢0 when the seven subtotals are set to reconcile with the target total.
A20: Tax Reconciliation (indicative, at blended rate above)
B21: Net Cost (excl. tax) | C21: Tax Element | D21: Gross (tax-inclusive)
A22: Total Project Budget | B22: =B16/(1+$B$5) -> 13913043 | C22: =D22-B22 -> 2086956.5 | D22: =B16 -> 16000000

Sheet Summary
A1: Ghana National Gas Company (GNGC) — Integrated Control Room Budget: Summary
A2: All figures are pulled live from the Assumptions sheet and the seven cost-centre sheets. Tax inclusive, in Ghana Cedis (GH¢).
A4: Cost Centre | B4: Net Cost (GH¢) | C4: Tax (GH¢) | D4: Amount — GH¢ (tax-incl.) | E4: % of Total
A5: 1. Control Room Space Re-Engineering — Fixtures & Fittings | B5: ='1. Control Room Space'!C14 -> 2782608.7 | C5: ='1. Control Room Space'!D14 -> 417391.3 | D5: ='1. Control Room Space'!E14 -> 3200000 | E5: =D5/$D$12 -> 0.2
A6: 2. Procurement of UAVs (Long-Range & Short-Range) | B6: ='2. UAV Procurement'!C14 -> 3130434.8 | C6: ='2. UAV Procurement'!D14 -> 469565.22 | D6: ='2. UAV Procurement'!E14 -> 3600000 | E6: =D6/$D$12 -> 0.225
A7: 3. Software Development and Deployment | B7: ='3. Software Dev & Deploy'!C14 -> 3478260.9 | C7: ='3. Software Dev & Deploy'!D14 -> 521739.13 | D7: ='3. Software Dev & Deploy'!E14 -> 4000000 | E7: =D7/$D$12 -> 0.25
A8: 4. Procurement of Vehicles (Pick-Up) | B8: ='4. Vehicle Procurement'!C11 -> 1043478.3 | C8: ='4. Vehicle Procurement'!D11 -> 156521.74 | D8: ='4. Vehicle Procurement'!E11 -> 1200000 | E8: =D8/$D$12 -> 0.075
A9: 5. Training and Capacity Building | B9: ='5. Training & Capacity'!C13 -> 1043478.3 | C9: ='5. Training & Capacity'!D13 -> 156521.74 | D9: ='5. Training & Capacity'!E13 -> 1200000 | E9: =D9/$D$12 -> 0.075
A10: 6. Project Management | B10: ='6. Project Management'!C12 -> 1391304.3 | C10: ='6. Project Management'!D12 -> 208695.65 | D10: ='6. Project Management'!E12 -> 1600000 | E10: =D10/$D$12 -> 0.1
A11: 7. Contingency | B11: ='7. Contingency'!C10 -> 1043478.3 | C11: ='7. Contingency'!D10 -> 156521.74 | D11: ='7. Contingency'!E10 -> 1200000 | E11: =D11/$D$12 -> 0.075
A12: GRAND TOTAL | B12: =SUM(B5:B11) -> 13913043 | C12: =SUM(C5:C11) -> 2086956.5 | D12: =SUM(D5:D11) -> 16000000
A14: To change any cost centre's total, edit the yellow Subtotal cell on the 'Assumptions' sheet — all figures above and on each cost-centre sheet update automatically.

Sheet 1. Control Room Space
A1: 1. Control Room Space Re-Engineering — Fixtures & Fittings
A2: Line-item weights are fixed (%); amounts scale automatically from the Subtotal set on the Assumptions sheet.
A4: Cost Centre Subtotal (tax-inclusive, from Assumptions) | B4: =Assumptions!$B$9 -> 3200000 | D4: VAT/NHIL/GETFund rate: | E4: =Assumptions!$B$5 -> 0.15
A6: Line Item | B6: Weight (%) | C6: Net Cost (GH¢) | D6: Tax (GH¢) | E6: Amount — GH¢ (tax-incl.) | F6: Notes
A7: Civil works & interior renovation of control room space | B7: 0.3 | C7: =E7/(1+$E$4) -> 834782.61 | D7: =E7-C7 -> 125217.39 | E7: =B7*$B$4 -> 960000
A8: Raised access flooring & fire suppression system | B8: 0.15 | C8: =E8/(1+$E$4) -> 417391.3 | D8: =E8-C8 -> 62608.696 | E8: =B8*$B$4 -> 480000
A9: Video wall, large-format displays & mounting systems | B9: 0.2 | C9: =E9/(1+$E$4) -> 556521.74 | D9: =E9-C9 -> 83478.261 | E9: =B9*$B$4 -> 640000
A10: Ergonomic console furniture & operator workstations | B10: 0.15 | C10: =E10/(1+$E$4) -> 417391.3 | D10: =E10-C10 -> 62608.696 | E10: =B10*$B$4 -> 480000
A11: Electrical rewiring, UPS & backup power system | B11: 0.1 | C11: =E11/(1+$E$4) -> 278260.87 | D11: =E11-C11 -> 41739.13 | E11: =B11*$B$4 -> 320000
A12: HVAC & environmental control upgrade | B12: 0.05 | C12: =E12/(1+$E$4) -> 139130.43 | D12: =E12-C12 -> 20869.565 | E12: =B12*$B$4 -> 160000
A13: Access control, CCTV & physical security fit-out | B13: 0.05 | C13: =E13/(1+$E$4) -> 139130.43 | D13: =E13-C13 -> 20869.565 | E13: =B13*$B$4 -> 160000
A14: SUBTOTAL | B14: =SUM(B7:B13) -> 1 | C14: =SUM(C7:C13) -> 2782608.7 | D14: =SUM(D7:D13) -> 417391.3 | E14: =SUM(E7:E13) -> 3200000
A15: =IF(ROUND(B14,4)=1,"Weights check OK (100%)","WARNING: line-item weights do not sum to 100% — adjust yellow cells") -> Weights check OK (100%)

Sheet 2. UAV Procurement
A1: 2. Procurement of UAVs (Long-Range & Short-Range)
A2: Line-item weights are fixed (%); amounts scale automatically from the Subtotal set on the Assumptions sheet.
A4: Cost Centre Subtotal (tax-inclusive, from Assumptions) | B4: =Assumptions!$B$10 -> 3600000 | D4: VAT/NHIL/GETFund rate: | E4: =Assumptions!$B$5 -> 0.15
A6: Line Item | B6: Weight (%) | C6: Net Cost (GH¢) | D6: Tax (GH¢) | E6: Amount — GH¢ (tax-incl.) | F6: Notes
A7: Long-range fixed-wing UAV units (x2) — WAGP corridor survey | B7: 0.35 | C7: =E7/(1+$E$4) -> 1095652.2 | D7: =E7-C7 -> 164347.83 | E7: =B7*$B$4 -> 1260000
A8: Short-range multirotor UAV units (x4) — site & incident response | B8: 0.2 | C8: =E8/(1+$E$4) -> 626086.96 | D8: =E8-C8 -> 93913.043 | E8: =B8*$B$4 -> 720000
A9: Payload sensors: thermal, methane-sensing & optical cameras | B9: 0.2 | C9: =E9/(1+$E$4) -> 626086.96 | D9: =E9-C9 -> 93913.043 | E9: =B9*$B$4 -> 720000
A10: Ground control stations & data-link equipment | B10: 0.1 | C10: =E10/(1+$E$4) -> 313043.48 | D10: =E10-C10 -> 46956.522 | E10: =B10*$B$4 -> 360000
A11: Spare parts, batteries & maintenance kits | B11: 0.08 | C11: =E11/(1+$E$4) -> 250434.78 | D11: =E11-C11 -> 37565.217 | E11: =B11*$B$4 -> 288000
A12: UAV pilot operator training & certification | B12: 0.04 | C12: =E12/(1+$E$4) -> 125217.39 | D12: =E12-C12 -> 18782.609 | E12: =B12*$B$4 -> 144000
A13: Import duties, clearing & logistics (UAV-specific) | B13: 0.03 | C13: =E13/(1+$E$4) -> 93913.043 | D13: =E13-C13 -> 14086.957 | E13: =B13*$B$4 -> 108000
A14: SUBTOTAL | B14: =SUM(B7:B13) -> 1 | C14: =SUM(C7:C13) -> 3130434.8 | D14: =SUM(D7:D13) -> 469565.22 | E14: =SUM(E7:E13) -> 3600000
A15: =IF(ROUND(B14,4)=1,"Weights check OK (100%)","WARNING: line-item weights do not sum to 100% — adjust yellow cells") -> Weights check OK (100%)

Sheet 3. Software Dev & Deploy
A1: 3. Software Development and Deployment
A2: Line-item weights are fixed (%); amounts scale automatically from the Subtotal set on the Assumptions sheet.
A4: Cost Centre Subtotal (tax-inclusive, from Assumptions) | B4: =Assumptions!$B$11 -> 4000000 | D4: VAT/NHIL/GETFund rate: | E4: =Assumptions!$B$5 -> 0.15
A6: Line Item | B6: Weight (%) | C6: Net Cost (GH¢) | D6: Tax (GH¢) | E6: Amount — GH¢ (tax-incl.) | F6: Notes
A7: GasGuard Fusion platform — core development | B7: 0.35 | C7: =E7/(1+$E$4) -> 1217391.3 | D7: =E7-C7 -> 182608.7 | E7: =B7*$B$4 -> 1400000
A8: SCADA/CPM integration & mass-balance reconciliation module | B8: 0.15 | C8: =E8/(1+$E$4) -> 521739.13 | D8: =E8-C8 -> 78260.87 | E8: =B8*$B$4 -> 600000
A9: AI/ML anomaly-detection model development & training | B9: 0.2 | C9: =E9/(1+$E$4) -> 695652.17 | D9: =E9-C9 -> 104347.83 | E9: =B9*$B$4 -> 800000
A10: Control-room dashboard & field mobile app development | B10: 0.1 | C10: =E10/(1+$E$4) -> 347826.09 | D10: =E10-C10 -> 52173.913 | E10: =B10*$B$4 -> 400000
A11: Cloud/server infrastructure, hosting & licensing (Year 1) | B11: 0.1 | C11: =E11/(1+$E$4) -> 347826.09 | D11: =E11-C11 -> 52173.913 | E11: =B11*$B$4 -> 400000
A12: Cybersecurity hardening & OT/IT network integration | B12: 0.05 | C12: =E12/(1+$E$4) -> 173913.04 | D12: =E12-C12 -> 26086.957 | E12: =B12*$B$4 -> 200000
A13: System testing, QA & deployment | B13: 0.05 | C13: =E13/(1+$E$4) -> 173913.04 | D13: =E13-C13 -> 26086.957 | E13: =B13*$B$4 -> 200000
A14: SUBTOTAL | B14: =SUM(B7:B13) -> 1 | C14: =SUM(C7:C13) -> 3478260.9 | D14: =SUM(D7:D13) -> 521739.13 | E14: =SUM(E7:E13) -> 4000000
A15: =IF(ROUND(B14,4)=1,"Weights check OK (100%)","WARNING: line-item weights do not sum to 100% — adjust yellow cells") -> Weights check OK (100%)

Sheet 4. Vehicle Procurement
A1: 4. Procurement of Vehicles (Pick-Up)
A2: Line-item weights are fixed (%); amounts scale automatically from the Subtotal set on the Assumptions sheet.
A4: Cost Centre Subtotal (tax-inclusive, from Assumptions) | B4: =Assumptions!$B$12 -> 1200000 | D4: VAT/NHIL/GETFund rate: | E4: =Assumptions!$B$5 -> 0.15
A6: Line Item | B6: Weight (%) | C6: Net Cost (GH¢) | D6: Tax (GH¢) | E6: Amount — GH¢ (tax-incl.) | F6: Notes
A7: 4x4 double-cab pick-up trucks (x2 units) | B7: 0.7 | C7: =E7/(1+$E$4) -> 730434.78 | D7: =E7-C7 -> 109565.22 | E7: =B7*$B$4 -> 840000
A8: Vehicle branding, radio/GPS & field-comms fit-out | B8: 0.15 | C8: =E8/(1+$E$4) -> 156521.74 | D8: =E8-C8 -> 23478.261 | E8: =B8*$B$4 -> 180000
A9: Registration, insurance & road-worthiness licensing | B9: 0.1 | C9: =E9/(1+$E$4) -> 104347.83 | D9: =E9-C9 -> 15652.174 | E9: =B9*$B$4 -> 120000
A10: Spare tyres, recovery & tool kits | B10: 0.05 | C10: =E10/(1+$E$4) -> 52173.913 | D10: =E10-C10 -> 7826.087 | E10: =B10*$B$4 -> 60000
A11: SUBTOTAL | B11: =SUM(B7:B10) -> 1 | C11: =SUM(C7:C10) -> 1043478.3 | D11: =SUM(D7:D10) -> 156521.74 | E11: =SUM(E7:E10) -> 1200000
A12: =IF(ROUND(B11,4)=1,"Weights check OK (100%)","WARNING: line-item weights do not sum to 100% — adjust yellow cells") -> Weights check OK (100%)

Sheet 5. Training & Capacity
A1: 5. Training and Capacity Building
A2: Line-item weights are fixed (%); amounts scale automatically from the Subtotal set on the Assumptions sheet.
A4: Cost Centre Subtotal (tax-inclusive, from Assumptions) | B4: =Assumptions!$B$13 -> 1200000 | D4: VAT/NHIL/GETFund rate: | E4: =Assumptions!$B$5 -> 0.15
A6: Line Item | B6: Weight (%) | C6: Net Cost (GH¢) | D6: Tax (GH¢) | E6: Amount — GH¢ (tax-incl.) | F6: Notes
A7: Control room operations & dashboard-use training | B7: 0.3 | C7: =E7/(1+$E$4) -> 313043.48 | D7: =E7-C7 -> 46956.522 | E7: =B7*$B$4 -> 360000
A8: UAV pilot certification programme | B8: 0.2 | C8: =E8/(1+$E$4) -> 208695.65 | D8: =E8-C8 -> 31304.348 | E8: =B8*$B$4 -> 240000
A9: Software/platform administrator training | B9: 0.2 | C9: =E9/(1+$E$4) -> 208695.65 | D9: =E9-C9 -> 31304.348 | E9: =B9*$B$4 -> 240000
A10: Field technician & OT/IT integration training | B10: 0.15 | C10: =E10/(1+$E$4) -> 156521.74 | D10: =E10-C10 -> 23478.261 | E10: =B10*$B$4 -> 180000
A11: Training materials, venue & facilitation costs | B11: 0.1 | C11: =E11/(1+$E$4) -> 104347.83 | D11: =E11-C11 -> 15652.174 | E11: =B11*$B$4 -> 120000
A12: Study tour / knowledge-exchange with peer operator | B12: 0.05 | C12: =E12/(1+$E$4) -> 52173.913 | D12: =E12-C12 -> 7826.087 | E12: =B12*$B$4 -> 60000
A13: SUBTOTAL | B13: =SUM(B7:B12) -> 1 | C13: =SUM(C7:C12) -> 1043478.3 | D13: =SUM(D7:D12) -> 156521.74 | E13: =SUM(E7:E12) -> 1200000
A14: =IF(ROUND(B13,4)=1,"Weights check OK (100%)","WARNING: line-item weights do not sum to 100% — adjust yellow cells") -> Weights check OK (100%)

Sheet 6. Project Management
A1: 6. Project Management
A2: Line-item weights are fixed (%); amounts scale automatically from the Subtotal set on the Assumptions sheet.
A4: Cost Centre Subtotal (tax-inclusive, from Assumptions) | B4: =Assumptions!$B$14 -> 1600000 | D4: VAT/NHIL/GETFund rate: | E4: =Assumptions!$B$5 -> 0.15
A6: Line Item | B6: Weight (%) | C6: Net Cost (GH¢) | D6: Tax (GH¢) | E6: Amount — GH¢ (tax-incl.) | F6: Notes
A7: Project manager & core project team fees (12 months) | B7: 0.4 | C7: =E7/(1+$E$4) -> 556521.74 | D7: =E7-C7 -> 83478.261 | E7: =B7*$B$4 -> 640000
A8: Site supervision & QA/QC oversight | B8: 0.2 | C8: =E8/(1+$E$4) -> 278260.87 | D8: =E8-C8 -> 41739.13 | E8: =B8*$B$4 -> 320000
A9: Documentation, reporting & change management | B9: 0.15 | C9: =E9/(1+$E$4) -> 208695.65 | D9: =E9-C9 -> 31304.348 | E9: =B9*$B$4 -> 240000
A10: Stakeholder engagement & NPA/regulatory coordination | B10: 0.15 | C10: =E10/(1+$E$4) -> 208695.65 | D10: =E10-C10 -> 31304.348 | E10: =B10*$B$4 -> 240000
A11: PM software/tools, communications & travel | B11: 0.1 | C11: =E11/(1+$E$4) -> 139130.43 | D11: =E11-C11 -> 20869.565 | E11: =B11*$B$4 -> 160000
A12: SUBTOTAL | B12: =SUM(B7:B11) -> 1 | C12: =SUM(C7:C11) -> 1391304.3 | D12: =SUM(D7:D11) -> 208695.65 | E12: =SUM(E7:E11) -> 1600000
A13: =IF(ROUND(B12,4)=1,"Weights check OK (100%)","WARNING: line-item weights do not sum to 100% — adjust yellow cells") -> Weights check OK (100%)

Sheet 7. Contingency
A1: 7. Contingency
A2: Line-item weights are fixed (%); amounts scale automatically from the Subtotal set on the Assumptions sheet.
A4: Cost Centre Subtotal (tax-inclusive, from Assumptions) | B4: =Assumptions!$B$15 -> 1200000 | D4: VAT/NHIL/GETFund rate: | E4: =Assumptions!$B$5 -> 0.15
A6: Line Item | B6: Weight (%) | C6: Net Cost (GH¢) | D6: Tax (GH¢) | E6: Amount — GH¢ (tax-incl.) | F6: Notes
A7: Price escalation contingency | B7: 0.4 | C7: =E7/(1+$E$4) -> 417391.3 | D7: =E7-C7 -> 62608.696 | E7: =B7*$B$4 -> 480000
A8: Currency / FX fluctuation buffer (USD-denominated hardware) | B8: 0.3 | C8: =E8/(1+$E$4) -> 313043.48 | D8: =E8-C8 -> 46956.522 | E8: =B8*$B$4 -> 360000
A9: Unforeseen scope & technical risk allowance | B9: 0.3 | C9: =E9/(1+$E$4) -> 313043.48 | D9: =E9-C9 -> 46956.522 | E9: =B9*$B$4 -> 360000
A10: SUBTOTAL | B10: =SUM(B7:B9) -> 1 | C10: =SUM(C7:C9) -> 1043478.3 | D10: =SUM(D7:D9) -> 156521.74 | E10: =SUM(E7:E9) -> 1200000
A11: =IF(ROUND(B10,4)=1,"Weights check OK (100%)","WARNING: line-item weights do not sum to 100% — adjust yellow cells") -> Weights check OK (100%)
