Workbook

Sheet Summary
A1: SMART INNOVATIONS GHANA LIMITED
A2: GasGuard Suite — Integrated Pipeline Monitoring, Loss-Prevention & Custody-Integrity Platform
A3: Budget Proposal for Ghana National Gas Company (GNGC) — Prepared by Smart Innovations Ghana Limited, Accra
B5: TOTAL CONTRACT VALUE (TAX INCL.) | D5: TOTAL CONTRACT VALUE (TAX EXCL.) | F5: TOTAL TAX
B6: =Assumptions!B5 -> 16786452 | D6: =Assumptions!B7 -> 14596915 | F6: =Assumptions!B8 -> 2189537.2
B8: EFFECTIVE TAX RATE
B9: =Assumptions!B6 -> 0.15
A10: BUDGET BY SECTION
B11: Budget Section | C11: Subtotal (Tax Excl) | D11: Tax | E11: Subtotal (Tax Incl) | F11: % of Total
B12: 1. Control Room Space Re-Engineering | C12: =Assumptions!C13 -> 1167753.2 | D12: =Assumptions!D13 -> 175162.98 | E12: =Assumptions!E13 -> 1342916.2 | F12: =E12/$B$6 -> 0.08
B13: 2. UAV Procurement (Long- & Short-Range) | C13: =Assumptions!C14 -> 2627444.7 | D13: =Assumptions!D14 -> 394116.7 | E13: =Assumptions!E14 -> 3021561.4 | F13: =E13/$B$6 -> 0.18
B14: 3. Software Development and Deployment | C14: =Assumptions!C15 -> 4379074.4 | D14: =Assumptions!D15 -> 656861.17 | E14: =Assumptions!E15 -> 5035935.6 | F14: =E14/$B$6 -> 0.3
B15: 4. Vehicle Procurement (Pick-Ups) | C15: =Assumptions!C16 -> 1459691.5 | D15: =Assumptions!D16 -> 218953.72 | E15: =Assumptions!E16 -> 1678645.2 | F15: =E15/$B$6 -> 0.1
B16: 5. Training and Capacity Building | C16: =Assumptions!C17 -> 1167753.2 | D16: =Assumptions!D17 -> 175162.98 | E16: =Assumptions!E17 -> 1342916.2 | F16: =E16/$B$6 -> 0.08
B17: 6. Project Management | C17: =Assumptions!C18 -> 2335506.4 | D17: =Assumptions!D18 -> 350325.95 | E17: =Assumptions!E18 -> 2685832.3 | F17: =E17/$B$6 -> 0.16
B18: 7. Contingency | C18: =Assumptions!C19 -> 1459691.5 | D18: =Assumptions!D19 -> 218953.72 | E18: =Assumptions!E19 -> 1678645.2 | F18: =E18/$B$6 -> 0.1
B19: TOTAL | C19: =SUM(C12:C18) -> 14596915 | D19: =SUM(D12:D18) -> 2189537.2 | E19: =SUM(E12:E18) -> 16786452 | F19: =SUM(F12:F18) -> 1
B20: Check — Total (Tax Incl.) should equal Master Contract Value | E20: =IF(ROUND(E19-B6,2)=0,"OK ✓","CHECK") -> OK ✓
A41: HOW TO USE THIS WORKBOOK
B42: 1. Go to the Assumptions tab. Set the Total Contract Value (Tax Inclusive) and Tax Rate at the top.
B43: 2. Adjust the Allocation % for each of the 7 budget sections — they must sum to 100%.
B44: 3. Open any numbered section tab to fine-tune the Weight % of individual line items — must sum to 100% within that section.
B45: 4. Every subtotal, tax figure, and the grand total recalculate automatically — no other cells need to be touched.
B46: 5. Green text = linked from Assumptions. Blue text/yellow fill = editable input. Black text = formula.

Sheet Assumptions
A1: GasGuard Suite — Budget Assumptions & Controls
A2: Ghana National Gas Company (GNGC) | All amounts in Ghana Cedis (GH₵). Edit BLUE cells only — changes flow automatically into every section sheet and the Summary.
A4: 1. MASTER CONTRACT VALUE
A5: Total Contract Value (Tax Inclusive) | B5: 16786452
A6: Effective Tax Rate (VAT / NHIL / GETFund, applied on tax-exclusive value) | B6: 0.15
A7: Total Contract Value (Tax Exclusive) | B7: =B5/(1+B6) -> 14596915
A8: Total Tax Amount | B8: =B5-B7 -> 2189537.2
A9: Note: adjust the tax rate here to match GNGC's applicable VAT/levy treatment for this contract.
A11: 2. BUDGET SECTION ALLOCATION (% of Tax-Exclusive Total)
A12: Budget Section | B12: Allocation % | C12: Subtotal (Tax Excl) | D12: Tax | E12: Subtotal (Tax Incl)
A13: 1. Control Room Space Re-Engineering (fixtures & fittings) | B13: 0.08 | C13: =$B$7*B13 -> 1167753.2 | D13: =C13*$B$6 -> 175162.98 | E13: =C13+D13 -> 1342916.2
A14: 2. UAV Procurement (long- & short-range) | B14: 0.18 | C14: =$B$7*B14 -> 2627444.7 | D14: =C14*$B$6 -> 394116.7 | E14: =C14+D14 -> 3021561.4
A15: 3. Software Development and Deployment | B15: 0.3 | C15: =$B$7*B15 -> 4379074.4 | D15: =C15*$B$6 -> 656861.17 | E15: =C15+D15 -> 5035935.6
A16: 4. Vehicle Procurement (pick-ups) | B16: 0.1 | C16: =$B$7*B16 -> 1459691.5 | D16: =C16*$B$6 -> 218953.72 | E16: =C16+D16 -> 1678645.2
A17: 5. Training and Capacity Building | B17: 0.08 | C17: =$B$7*B17 -> 1167753.2 | D17: =C17*$B$6 -> 175162.98 | E17: =C17+D17 -> 1342916.2
A18: 6. Project Management | B18: 0.16 | C18: =$B$7*B18 -> 2335506.4 | D18: =C18*$B$6 -> 350325.95 | E18: =C18+D18 -> 2685832.3
A19: 7. Contingency | B19: 0.1 | C19: =$B$7*B19 -> 1459691.5 | D19: =C19*$B$6 -> 218953.72 | E19: =C19+D19 -> 1678645.2
A20: TOTAL | B20: =SUM(B13:B19) -> 1 | C20: =SUM(C13:C19) -> 14596915 | D20: =SUM(D13:D19) -> 2189537.2 | E20: =SUM(E13:E19) -> 16786452
A21: Check — Allocation % must equal 100% | B21: =IF(ROUND(B20,4)=1,"OK ✓","CHECK — adjust %") -> OK ✓
A23: LEGEND
A24: Blue text / yellow fill = editable input cell
A25: Black text = formula (auto-calculated — do not overwrite)
A26: Green text = link pulled in from this Assumptions sheet on the section tabs

Sheet 1. Control Room
A1: 1. Control Room Space Re-Engineering
A2: Fixtures & fittings to convert GNGC's existing control room into the GasGuard Fusion command centre — unified dashboard, video wall, and secure workstations for control-room and integrity staff.
A4: Section Subtotal (Tax Exclusive) — linked from Assumptions | B4: =Assumptions!C13 -> 1167753.2
A5: Section Subtotal (Tax Inclusive) — linked from Assumptions | B5: =Assumptions!E13 -> 1342916.2
A6: Effective Tax Rate — linked from Assumptions | B6: =Assumptions!$B$6 -> 0.15
A7: % of Total Contract Value (Tax Incl.) | B7: =B5/Assumptions!$B$5 -> 0.08
A8: LINE-ITEM DETAIL (Weight % is editable and must sum to 100%)
A9: Line Item | B9: Weight % within Section | C9: Amount (Tax Excl) | D9: Tax | E9: Amount (Tax Incl) | F9: Notes
A10: Control Room Civil & Electrical Re-Engineering | B10: 0.3 | C10: =$B$4*B10 -> 350325.95 | D10: =C10*$B$6 -> 52548.893 | E10: =C10+D10 -> 402874.85 | F10: Partitioning, cabling, raised flooring, power re-distribution
A11: Operator Workstations & Ergonomic Furniture | B11: 0.2 | C11: =$B$4*B11 -> 233550.64 | D11: =C11*$B$6 -> 35032.595 | E11: =C11+D11 -> 268583.23 | F11: Multi-monitor consoles for control-room operators
A12: Video Wall / Large-Format Display System | B12: 0.2 | C12: =$B$4*B12 -> 233550.64 | D12: =C12*$B$6 -> 35032.595 | E12: =C12+D12 -> 268583.23 | F12: Unified GasGuard Fusion dashboard display
A13: HVAC, Lighting & Power Backup Upgrade | B13: 0.15 | C13: =$B$4*B13 -> 175162.98 | D13: =C13*$B$6 -> 26274.447 | E13: =C13+D13 -> 201437.42 | F13: Includes UPS sizing for 24/7 monitoring operations
A14: Access Control & Physical Security Fit-Out | B14: 0.15 | C14: =$B$4*B14 -> 175162.98 | D14: =C14*$B$6 -> 26274.447 | E14: =C14+D14 -> 201437.42 | F14: Biometric/card access to the re-engineered space
A15: SECTION TOTAL | B15: =SUM(B10:B14) -> 1 | C15: =SUM(C10:C14) -> 1167753.2 | D15: =SUM(D10:D14) -> 175162.98 | E15: =SUM(E10:E14) -> 1342916.2
A16: Check — Weight % sums to 100% and Section Total ties to Assumptions | B16: =IF(ROUND(B15,4)=1,"OK ✓","CHECK") -> OK ✓ | E16: =IF(ROUND(E15-B5,2)=0,"OK ✓","CHECK") -> OK ✓

Sheet 2. UAV Procurement
A1: 2. UAV Procurement (Long- & Short-Range)
A2: Unmanned aerial platforms supporting GasGuard SkyView aerial screening — long-range coverage of the WAGP corridor and upstream feeder network, short-range rapid response to flagged incidents.
A4: Section Subtotal (Tax Exclusive) — linked from Assumptions | B4: =Assumptions!C14 -> 2627444.7
A5: Section Subtotal (Tax Inclusive) — linked from Assumptions | B5: =Assumptions!E14 -> 3021561.4
A6: Effective Tax Rate — linked from Assumptions | B6: =Assumptions!$B$6 -> 0.15
A7: % of Total Contract Value (Tax Incl.) | B7: =B5/Assumptions!$B$5 -> 0.18
A8: LINE-ITEM DETAIL (Weight % is editable and must sum to 100%)
A9: Line Item | B9: Weight % within Section | C9: Amount (Tax Excl) | D9: Tax | E9: Amount (Tax Incl) | F9: Notes
A10: Long-Range Fixed-Wing UAV Units (2) – corridor & basin screening | B10: 0.35 | C10: =$B$4*B10 -> 919605.63 | D10: =C10*$B$6 -> 137940.84 | E10: =C10+D10 -> 1057546.5 | F10: Extended-endurance platforms for WAGP corridor coverage
A11: Short-Range Multirotor UAV Units (4) – site & incident response | B11: 0.2 | C11: =$B$4*B11 -> 525488.93 | D11: =C11*$B$6 -> 78823.34 | E11: =C11+D11 -> 604312.27 | F11: Rapid-deployment units for flagged sites
A12: UAV Sensor Payloads (Methane/Gas Detection & Thermal Imaging) | B12: 0.25 | C12: =$B$4*B12 -> 656861.17 | D12: =C12*$B$6 -> 98529.175 | E12: =C12+D12 -> 755390.34 | F12: Complements GasGuard SkyView satellite screening
A13: Ground Control Stations & Communications Equipment | B13: 0.12 | C13: =$B$4*B13 -> 315293.36 | D13: =C13*$B$6 -> 47294.004 | E13: =C13+D13 -> 362587.36
A14: Spare Parts, Maintenance Kit & Charging Infrastructure | B14: 0.08 | C14: =$B$4*B14 -> 210195.57 | D14: =C14*$B$6 -> 31529.336 | E14: =C14+D14 -> 241724.91
A15: SECTION TOTAL | B15: =SUM(B10:B14) -> 1 | C15: =SUM(C10:C14) -> 2627444.7 | D15: =SUM(D10:D14) -> 394116.7 | E15: =SUM(E10:E14) -> 3021561.4
A16: Check — Weight % sums to 100% and Section Total ties to Assumptions | B16: =IF(ROUND(B15,4)=1,"OK ✓","CHECK") -> OK ✓ | E16: =IF(ROUND(E15-B5,2)=0,"OK ✓","CHECK") -> OK ✓

Sheet 3. Software Dev & Deploy
A1: 3. Software Development and Deployment
A2: Development and deployment of the GasGuard Suite software layer — Reconcile, Fusion, FiberWatch/TrackTrace analytics, MarkChain, and the control-room/mobile applications.
A4: Section Subtotal (Tax Exclusive) — linked from Assumptions | B4: =Assumptions!C15 -> 4379074.4
A5: Section Subtotal (Tax Inclusive) — linked from Assumptions | B5: =Assumptions!E15 -> 5035935.6
A6: Effective Tax Rate — linked from Assumptions | B6: =Assumptions!$B$6 -> 0.15
A7: % of Total Contract Value (Tax Incl.) | B7: =B5/Assumptions!$B$5 -> 0.3
A8: LINE-ITEM DETAIL (Weight % is editable and must sum to 100%)
A9: Line Item | B9: Weight % within Section | C9: Amount (Tax Excl) | D9: Tax | E9: Amount (Tax Incl) | F9: Notes
A10: GasGuard Reconcile – CPM Mass-Balance Software Development | B10: 0.2 | C10: =$B$4*B10 -> 875814.89 | D10: =C10*$B$6 -> 131372.23 | E10: =C10+D10 -> 1007187.1 | F10: API 1130 methodology, custody-point configuration
A11: GasGuard Fusion – AI/ML Anomaly-Detection Platform Development | B11: 0.25 | C11: =$B$4*B11 -> 1094768.6 | D11: =C11*$B$6 -> 164215.29 | E11: =C11+D11 -> 1258983.9 | F11: Trained on GNGC's own operating/incident data
A12: GasGuard FiberWatch & TrackTrace Analytics Modules | B12: 0.15 | C12: =$B$4*B12 -> 656861.17 | D12: =C12*$B$6 -> 98529.175 | E12: =C12+D12 -> 755390.34 | F12: DAS/AIS fusion; LPG fleet route analytics
A13: GasGuard MarkChain – Custody Audit-Trail Software | B13: 0.1 | C13: =$B$4*B13 -> 437907.44 | D13: =C13*$B$6 -> 65686.117 | E13: =C13+D13 -> 503593.56 | F13: Digital custody-transfer audit trail
A14: Control-Room Dashboard & Mobile App Development | B14: 0.12 | C14: =$B$4*B14 -> 525488.93 | D14: =C14*$B$6 -> 78823.34 | E14: =C14+D14 -> 604312.27 | F14: Field/enforcement mobile application
A15: Cloud Hosting, Data Infrastructure & Cybersecurity Implementation (Yr 1) | B15: 0.1 | C15: =$B$4*B15 -> 437907.44 | D15: =C15*$B$6 -> 65686.117 | E15: =C15+D15 -> 503593.56 | F15: OT/IT boundary hardening per Section 9 of the proposal
A16: System Integration & User Acceptance Testing | B16: 0.08 | C16: =$B$4*B16 -> 350325.95 | D16: =C16*$B$6 -> 52548.893 | E16: =C16+D16 -> 402874.85
A17: SECTION TOTAL | B17: =SUM(B10:B16) -> 1 | C17: =SUM(C10:C16) -> 4379074.4 | D17: =SUM(D10:D16) -> 656861.17 | E17: =SUM(E10:E16) -> 5035935.6
A18: Check — Weight % sums to 100% and Section Total ties to Assumptions | B18: =IF(ROUND(B17,4)=1,"OK ✓","CHECK") -> OK ✓ | E18: =IF(ROUND(E17-B5,2)=0,"OK ✓","CHECK") -> OK ✓

Sheet 4. Vehicle Procurement
A1: 4. Vehicle Procurement (Pick-Ups)
A2: Field vehicles supporting site survey, installation/commissioning, and ongoing enforcement and inspection activity across GNGC's network.
A4: Section Subtotal (Tax Exclusive) — linked from Assumptions | B4: =Assumptions!C16 -> 1459691.5
A5: Section Subtotal (Tax Inclusive) — linked from Assumptions | B5: =Assumptions!E16 -> 1678645.2
A6: Effective Tax Rate — linked from Assumptions | B6: =Assumptions!$B$6 -> 0.15
A7: % of Total Contract Value (Tax Incl.) | B7: =B5/Assumptions!$B$5 -> 0.1
A8: LINE-ITEM DETAIL (Weight % is editable and must sum to 100%)
A9: Line Item | B9: Weight % within Section | C9: Amount (Tax Excl) | D9: Tax | E9: Amount (Tax Incl) | F9: Notes
A10: 4x4 Double-Cab Pick-Up Trucks – Field Inspection & Enforcement (6 units) | B10: 0.65 | C10: =$B$4*B10 -> 948799.46 | D10: =C10*$B$6 -> 142319.92 | E10: =C10+D10 -> 1091119.4 | F10: Indicative fleet size; confirm final count in Phase 0
A11: Vehicle GPS/Telematics Fitting & Branding | B11: 0.15 | C11: =$B$4*B11 -> 218953.72 | D11: =C11*$B$6 -> 32843.058 | E11: =C11+D11 -> 251796.78
A12: Registration, Insurance & Roadworthy Certification (Year 1) | B12: 0.12 | C12: =$B$4*B12 -> 175162.98 | D12: =C12*$B$6 -> 26274.447 | E12: =C12+D12 -> 201437.42
A13: Vehicle Tools, Recovery & Safety Equipment | B13: 0.08 | C13: =$B$4*B13 -> 116775.32 | D13: =C13*$B$6 -> 17516.298 | E13: =C13+D13 -> 134291.62
A14: SECTION TOTAL | B14: =SUM(B10:B13) -> 1 | C14: =SUM(C10:C13) -> 1459691.5 | D14: =SUM(D10:D13) -> 218953.72 | E14: =SUM(E10:E13) -> 1678645.2
A15: Check — Weight % sums to 100% and Section Total ties to Assumptions | B15: =IF(ROUND(B14,4)=1,"OK ✓","CHECK") -> OK ✓ | E15: =IF(ROUND(E14-B5,2)=0,"OK ✓","CHECK") -> OK ✓

Sheet 5. Training & Capacity
A1: 5. Training and Capacity Building
A2: Structured knowledge transfer so GNGC's own teams can operate and extend the GasGuard platform independently, per the commitment in Section 6 of the proposal.
A4: Section Subtotal (Tax Exclusive) — linked from Assumptions | B4: =Assumptions!C17 -> 1167753.2
A5: Section Subtotal (Tax Inclusive) — linked from Assumptions | B5: =Assumptions!E17 -> 1342916.2
A6: Effective Tax Rate — linked from Assumptions | B6: =Assumptions!$B$6 -> 0.15
A7: % of Total Contract Value (Tax Incl.) | B7: =B5/Assumptions!$B$5 -> 0.08
A8: LINE-ITEM DETAIL (Weight % is editable and must sum to 100%)
A9: Line Item | B9: Weight % within Section | C9: Amount (Tax Excl) | D9: Tax | E9: Amount (Tax Incl) | F9: Notes
A10: Control Room Operator Training | B10: 0.25 | C10: =$B$4*B10 -> 291938.3 | D10: =C10*$B$6 -> 43790.744 | E10: =C10+D10 -> 335729.04
A11: Field & Enforcement Staff Training (incl. UAV Pilot Certification) | B11: 0.3 | C11: =$B$4*B11 -> 350325.95 | D11: =C11*$B$6 -> 52548.893 | E11: =C11+D11 -> 402874.85
A12: IT/OT Staff Technical Knowledge Transfer | B12: 0.25 | C12: =$B$4*B12 -> 291938.3 | D12: =C12*$B$6 -> 43790.744 | E12: =C12+D12 -> 335729.04
A13: GNGC Management & Executive Briefing Programme | B13: 0.2 | C13: =$B$4*B13 -> 233550.64 | D13: =C13*$B$6 -> 35032.595 | E13: =C13+D13 -> 268583.23
A14: SECTION TOTAL | B14: =SUM(B10:B13) -> 1 | C14: =SUM(C10:C13) -> 1167753.2 | D14: =SUM(D10:D13) -> 175162.98 | E14: =SUM(E10:E13) -> 1342916.2
A15: Check — Weight % sums to 100% and Section Total ties to Assumptions | B15: =IF(ROUND(B14,4)=1,"OK ✓","CHECK") -> OK ✓ | E15: =IF(ROUND(E14-B5,2)=0,"OK ✓","CHECK") -> OK ✓

Sheet 6. Project Management
A1: 6. Project Management
A2: In-country project leadership embedded alongside GNGC's integrity, IT/OT, and operations staff across the full engagement.
A4: Section Subtotal (Tax Exclusive) — linked from Assumptions | B4: =Assumptions!C18 -> 2335506.4
A5: Section Subtotal (Tax Inclusive) — linked from Assumptions | B5: =Assumptions!E18 -> 2685832.3
A6: Effective Tax Rate — linked from Assumptions | B6: =Assumptions!$B$6 -> 0.15
A7: % of Total Contract Value (Tax Incl.) | B7: =B5/Assumptions!$B$5 -> 0.16
A8: LINE-ITEM DETAIL (Weight % is editable and must sum to 100%)
A9: Line Item | B9: Weight % within Section | C9: Amount (Tax Excl) | D9: Tax | E9: Amount (Tax Incl) | F9: Notes
A10: Project Director (18-Month Engagement) | B10: 0.3 | C10: =$B$4*B10 -> 700651.91 | D10: =C10*$B$6 -> 105097.79 | E10: =C10+D10 -> 805749.7
A11: Local Project Management Team | B11: 0.25 | C11: =$B$4*B11 -> 583876.59 | D11: =C11*$B$6 -> 87581.489 | E11: =C11+D11 -> 671458.08
A12: Cybersecurity/OT Integration Coordination | B12: 0.2 | C12: =$B$4*B12 -> 467101.27 | D12: =C12*$B$6 -> 70065.191 | E12: =C12+D12 -> 537166.46
A13: In-Country SLA Support Mobilization (Year 1) | B13: 0.15 | C13: =$B$4*B13 -> 350325.95 | D13: =C13*$B$6 -> 52548.893 | E13: =C13+D13 -> 402874.85
A14: Reporting, Governance & Stakeholder Coordination | B14: 0.1 | C14: =$B$4*B14 -> 233550.64 | D14: =C14*$B$6 -> 35032.595 | E14: =C14+D14 -> 268583.23
A15: SECTION TOTAL | B15: =SUM(B10:B14) -> 1 | C15: =SUM(C10:C14) -> 2335506.4 | D15: =SUM(D10:D14) -> 350325.95 | E15: =SUM(E10:E14) -> 2685832.3
A16: Check — Weight % sums to 100% and Section Total ties to Assumptions | B16: =IF(ROUND(B15,4)=1,"OK ✓","CHECK") -> OK ✓ | E16: =IF(ROUND(E15-B5,2)=0,"OK ✓","CHECK") -> OK ✓

Sheet 7. Contingency
A1: 7. Contingency
A2: Master project-level contingency covering scope, schedule, and price risk across all budget sections.
A4: Section Subtotal (Tax Exclusive) — linked from Assumptions | B4: =Assumptions!C19 -> 1459691.5
A5: Section Subtotal (Tax Inclusive) — linked from Assumptions | B5: =Assumptions!E19 -> 1678645.2
A6: Effective Tax Rate — linked from Assumptions | B6: =Assumptions!$B$6 -> 0.15
A7: % of Total Contract Value (Tax Incl.) | B7: =B5/Assumptions!$B$5 -> 0.1
A8: LINE-ITEM DETAIL (Weight % is editable and must sum to 100%)
A9: Line Item | B9: Weight % within Section | C9: Amount (Tax Excl) | D9: Tax | E9: Amount (Tax Incl) | F9: Notes
A10: Master Project-Level Contingency | B10: 1 | C10: =$B$4*B10 -> 1459691.5 | D10: =C10*$B$6 -> 218953.72 | E10: =C10+D10 -> 1678645.2 | F10: Held centrally; drawn down only against approved change requests
A11: SECTION TOTAL | B11: =SUM(B10:B10) -> 1 | C11: =SUM(C10:C10) -> 1459691.5 | D11: =SUM(D10:D10) -> 218953.72 | E11: =SUM(E10:E10) -> 1678645.2
A12: Check — Weight % sums to 100% and Section Total ties to Assumptions | B12: =IF(ROUND(B11,4)=1,"OK ✓","CHECK") -> OK ✓ | E12: =IF(ROUND(E11-B5,2)=0,"OK ✓","CHECK") -> OK ✓
