Workbook

Sheet Cover
A1: GasGuard Suite — Integrated Budget Model
A2: Prepared by Smart Innovations Ghana Limited (SIGL) for Ghana National Gas Company (GNGC)
A3: CONFIDENTIAL — Prepared exclusively for GNGC evaluation purposes | July 2026
A6: How this workbook works
A7: This workbook contains a single, project-wide budget of GHS 16,000,000 (tax-inclusive), phased in line with Section 6 of the SIGL proposal (Phase 0 - Phase 3). All figures are driven from the Assumptions tab: change any blue cell there and every phase tab, plus the Summary tab, recalculates automatically.
A9: Tab | B9: Purpose
A10: Assumptions | B10: Master control tab. Set the total contract value, the effective tax rate, the % of budget allocated to each phase, and the % split of each phase across cost categories (hardware, software, professional services, training, project management, contingency). Also sets the illustrative Year 2+ support fee.
A11: Summary | B11: Roll-up of all four phases: tax-exclusive subtotal, tax, and tax-inclusive total per phase, reconciled against the Assumptions tab.
A12: Phase 0 - Diagnostic | B12: Joint diagnostic assessment (Weeks 1-6): infrastructure review, data review, site survey, business case.
A13: Phase 1 - Foundational | B13: Foundational modules (Months 2-8): GasGuard Reconcile, GasGuard FieldLink, core GasGuard Fusion dashboard.
A14: Phase 2 - Corridor-Fleet | B14: Corridor and fleet instrumentation (Months 6-14): GasGuard FiberWatch, GasGuard TrackTrace, GasGuard SkyView.
A15: Phase 3 - Marking-Fusion | B15: Product marking and full fusion (Months 12-18): GasGuard MarkChain and full AI/ML fusion-layer integration.
A17: Colour legend
A18: Blue text | B18: Editable input — safe to change.
A19: Black text | B19: Formula calculated within the same sheet — do not overtype.
A20: Green text | B20: Formula linked from another sheet (usually Assumptions) — do not overtype.
A22: Note on tax | B22: The effective rate combines VAT (15%), NHIL (2.5%) and GETFund (2.5%) on the same base, per Ghana's VAT Act, 2025 (Act 1151), effective 1 January 2026 (Ghana Revenue Authority). Adjust the rate in Assumptions!C8 if regulations change.

Sheet Assumptions
A1: GasGuard Suite — Master Budget Assumptions
A2: Ghana National Gas Company (GNGC) — Integrated Pipeline Monitoring, Loss-Prevention & Custody-Integrity Platform
A4: EDIT ONLY THE BLUE CELLS BELOW. All phase, category and summary totals recalculate automatically from these inputs.
A6: 1. CONTRACT VALUE & TAX
B7: Total Contract Value (Tax-Inclusive, GHS) | C7: 16000000
B8: Effective Tax Rate (VAT 15% + NHIL 2.5% + GETFund 2.5%, same base) | C8: 0.2
B9: Tax-Exclusive Contract Value (GHS) | C9: =C7/(1+C8) -> 13333333
B10: Total Tax Amount (GHS) | C10: =C7-C9 -> 2666666.7
A11: Source: Ghana Revenue Authority, VAT Act, 2025 (Act 1151), effective 1 January 2026 (combined VAT + NHIL + GETFund = 20.0% effective rate). https://gra.gov.gh/domestic-tax/tax-types/vat/
A13: 2. PHASE ALLOCATION (% of Tax-Exclusive Contract Value)
B14: Phase | C14: % Allocation | D14: Tax-Exclusive Amount (GHS) | E14: Tax (GHS) | F14: Tax-Inclusive Amount (GHS)
B15: Phase 0 - Diagnostic Assessment | C15: 0.03 | D15: =$C$9*C15 -> 400000 | E15: =D15*$C$8 -> 80000 | F15: =D15+E15 -> 480000
B16: Phase 1 - Foundational Modules | C16: 0.32 | D16: =$C$9*C16 -> 4266666.7 | E16: =D16*$C$8 -> 853333.33 | F16: =D16+E16 -> 5120000
B17: Phase 2 - Corridor & Fleet Instrumentation | C17: 0.4 | D17: =$C$9*C17 -> 5333333.3 | E17: =D17*$C$8 -> 1066666.7 | F17: =D17+E17 -> 6400000
B18: Phase 3 - Product Marking & Full Fusion | C18: 0.25 | D18: =$C$9*C18 -> 3333333.3 | E18: =D18*$C$8 -> 666666.67 | F18: =D18+E18 -> 4000000
B19: TOTAL | C19: =SUM(C15:C18) -> 1 | D19: =SUM(D15:D18) -> 13333333 | E19: =SUM(E15:E18) -> 2666666.7 | F19: =SUM(F15:F18) -> 16000000
B20: Check: % Allocation sums to 100%? | C20: =IF(ROUND(C19,4)=1,"OK","MISMATCH") -> OK
A22: 3. COST CATEGORY ALLOCATION (% within each Phase — each column must total 100%)
B23: Cost Category | C23: Phase 0 | D23: Phase 1 | E23: Phase 2 | F23: Phase 3
B24: Hardware & Equipment Procurement | C24: 0 | D24: 0.25 | E24: 0.45 | F24: 0.15
B25: Software Licensing & Platform Integration | C25: 0 | D25: 0.35 | E25: 0.25 | F25: 0.35
B26: Professional Services & Implementation | C26: 0.55 | D26: 0.25 | E26: 0.2 | F26: 0.3
B27: Training & Knowledge Transfer | C27: 0.1 | D27: 0.05 | E27: 0.04 | F27: 0.08
B28: Project Management & Governance | C28: 0.2 | D28: 0.05 | E28: 0.04 | F28: 0.07
B29: Contingency | C29: 0.15 | D29: 0.05 | E29: 0.02 | F29: 0.05
B30: TOTAL (must equal 100%) | C30: =SUM(C24:C29) -> 1 | D30: =SUM(D24:D29) -> 1 | E30: =SUM(E24:E29) -> 1 | F30: =SUM(F24:F29) -> 1
A32: 4. YEAR 2+ ANNUAL SUPPORT & SUBSCRIPTION (illustrative — NOT included in the GHS 16,000,000 Phase 0-3 total)
B33: Annual Support Fee (% of cumulative Software Licensing value) | C33: 0.18
B34: Cumulative Software Licensing Value (Tax-Exclusive, GHS) | C34: =D15*C25+D16*D25+D17*E25+D18*F25 -> 3993333.3
B35: Annual Support Fee (Tax-Exclusive, GHS) | C35: =C34*C33 -> 718800
B36: Annual Support Fee (Tax-Inclusive, GHS) | C36: =C35*(1+$C$8) -> 862560
A37: Recommended commercial structure per proposal Section 8: one-time integration/implementation fees (Phases 0-3 above) plus an annual software-and-support subscription beginning in Year 2, following Phase 1 go-live.

Sheet Summary
A1: GasGuard Suite — Budget Summary
A2: Roll-up of all phases, reconciled against the Assumptions tab. Change inputs on the Assumptions tab; this sheet updates automatically.
B4: Phase | C4: Subtotal (Tax-Excl, GHS) | D4: Tax (GHS) | E4: Total (Tax-Incl, GHS) | F4: % of Project
B5: Phase 0 - Diagnostic Assessment | C5: ='Phase 0 - Diagnostic'!D19 -> 400000 | D5: ='Phase 0 - Diagnostic'!D20 -> 80000 | E5: ='Phase 0 - Diagnostic'!D21 -> 480000 | F5: =E5/$E$9 -> 0.03
B6: Phase 1 - Foundational Modules | C6: ='Phase 1 - Foundational'!D25 -> 4266666.7 | D6: ='Phase 1 - Foundational'!D26 -> 853333.33 | E6: ='Phase 1 - Foundational'!D27 -> 5120000 | F6: =E6/$E$9 -> 0.32
B7: Phase 2 - Corridor & Fleet Instrumentation | C7: ='Phase 2 - Corridor-Fleet'!D26 -> 5333333.3 | D7: ='Phase 2 - Corridor-Fleet'!D27 -> 1066666.7 | E7: ='Phase 2 - Corridor-Fleet'!D28 -> 6400000 | F7: =E7/$E$9 -> 0.4
B8: Phase 3 - Product Marking & Full Fusion | C8: ='Phase 3 - Marking-Fusion'!D23 -> 3333333.3 | D8: ='Phase 3 - Marking-Fusion'!D24 -> 666666.67 | E8: ='Phase 3 - Marking-Fusion'!D25 -> 4000000 | F8: =E8/$E$9 -> 0.25
B9: GRAND TOTAL | C9: =SUM(C5:C8) -> 13333333 | D9: =SUM(D5:D8) -> 2666666.7 | E9: =SUM(E5:E8) -> 16000000 | F9: =E9/E9 -> 1
B11: Check: Grand Total = Assumptions Total Contract Value? | E11: =IF(ROUND(E9-Assumptions!$C$7,2)=0,"OK","MISMATCH") -> OK
A13: COST CATEGORY ROLL-UP (across all phases, Tax-Exclusive GHS)
B14: Cost Category | C14: Total (Tax-Excl, GHS)
B15: Hardware & Equipment Procurement | C15: =Assumptions!D15*Assumptions!C24+Assumptions!D16*Assumptions!D24+Assumptions!D17*Assumptions!E24+Assumptions!D18*Assumptions!F24 -> 3966666.7
B16: Software Licensing & Platform Integration | C16: =Assumptions!D15*Assumptions!C25+Assumptions!D16*Assumptions!D25+Assumptions!D17*Assumptions!E25+Assumptions!D18*Assumptions!F25 -> 3993333.3
B17: Professional Services & Implementation | C17: =Assumptions!D15*Assumptions!C26+Assumptions!D16*Assumptions!D26+Assumptions!D17*Assumptions!E26+Assumptions!D18*Assumptions!F26 -> 3353333.3
B18: Training & Knowledge Transfer | C18: =Assumptions!D15*Assumptions!C27+Assumptions!D16*Assumptions!D27+Assumptions!D17*Assumptions!E27+Assumptions!D18*Assumptions!F27 -> 733333.33
B19: Project Management & Governance | C19: =Assumptions!D15*Assumptions!C28+Assumptions!D16*Assumptions!D28+Assumptions!D17*Assumptions!E28+Assumptions!D18*Assumptions!F28 -> 740000
B20: Contingency | C20: =Assumptions!D15*Assumptions!C29+Assumptions!D16*Assumptions!D29+Assumptions!D17*Assumptions!E29+Assumptions!D18*Assumptions!F29 -> 546666.67
B21: TOTAL | C21: =SUM(C15:C20) -> 13333333

Sheet Phase 0 - Diagnostic
A1: PHASE 0 — Joint Diagnostic Assessment
A2: Weeks 1-6 | SCADA/metering/reporting review, internal loss-data review (NDA), site survey, GNGC-specific business case
B4: Phase Total (Tax-Exclusive, GHS) | C4: =Assumptions!D15 -> 400000
B5: Effective Tax Rate | C5: =Assumptions!$C$8 -> 0.2
B6: Phase Total (Tax-Inclusive, GHS) | C6: =Assumptions!F15 -> 480000
B8: Cost Category / Line Item | C8: Weight | D8: Amount (Tax-Excl, GHS)
B9: PROFESSIONAL SERVICES & IMPLEMENTATION | C9: =Assumptions!C26 -> 0.55 | D9: =$C$4*C9 -> 220000
B10: Site survey & data review (Atuabo plant, offshore WAGP corridor, LPG routes) | C10: 0.5 | D10: =$D$9*C10 -> 110000
B11: SCADA / metering infrastructure review | C11: 0.3 | D11: =$D$9*C11 -> 66000
B12: Business case & prioritized deployment plan development | C12: 0.2 | D12: =$D$9*C12 -> 44000
B13: PROJECT MANAGEMENT & GOVERNANCE | C13: =Assumptions!C28 -> 0.2 | D13: =$C$4*C13 -> 80000
B14: Phase 0 project coordination & GNGC liaison | C14: 1 | D14: =$D$13*C14 -> 80000
B15: TRAINING & KNOWLEDGE TRANSFER | C15: =Assumptions!C27 -> 0.1 | D15: =$C$4*C15 -> 40000
B16: Kickoff workshops with GNGC technical, integrity & IT/OT teams | C16: 1 | D16: =$D$15*C16 -> 40000
B17: CONTINGENCY | C17: =Assumptions!C29 -> 0.15 | D17: =$C$4*C17 -> 60000
B18: Contingency reserve | C18: 1 | D18: =$D$17*C18 -> 60000
B19: SUBTOTAL (Tax-Exclusive, GHS) | D19: =D9+D13+D15+D17 -> 400000
B20: Tax (Effective Rate) | D20: =D19*$C$5 -> 80000
B21: TOTAL (Tax-Inclusive, GHS) | D21: =D19+D20 -> 480000
B23: Check vs Assumptions Phase Total | D23: =IF(ROUND(D21-$C$6,2)=0,"OK","MISMATCH") -> OK

Sheet Phase 1 - Foundational
A1: PHASE 1 — Foundational Modules
A2: Months 2-8 | GasGuard Reconcile across custody-transfer points, GasGuard FieldLink at priority sites, core GasGuard Fusion dashboard
B4: Phase Total (Tax-Exclusive, GHS) | C4: =Assumptions!D16 -> 4266666.7
B5: Effective Tax Rate | C5: =Assumptions!$C$8 -> 0.2
B6: Phase Total (Tax-Inclusive, GHS) | C6: =Assumptions!F16 -> 5120000
B8: Cost Category / Line Item | C8: Weight | D8: Amount (Tax-Excl, GHS)
B9: HARDWARE & EQUIPMENT PROCUREMENT | C9: =Assumptions!D24 -> 0.25 | D9: =$C$4*C9 -> 1066666.7
B10: IoT LPWAN / cellular sensors & gateways (GasGuard FieldLink) | C10: 0.7 | D10: =$D$9*C10 -> 746666.67
B11: Metering interface / integration hardware (GasGuard Reconcile) | C11: 0.3 | D11: =$D$9*C11 -> 320000
B12: SOFTWARE LICENSING & PLATFORM INTEGRATION | C12: =Assumptions!D25 -> 0.35 | D12: =$C$4*C12 -> 1493333.3
B13: GasGuard Reconcile (CPM mass-balance) licensing & configuration | C13: 0.45 | D13: =$D$12*C13 -> 672000
B14: GasGuard Fusion core dashboard build | C14: 0.4 | D14: =$D$12*C14 -> 597333.33
B15: SCADA / telemetry data-integration connectors | C15: 0.15 | D15: =$D$12*C15 -> 224000
B16: PROFESSIONAL SERVICES & IMPLEMENTATION | C16: =Assumptions!D26 -> 0.25 | D16: =$C$4*C16 -> 1066666.7
B17: Field deployment & commissioning | C17: 0.6 | D17: =$D$16*C17 -> 640000
B18: Systems integration & testing | C18: 0.4 | D18: =$D$16*C18 -> 426666.67
B19: TRAINING & KNOWLEDGE TRANSFER | C19: =Assumptions!D27 -> 0.05 | D19: =$C$4*C19 -> 213333.33
B20: Control-room & field-staff training | C20: 1 | D20: =$D$19*C20 -> 213333.33
B21: PROJECT MANAGEMENT & GOVERNANCE | C21: =Assumptions!D28 -> 0.05 | D21: =$C$4*C21 -> 213333.33
B22: Phase 1 project management | C22: 1 | D22: =$D$21*C22 -> 213333.33
B23: CONTINGENCY | C23: =Assumptions!D29 -> 0.05 | D23: =$C$4*C23 -> 213333.33
B24: Contingency reserve | C24: 1 | D24: =$D$23*C24 -> 213333.33
B25: SUBTOTAL (Tax-Exclusive, GHS) | D25: =D9+D12+D16+D19+D21+D23 -> 4266666.7
B26: Tax (Effective Rate) | D26: =D25*$C$5 -> 853333.33
B27: TOTAL (Tax-Inclusive, GHS) | D27: =D25+D26 -> 5120000
B29: Check vs Assumptions Phase Total | D29: =IF(ROUND(D27-$C$6,2)=0,"OK","MISMATCH") -> OK

Sheet Phase 2 - Corridor-Fleet
A1: PHASE 2 — Corridor & Fleet Instrumentation
A2: Months 6-14 | GasGuard FiberWatch on the offshore WAGP corridor, GasGuard TrackTrace on the LPG bulk-vehicle fleet, GasGuard SkyView onboarding
B4: Phase Total (Tax-Exclusive, GHS) | C4: =Assumptions!D17 -> 5333333.3
B5: Effective Tax Rate | C5: =Assumptions!$C$8 -> 0.2
B6: Phase Total (Tax-Inclusive, GHS) | C6: =Assumptions!F17 -> 6400000
B8: Cost Category / Line Item | C8: Weight | D8: Amount (Tax-Excl, GHS)
B9: HARDWARE & EQUIPMENT PROCUREMENT | C9: =Assumptions!E24 -> 0.45 | D9: =$C$4*C9 -> 2400000
B10: Fiber-optic DAS interrogator units & cabling (GasGuard FiberWatch) | C10: 0.55 | D10: =$D$9*C10 -> 1320000
B11: Tamper-evident flow meters & GPS telematics units (GasGuard TrackTrace) | C11: 0.3 | D11: =$D$9*C11 -> 720000
B12: Satellite imagery subscription setup (GasGuard SkyView) | C12: 0.15 | D12: =$D$9*C12 -> 360000
B13: SOFTWARE LICENSING & PLATFORM INTEGRATION | C13: =Assumptions!E25 -> 0.25 | D13: =$C$4*C13 -> 1333333.3
B14: DAS analytics & AIS vessel-tracking fusion | C14: 0.4 | D14: =$D$13*C14 -> 533333.33
B15: TrackTrace fleet-management software | C15: 0.35 | D15: =$D$13*C15 -> 466666.67
B16: SkyView satellite data integration | C16: 0.25 | D16: =$D$13*C16 -> 333333.33
B17: PROFESSIONAL SERVICES & IMPLEMENTATION | C17: =Assumptions!E26 -> 0.2 | D17: =$C$4*C17 -> 1066666.7
B18: Offshore corridor installation & commissioning | C18: 0.5 | D18: =$D$17*C18 -> 533333.33
B19: LPG bulk-fleet instrumentation rollout | C19: 0.5 | D19: =$D$17*C19 -> 533333.33
B20: TRAINING & KNOWLEDGE TRANSFER | C20: =Assumptions!E27 -> 0.04 | D20: =$C$4*C20 -> 213333.33
B21: Enforcement & field-team training | C21: 1 | D21: =$D$20*C21 -> 213333.33
B22: PROJECT MANAGEMENT & GOVERNANCE | C22: =Assumptions!E28 -> 0.04 | D22: =$C$4*C22 -> 213333.33
B23: Phase 2 project management | C23: 1 | D23: =$D$22*C23 -> 213333.33
B24: CONTINGENCY | C24: =Assumptions!E29 -> 0.02 | D24: =$C$4*C24 -> 106666.67
B25: Contingency reserve | C25: 1 | D25: =$D$24*C25 -> 106666.67
B26: SUBTOTAL (Tax-Exclusive, GHS) | D26: =D9+D13+D17+D20+D22+D24 -> 5333333.3
B27: Tax (Effective Rate) | D27: =D26*$C$5 -> 1066666.7
B28: TOTAL (Tax-Inclusive, GHS) | D28: =D26+D27 -> 6400000
B30: Check vs Assumptions Phase Total | D30: =IF(ROUND(D28-$C$6,2)=0,"OK","MISMATCH") -> OK

Sheet Phase 3 - Marking-Fusion
A1: PHASE 3 — Product Marking & Full Fusion
A2: Months 12-18 | GasGuard MarkChain rollout with the NPA's Petroleum Product Marking Scheme, full AI fusion-layer integration
B4: Phase Total (Tax-Exclusive, GHS) | C4: =Assumptions!D18 -> 3333333.3
B5: Effective Tax Rate | C5: =Assumptions!$C$8 -> 0.2
B6: Phase Total (Tax-Inclusive, GHS) | C6: =Assumptions!F18 -> 4000000
B8: Cost Category / Line Item | C8: Weight | D8: Amount (Tax-Excl, GHS)
B9: HARDWARE & EQUIPMENT PROCUREMENT | C9: =Assumptions!F24 -> 0.15 | D9: =$C$4*C9 -> 500000
B10: Product-marking / tracer dosing equipment | C10: 1 | D10: =$D$9*C10 -> 500000
B11: SOFTWARE LICENSING & PLATFORM INTEGRATION | C11: =Assumptions!F25 -> 0.35 | D11: =$C$4*C11 -> 1166666.7
B12: GasGuard MarkChain digital custody audit trail | C12: 0.5 | D12: =$D$11*C12 -> 583333.33
B13: Full AI/ML fusion-layer integration & model refinement | C13: 0.5 | D13: =$D$11*C13 -> 583333.33
B14: PROFESSIONAL SERVICES & IMPLEMENTATION | C14: =Assumptions!F26 -> 0.3 | D14: =$C$4*C14 -> 1000000
B15: NPA coordination & marking-scheme rollout | C15: 0.4 | D15: =$D$14*C15 -> 400000
B16: Full-network fusion integration & testing | C16: 0.6 | D16: =$D$14*C16 -> 600000
B17: TRAINING & KNOWLEDGE TRANSFER | C17: =Assumptions!F27 -> 0.08 | D17: =$C$4*C17 -> 266666.67
B18: Knowledge transfer & handover to GNGC operations team | C18: 1 | D18: =$D$17*C18 -> 266666.67
B19: PROJECT MANAGEMENT & GOVERNANCE | C19: =Assumptions!F28 -> 0.07 | D19: =$C$4*C19 -> 233333.33
B20: Phase 3 project management | C20: 1 | D20: =$D$19*C20 -> 233333.33
B21: CONTINGENCY | C21: =Assumptions!F29 -> 0.05 | D21: =$C$4*C21 -> 166666.67
B22: Contingency reserve | C22: 1 | D22: =$D$21*C22 -> 166666.67
B23: SUBTOTAL (Tax-Exclusive, GHS) | D23: =D9+D11+D14+D17+D19+D21 -> 3333333.3
B24: Tax (Effective Rate) | D24: =D23*$C$5 -> 666666.67
B25: TOTAL (Tax-Inclusive, GHS) | D25: =D23+D24 -> 4000000
B27: Check vs Assumptions Phase Total | D27: =IF(ROUND(D25-$C$6,2)=0,"OK","MISMATCH") -> OK

Sheet Support-Subscription (Yr2+)
A1: Year 2+ Annual Support & Subscription (Illustrative)
A2: NOT part of the GHS 16,000,000 Phase 0-3 project total — a recommended recurring commercial structure per proposal Section 8.
B4: Cumulative Software Licensing Value (Tax-Exclusive, GHS) | C4: =Assumptions!C34 -> 3993333.3
B5: Annual Support Fee Rate (% of Software Licensing value) | C5: =Assumptions!C33 -> 0.18
B6: Annual Support Fee (Tax-Exclusive, GHS) | C6: =Assumptions!C35 -> 718800
B7: Effective Tax Rate | C7: =Assumptions!$C$8 -> 0.2
B8: Annual Support Fee (Tax-Inclusive, GHS) | C8: =Assumptions!C36 -> 862560
A10: This fee is recommended to begin in Year 2, following Phase 1 go-live, and covers the GasGuard Fusion platform, dashboard, and AI/ML model maintenance across all deployed modules. Third-party hardware maintenance/renewal (fiber interrogators, satellite subscriptions, IoT device replacement) is separate and to be defined jointly during Phase 0, per proposal Section 8.
